Workbook

Sheet Sheet1
A1: Grasmere Farm Manual
A2: Kitchen KPI Weekly Summary Sheet W/C
B3: COST PRiCE | C3: WEEKLY PREPPED TOTAL | D3: POINT VALUE | E3: POINTS TOTAL | F3: STOCK VALUE TOTAL
A4: MEAT PIES SMALL
A5: Steak | B5: ='Steak Pie v2'!D66 -> 1.423461 | D5: 1
A6: Steak & Ale | B6: ='Steak & Ale Pie'!D56 -> #NAME? | D6: 1
A7: Steak & Kidney | B7: ='Steak & Kidney Pie'!D52 -> 1.5362969 | D7: 1
A8: Steak & Stilton | B8: ='Steak & Stilton Pie'!D53 -> 1.6345876
A9: Chicken & Ham | B9: ='C&H Pie'!D49 -> 1.2106156 | D9: 1
A10: Chicken & Chorizo | B10: ='C&C Pie'!D62 -> 1.2049576 | D10: 1
A11: Chicken & Bacon with Stilton | B11: ='C&S Pie'!D52 -> 1.2636383 | D11: 1
A12: Pulled Pork, Cider & Mustard | B12: ='Pulled Pork Pie'!D50 -> 1.3805483 | D12: 1
A13: Ham Hock, Cider & Tarragon | B13: ='Ham Hock Pie'!D52 -> 1.2270388 | D13: 1
A14: TOTAL
A16: MEAT PIES MEDIUM
A17: Steak | B17: ='Steak Pie v2'!I66 -> 2.6404446 | D17: 2
A18: Steak & Ale | B18: ='Steak & Ale Pie'!I56 -> #REF! | D18: 2
A19: Steak & Kidney | B19: ='Steak & Kidney Pie'!I52 -> 2.5079359 | D19: 2
A20: Steak & Stilton | B20: ='Steak & Stilton Pie'!I53 -> 2.7026668
A21: Chicken & Ham | B21: ='C&H Pie'!I50 -> 2.4726485 | D21: 2
A22: Chicken & Chorizo | B22: ='C&C Pie'!I62 -> 1.8928079 | D22: 2
A23: Chicken & Bacon with Stilton | B23: ='C&S Pie'!I52 -> 2.0032005 | D23: 2
A24: Pulled Pork, Cider & Mustard | B24: ='Pulled Pork Pie'!I50 -> 2.2361144 | D24: 2
A25: Ham Hock, Cider & Tarragon | B25: ='Ham Hock Pie'!I52 -> 2.1971121 | D25: 2
A26: TOTAL
A28: MEAT PIES LARGE
A29: Steak | B29: ='Steak Pie v2'!N54 -> 5.3284461 | D29: 3
A30: Steak & Ale | B30: ='Steak & Ale Pie'!N40 -> 5.3580408 | D30: 3
A31: Steak & Kidney | B31: ='Steak & Kidney Pie'!N37 -> 5.0774503 | D31: 3
A32: Chicken & Ham | B32: ='Steak & Stilton Pie'!I65 -> 0 | D32: 3
A33: Chicken & Chorizo | B33: ='C&H Pie'!I62 -> 0 | D33: 3
A34: Chicken & Bacon with Stilton | B34: ='C&C Pie'!I74 -> 0 | D34: 3
A35: Pulled Pork, Cider & Mustard | B35: ='C&S Pie'!I64 -> 0 | D35: 3
A36: Ham Hock, Cider & Tarragon | B36: ='Pulled Pork Pie'!I62 -> 0 | D36: 3
A37: TOTAL | B37: ='Ham Hock Pie'!I64 -> 0
A39: PORK PIES
A40: 3lb | D40: 6
A41: 2lb | D41: 3
A42: Medium | D42: 1
A43: Small | D43: 1
A44: Mini lided | D44: 1
A45: Mini open | D45: 0.5
A46: Medium Stilton | D46: 1
A47: Small Stilton | D47: 1
A48: Hunters Pie | D48: 1
A49: TOTAL
A51: SAUSAGE ROLLS & PUFFS
A52: Small Sausage Roll Box of 60 | D52: 0.125
A53: Jumbo Sausage Roll Box of 48 | D53: 0.1
A54: Flavoured Sausage Roll Box of 32 | D54: 0.1
A55: Small Sausage Roll Tray of 130 Cooked 24 | D55: 0.125
A56: Jumbo Sausage Roll Tray of 110 Cooked 4 | D56: 0.1
A57: Buffet Sausage Rolls (30's) | D57: 0.05
A58: Chorizo Puff | D58: 1
A59: Bacon Puff | D59: 1
A60: Onion Puff | D60: 1
A61: TOTAL
A63: OTHER
A64: Black Budding batch of 185 | D64: 20
A65: Faggots batch of 150 Cooked 60 | D65: 0.5
A66: Haslet 1lb | D66: 1
A67: Haslet 6lb | D67: 2
A68: Meatballs trays of 60 | D68: 0.1
A69: Scotch Eggs trays of 64 | D69: 1.5
A70: Bacon Eggs trays of 64 | D70: 1.5
A71: Crackles | D71: 0.1
A72: ROM jars (20) | D72: 2
A73: Chilli ROM jars (20) | D73: 2
A74: ROM/Chilli Batch | D74: 20
A75: Ham | D75: 2
... A80: Bratwurst | D80: 0.25
A81: TOTAL
A83: MEAT PIE BASES
A84: Large | D84: 0.5
A85: Medium | D85: 0.5
A86: Small | D86: 0.5
A87: TOTAL

Sheet Ingredient Cost
A1: Kitchen Ingredient Costs
A2: Change info in yellow boxes
H3: Labour | J3: 20 | K3: per hour
A4: INGREDIENT | D4: COST | E4: PER
A5: PASTRY
A6: Fat/Butter/Lard | D6: 2.06 | E6: kg
A7: Flour | D7: 0.62 | E7: kg
A8: Salt | D8: 0.54 | E8: kg
A9: Pukka Puffy Pastry | D9: 1.94 | E9: kg
A10: Pepper | D10: 11 | E10: kg
A11: Egg/Milk Wash | D11: 0.02 | E11: per egg wash | G11: 16 eggs | H11: 2.93 | I11: 0.11
A12: Milk | D12: 0.74 | E12: per kg | G12: 2 ltre milk | H12: 1.48
H13: 4.41
A14: OTHER
A15: Vegetable Oil | D15: 1.29 | E15: per kg
A16: Hard Boiled Eggs | D16: 0.27 | E16: each
A17: Crumb | D17: 1.26 | E17: kg
A18: Stilton | D18: 4.75 | E18: kg
A19: Lincolnshire Poacher | D19: 25.2 | E19: kg
A20: Chicken Sauce Mix | D20: 8.95 | E20: kg
A21: Steak & Kidney Sauce Mix | D21: 8.9 | E21: kg | F21: ?
A22: Tarigan | D22: 13 | E22: kg
A23: Powder Mustard | D23: 9.37 | E23: kg
A24: Grain Mustard | D24: 7.65 | E24: kg
A25: Mace | D25: 36.9 | E25: kg
A26: Barley | D26: 0.83 | E26: kg
A27: Rusk | D27: 1.18 | E27: kg | F27: 18 | G27: 20kg
A28: Cider | D28: 1.15 | E28: kg
A29: Ale | D29: 1.38 | E29: kg
A30: Brown Sugar | D30: 1.02 | E30: kg
A32: Red Onions | D32: 13.5 | E32: kg
A33: Brown Onions | E33: kg
A34: Red wine vinegar | D34: 5.27 | E34: kg
A35: Chilli Flakes | D35: 9.4 | E35: kg
A36: Spiced Fruit Chutney | D36: 7.01 | E36: kg
A37: Real Ale Chutney | D37: 7.43
A38: Cranberrys | D38: 4.08 | E38: kg
A39: Ox Runners | D39: 17.11 | E39: per bundle
A40: Pork Pie Seasoning
A41: Red wine | D41: 0.66
A42: Cheese (for Puff) | D42: 0.17 | E42: per slice | F42: £44.95 for 5kg
A43: Tomato Pureee | D43: 0.31 | E43: kg
A44: Mint Sauce | D44: 1.79 | E44: kg
A46: MEAT
A47: Pork Pie meat -mini | D47: 21.25 | E47: per batch of 259
A48: Pork Pie meat - small | D48: 52.5 | E48: per batch of 101
A49: Pork Pie meat - Med | D49: 52.5 | E49: per batch of 50
A50: Sausage Strip | D50: 56.25 | E50: per tray | F50: 45 strips per tray | G50: £1.17 per strip
A51: Flavoured Sausage Strip | D51: 58.45 | E51: per tray | F51: 45 strips per tray | G51: £1.30 per strip
A52: Premium Sausage strip | D52: 2 | E52: per strip | I52: double to 2 a strip
A53: Chorizo Sausage strip | D53: 1.25 | E53: per strip
A54: Scotch Egg Meat | D54: 0.34 | E54: each
A55: Bacon Egg Meat | D55: 0.34 | E55: each
A56: Haslet meat 6lb | B56: 6 per tray | D56: 61.36 | E56: per tray
A57: Haslet meat 1lb | B57: 36 per tray | D57: 61.36 | E57: per tray
A58: Hock | D58: 6
A59: Beef | D59: 8.5 | E59: kg | G59: 16.50 for bag of steak
A60: Lamb | D60: 11.71 | E60: kg
A61: Kidney bits | D61: 4 | E61: kg | G61: 2kg per bag | H61: seems expensive
A62: Chicken | D62: 7.55 | E62: kg
A63: Chorizo | D63: 6 | E63: kg
A64: Pulled Pork | D64: 7 | E64: kg | G64: Ordered per shoulder- £15 per shoulder?? Approx start weight 3kg per shoulder. 2.2kg approx pulled meat.
A65: Gammon | D65: 25 | E65: each | G65: needs changing!
A66: Gammon bits | D66: 4 | E66: kg | G66: 2kg bag
A67: Bratwurst | D67: 37.5 | E67: per batch of 60
A68: Bacon | D68: 3.32 | E68: kg
A69: Game Mix | E69: kg
A70: Meatballs | D70: 15 | E70: per basket | G70: 230 per basket
A71: Faggot Mix | D71: 15 | E71: per bucket | G71: 12 per bucket
A72: Back Fat | D72: 1.7 | E72: kg | G72: 12.5kg bucket
A73: Skin | D73: 10 | E73: per basket | G73: 10 per basket
A74: Trotter | E74: kg
A75: Head | E75: kg
A76: Brawn | G76: 7 per bucket
A77: Black Pudding Mix | D77: 4.42 | E77: kg
A78: Vail Fat | D78: 2.25 | E78: kg
A79: Gelatine | D79: 17.85 | E79: kg | H79: Haslets 100 per hour
A82: PACKAGING
A83: Ham Bags | D83: 0.07 | E83: each
A84: String
A86: Cooking Paper | D86: 0.12 | E86: each
A88: Rectangle Retail Box | D88: 0.09 | E88: each
A89: Small Square Retail Box | D89: 0.06 | E89: each
A90: Large Square Retail Box with window | D90: 0.22 | E90: each
A91: Tray (Meaballs) | D91: 0.06 | E91: each
A92: Tray (Faggots) | D92: 0.06 | E92: each
A93: Tray (Crackles) | D93: 0.04 | E93: each
A95: Foils Small | D95: 0.09 | E95: each
A96: Foils Medium | D96: 0.12 | E96: each
A97: Foils Large | D97: 0.2 | E97: each
A98: Pork Pie Foils Mini | D98: 0.02 | E98: each
A99: Pork Pie Foil Small | D99: 0.07 | E99: each
... A103: Lids | D103: 0.006 | E103: each
A105: Gold Vac Bag 225 x 200 Eurohole | D105: 0.07
A106: Ham Cook Bag | D106: 0.87
A108: Morrisons Case | D108: 0.2 | E108: each
A109: Multi product Case | D109: 0.27 | E109: each
A110: Label | D110: 0.01 | E110: each
A111: Pie wrap round Label | D111: 0.15 | E111: each
A113: Labour | B113: 20 | C113: per hour

Sheet Sliced Ham
A1: Grasmere Farm Manual
A2: Product Page
A3: Sliced Ham
A6: HAM 1
A7: Input / Calculation | D7: Cost Per pack | E7: No | F7: Cost | G7: Total | N7: Butchery charge | P7: £25 each
A8: Raw start weight (kg) | B8: 8.002 | D8: Ham 180g pack | E8: 22 | F8: =B13*0.18 -> 1.4330855 | G8: =E8*F8 -> 31.52788 | N8: Kitchen
A9: Raw cost per kg (£) | B9: 3.94 | D9: Cook Bag | E9: 1 | F9: ='Ingredient Cost'!D106 -> 0.87 | G9: =E9*F9 -> 0.87
A10: Total raw cost (£) | B10: =B8*B9 -> 31.52788 | D10: Packaging | E10: =E8*E9 -> 22 | F10: ='Ingredient Cost'!D105 -> 0.07 | G10: =E10*F10 -> 1.54
A11: Cooked saleable weight (kg) | B11: 4.412 | D11: Label | E11: 22 | F11: ='Ingredient Cost'!D110 -> 0.01 | G11: =E11*F11 -> 0.22
A12: Cooked yield (%) | B12: =B11/B8 -> 0.55136216 | D12: Labour | E12: 54 | F12: 20 | G12: =F12/E12 -> 0.37037037
A13: Cooked cost per kg (£) | B13: =B10/(B11-B14) -> 7.9615859
A14: Waste (kg) | B14: 0.452
A15: Waste % of cooked weight | B15: =B14/B11 -> 0.10244787 | D15: Cost per pack | G15: =SUM(G8:G12)/22 -> 1.5694659
A17: HAM 2
A18: Input / Calculation | D18: Cost Per pack | E18: No | F18: Cost | G18: Total
A19: Raw start weight (kg) | B19: 9.556 | D19: Ham 180g pack | E19: 25 | F19: =B24*0.18 -> 1.5060256 | G19: =E19*F19 -> 37.65064
A20: Raw cost per kg (£) | B20: 3.94 | D20: Cook Bag | E20: 1 | F20: =F9 -> 0.87 | G20: =E20*F20 -> 0.87
A21: Total raw cost (£) | B21: =B19*B20 -> 37.65064 | D21: Packaging | E21: =E19*E20 -> 25 | F21: =F10 -> 0.07 | G21: =E21*F21 -> 1.75
A22: Cooked saleable weight (kg) | B22: 4.944 | D22: Label | E22: 25 | F22: =F11 -> 0.01 | G22: =E22*F22 -> 0.25
A23: Cooked yield (%) | B23: =B22/B19 -> 0.51737129 | D23: Labour | E23: 54 | F23: 20 | G23: =F23/E23 -> 0.37037037
A24: Cooked cost per kg (£) | B24: =B21/(B22-B25) -> 8.3668089
A25: Waste (kg) | B25: 0.444
A26: Waste % of cooked weight | B26: =B25/B22 -> 0.089805825 | D26: Cost per pack | G26: =SUM(G19:G23)/25 -> 1.6356404
A29: HAM 3
A30: Input / Calculation | D30: Cost Per pack | E30: No | F30: Cost | G30: Total
A31: Raw start weight (kg) | B31: 9.678 | D31: Ham 180g pack | E31: 22 | F31: =B36*0.18 -> 1.7332418 | G31: =E31*F31 -> 38.13132
A32: Raw cost per kg (£) | B32: 3.94 | D32: Cook Bag | E32: 1 | F32: =F9 -> 0.87 | G32: =E32*F32 -> 0.87
A33: Total raw cost (£) | B33: =B31*B32 -> 38.13132 | D33: Packaging | E33: =E31*E32 -> 22 | F33: =F10 -> 0.07 | G33: =E33*F33 -> 1.54
A34: Cooked saleable weight (kg) | B34: 4.91 | D34: Label | E34: 22 | F34: =F11 -> 0.01 | G34: =E34*F34 -> 0.22
A35: Cooked yield (%) | B35: =B34/B31 -> 0.50733623 | D35: Labour | E35: 54 | F35: 20 | G35: =F35/E35 -> 0.37037037
A36: Cooked cost per kg (£) | B36: =B33/(B34-B37) -> 9.6291212
A37: Waste (kg) | B37: 0.95
A38: Waste % of cooked weight | B38: =B37/B34 -> 0.19348269 | D38: Cost per pack | G38: =SUM(G31:G35)/22 -> 1.8696223
A40: HAM 4
A41: Input / Calculation | D41: Cost Per pack | E41: No | F41: Cost | G41: Total
A42: Raw start weight (kg) | B42: 11.066 | D42: Ham 180g pack | E42: 29 | F42: =B47*0.18 -> 1.5092322 | G42: =E42*F42 -> 43.767732
A43: Raw cost per kg (£) | B43: 3.94 | D43: Cook Bag | E43: 1 | F43: =F9 -> 0.87 | G43: =E43*F43 -> 0.87
A44: Total raw cost (£) | B44: =B42*B43 -> 43.60004 | D44: Packaging | E44: =E42*E43 -> 29 | F44: =F10 -> 0.07 | G44: =E44*F44 -> 2.03
A45: Cooked saleable weight (kg) | B45: 5.724 | D45: Label | E45: 29 | F45: =F11 -> 0.01 | G45: =E45*F45 -> 0.29
A46: Cooked yield (%) | B46: =B45/B42 -> 0.51726008 | D46: Labour | E46: 54 | F46: 20 | G46: =F46/E46 -> 0.37037037
A47: Cooked cost per kg (£) | B47: =B44/(B45-B48) -> 8.3846231
A48: Waste (kg) | B48: 0.524
A49: Waste % of cooked weight | B49: =B48/B45 -> 0.091544375 | D49: Cost per pack | G49: =SUM(G42:G46)/29 -> 1.6320035
A51: Average | B51: =(B13+B24+B36+B47)/4 -> 8.5855348 | D51: Average | G51: =(G15+G26+G38+G49)/4 -> 1.676683

Sheet Haslet
A1: Grasmere Farm Manual
A2: Product Page
A3: Haslets
A4: INGREDIENTS | B4: . All allergens in BOLD.
A16: Product | B16: Haslet 1lb | F16: Product | G16: Haslet packaged | K16: Product | L16: Haslet boxed
B17: Weight | C17: Cost | D17: Total | G17: Weight | H17: Cost | I17: Total | L17: Weight | M17: Cost | N17: Total
A18: Pork Meat | B18: 0.454 | C18: ='Ingredient Cost'!D56 -> 61.36 | D18: =B18*C18 -> 27.85744 | F18: Haslet | G18: 1 | H18: =D26 -> 28.17494 | I18: =G18*H18 -> 28.17494 | K18: Haslet | L18: 6 | M18: =I26 -> 28.40994 | N18: =L18*M18 -> 170.45964
A19: Vale Fat | B19: 0.03 | C19: ='Ingredient Cost'!D78 -> 2.25 | D19: =B19*C19 -> 0.0675 | F19: Packaging | G19: 1 | H19: ='Ingredient Cost'!D88 -> 0.09 | I19: =G19*H19 -> 0.09 | K19: Case | L19: 1 | M19: ='Ingredient Cost'!D108 -> 0.2 | N19: =L19*M19 -> 0.2
F20: Label/etc | G20: 1 | H20: 0.02 | I20: =H20/G20 -> 0.02 | K20: Label | M20: 0.01 | N20: =M20 -> 0.01
F21: Labour | G21: 120 | H21: 15 | I21: =H21/G21 -> 0.125 | K21: Labour | L21: 20 | M21: 15 | N21: =M21/L21 -> 0.75
A22: Labour | B22: 60 | C22: 15 | D22: =C22/B22 -> 0.25
A26: COST | D26: =SUM(D18:D22) -> 28.17494 | F26: COST | I26: =SUM(I18:I22) -> 28.40994 | K26: COST | N26: =SUM(N18:N22) -> 171.41964
K27: PER EACH | N27: =N26/6 -> 28.56994
A30: Product | B30: Haslet 6lb | F30: Product | G30: Haslet 6lb-sliced Case
B31: Weight | C31: Cost | D31: Total | G31: Weight | H31: Cost | I31: Total
A32: Pork Meat | B32: 2.724 | C32: ='Ingredient Cost'!D56 -> 61.36 | D32: =B32*C32 -> 167.14464 | F32: Haslet | G32: 1.56 | H32: =D40 -> 61.561385 | I32: =G32*H32 -> 96.03576
A33: Paper | B33: 1 | C33: ='Ingredient Cost'!D86 -> 0.12 | D33: =B33*C33 -> 0.12 | F33: Vac Bag | G33: 12 | H33: ='Ingredient Cost'!D105 -> 0.07 | I33: =G33*H33 -> 0.84
F34: Label | G34: 12 | H34: 0.01 | I34: =G34*H34 -> 0.12
A35: Labour | B35: 35 | C35: 15 | D35: =C35/B35 -> 0.42857143 | F35: Labour | G35: 90 | H35: 15 | I35: =H35/G35 -> 0.16666667
F36: Case | G36: 1 | H36: ='Ingredient Cost'!D108 -> 0.2 | I36: =H36/G36 -> 0.2
F37: End Label | G37: 1 | H37: 0.01 | I37: =H37/G37 -> 0.01
A39: COST | D39: =SUM(D32:D35) -> 167.69321 | F39: COST PER CASE | I39: =SUM(I32:I35) -> 97.162427
A40: PER KG | D40: =D39/B32 -> 61.561385 | F40: PER KG | I40: =I39/G32 -> 62.283607

Sheet Meatballs
A1: Grasmere Farm Manual
A2: Costing
A4: Product | F4: Product | G4: Meatballs
B5: Weight | C5: Cost | D5: Total | G5: Weight | H5: Cost | I5: Total
A6: Start weight (before hung if dry aged) | B6: 0.34 | F6: Meatball Pack | G6: 6 | H6: =D14 -> 0 | I6: =G6*H6 -> 0
A7: (Start weight after hanging if dry aged) | B7: 1 | F7: Case | G7: 1 | H7: ='Ingredient Cost'!D108 -> 0.2 | I7: =G7*H7 -> 0.2
A8: Product | B8: 1 | F8: Label | G8: 1 | H8: 0.01 | I8: =H8/G8 -> 0.01
A9: Trim | B9: 120 | F9: Labour | G9: 20 | H9: 15 | I9: =H9/G9 -> 0.75
A10: Waste
A14: COST PER PACK | D14: =SUM(D6:D10) -> 0 | F14: COST | I14: =SUM(I6:I10) -> 0.96

Sheet Black Pudding
A1: Grasmere Farm Manual
A2: Product Page
A3: Black Pudding
A4: INGREDIENTS | B4: . All allergens in BOLD.
A16: Product | B16: Black Pudding | F16: Black Pudding
B17: Weight | C17: Cost | D17: Total | G17: Weight | H17: Cost | I17: Total
A18: Pearl Barley | B18: 11 | C18: ='Ingredient Cost'!D26 -> 0.83 | D18: =B18*C18 -> 9.13 | F18: Black Pudding | G18: 0.25 | H18: =D26 -> 1.1688646 | I18: =G18*H18 -> 0.29221616
A19: Back Fat | B19: 11 | C19: ='Ingredient Cost'!D72 -> 1.7 | D19: =B19*C19 -> 18.7 | F19: Packaging | G19: 1 | H19: 0.1 | I19: =G19*H19 -> 0.1
A20: Cooked Onion | B20: 5 | C20: ='Ingredient Cost'!D33 -> 0 | D20: =B20*C20 -> 0 | F20: Labour | G20: 180 | H20: 15 | I20: =H20/G20 -> 0.083333333
A21: Black Pudding Mix | B21: 10.8 | C21: 2.38 | D21: =B21*C21 -> 25.704
A22: Water | B22: 8 | C22: 0 | D22: =B22*C22 -> 0
A23: Skin | B23: ?
B24: =SUM(B18:B22) -> 45.8 | D24: =SUM(D18:D22) -> 53.534
A26: COST | D26: =SUM(D24/B24) -> 1.1688646 | F26: COST | I26: =SUM(I18:I24) -> 0.47554949

Sheet Faggots
A1: Grasmere Farm Manual
A2: Product Page
A3: Faggots
A4: INGREDIENTS | B4: . All allergens in BOLD.
A16: Product | B16: Faggot Meat Mix | F16: Product | G16: Faggot Mix | K16: Product | L16: Faggot (4 per pack)
B17: Weight | C17: Cost | D17: Total | G17: Weight | H17: Cost | I17: Total | L17: Weight | M17: Cost | N17: Total
A18: Pork Meat | B18: 3 | C18: ='Ingredient Cost'!D56 -> 61.36 | D18: =B18*C18 -> 184.08 | F18: Faggot Mix | G18: 10 | I18: =G18*H18 -> 0 | K18: Faggot | L18: 0.4 | M18: =I26 -> 0.048 | N18: =L18*M18 -> 0.0192
A19: Kidney | B19: 1 | C19: 2 | D19: =B19*C19 -> 2 | F19: OXO Cube | G19: 0.024 | H19: 2 | I19: =G19*H19 -> 0.048 | K19: Vail | L19: 0.07 | M19: ='Ingredient Cost'!I88 -> 0 | N19: =L19*M19 -> 0
A20: Heart | B20: 1 | C20: 2 | D20: =B20*C20 -> 2 | F20: Water | G20: 1 | H20: 0 | I20: =G20*H20 -> 0 | K20: Packaging | L20: 1 | M20: 0.2 | N20: =M20/L20 -> 0.2
A21: Liver | B21: 1.5 | C21: 2 | D21: =B21*C21 -> 3 | F21: Rusk | G21: 2 | H21: ='Ingredient Cost'!I26 -> 0 | I21: =G21*H21 -> 0 | K21: Labour | L21: 29 | M21: 15 | N21: =M21/L21 -> 0.51724138
A22: Garlic | B22: 0.1 | D22: =B22*C22 -> 0
A23: Onion | B23: 2 | C23: ='Ingredient Cost'!D33 -> 0 | D23: =B23*C23 -> 0
A26: COST | D26: =SUM(D18:D22) -> 191.08 | F26: COST | I26: =SUM(I18:I22) -> 0.048 | K26: COST | N26: =SUM(N18:N22) -> 0.73644138
A30: Product | B30: Haslet 6lb
B31: Weight | C31: Cost | D31: Total
A32: Pork Meat | B32: 2.724 | C32: ='Ingredient Cost'!D56 -> 61.36 | D32: =B32*C32 -> 167.14464
A33: Paper | B33: 1 | C33: ='Ingredient Cost'!D86 -> 0.12 | D33: =B33*C33 -> 0.12
A35: Labour | B35: 35 | C35: 15 | D35: =C35/B35 -> 0.42857143
A39: COST | D39: =SUM(D32:D35) -> 167.69321

Sheet Scotch Eggs
A1: Grasmere Farm Manual
A2: Product Page
A3: Scotch & Bacon Eggs
A4: INGREDIENTS | B4: . All allergens in BOLD.
A16: Product | B16: Scotch or Bacon Eggs | F16: Product | G16: Scotch or Bacon Eggs Individual Pack | K16: Product | L16: Scotch or Bacon Eggs Twin Pack
B17: Weight | C17: Cost | D17: Total | G17: Weight | H17: Cost | I17: Total | L17: Weight | M17: Cost | N17: Total
A18: Sausage Strip | B18: 0.088 | C18: ='Ingredient Cost'!D50 -> 56.25 | D18: =B18*C18 -> 4.95 | F18: Scotch/Bacon Egg | G18: 1 | H18: =D26 -> 5.3013 | I18: =G18*H18 -> 5.3013 | K18: Twin Pack | L18: 12 | M18: =D26 -> 5.3013 | N18: =L18*M18 -> 63.6156
A19: Egg | B19: 1 | C19: ='Ingredient Cost'!D16 -> 0.27 | D19: =B19*C19 -> 0.27 | F19: Packaging/Label | G19: 1 | H19: 0.02 | I19: =G19*H19 -> 0.02 | K19: Packaging | L19: 6 | M19: ='Ingredient Cost'!D88 -> 0.09 | N19: =SUM(L19*M19) -> 0.54
A20: Crumb | B20: 0.01 | C20: ='Ingredient Cost'!D17 -> 1.26 | D20: =B20*C20 -> 0.0126 | F20: Labour | G20: 240 | H20: 15 | I20: =H20/G20 -> 0.0625 | K20: Case | L20: 1 | M20: ='Ingredient Cost'!D108 -> 0.2 | N20: =L20*M20 -> 0.2
A21: Flour/Egg Wash | B21: 0.01 | C21: ='Ingredient Cost'!D7 -> 0.62 | D21: =B21*C21 -> 0.0062 | K21: Label | M21: 0.07 | N21: =M21 -> 0.07
A22: Labour | B22: 240 | C22: 15 | D22: =C22/B22 -> 0.0625 | K22: Labour | L22: 20 | M22: 15 | N22: =M22/L22 -> 0.75
A26: COST | D26: =SUM(D18:D22) -> 5.3013 | F26: COST | I26: =SUM(I18:I22) -> 5.3838 | K26: COST | N26: =SUM(N18:N22) -> 65.1756
K27: PER EGG | N27: =N26/6 -> 10.8626

Sheet ROM
A1: Grasmere Farm Manual
A2: Product Page
A3: Red Onion Marmalade
A4: INGREDIENTS | B4: . All allergens in BOLD.
A16: Product | B16: Red Onion Marmalade | G16: Product | H16: Sweet Chilli Red Onion Marmalade
B17: Weight | C17: Cost | D17: Total | H17: Weight | I17: Cost | J17: Total
A18: Red Onions | B18: 5 | C18: ='Ingredient Cost'!D32 -> 13.5 | D18: =B18*C18 -> 67.5 | G18: Red Onions | H18: 5 | I18: ='Ingredient Cost'!D32 -> 13.5 | J18: =H18*I18 -> 67.5
A19: Brown Sugar | B19: 3.5 | C19: ='Ingredient Cost'!D30 -> 1.02 | D19: =B19*C19 -> 3.57 | G19: Brown Sugar | H19: 3.5 | I19: =C19 -> 1.02 | J19: =H19*I19 -> 3.57
A20: Red wine Vinegar | B20: 1 | C20: ='Ingredient Cost'!D34 -> 5.27 | D20: =B20*C20 -> 5.27 | G20: Red wine Vinegar | H20: 1 | I20: =C20 -> 5.27 | J20: =H20*I20 -> 5.27
A21: Total | B21: =SUM(B18:B20) -> 9.5 | D21: =SUM(D18:D20) -> 76.34 | G21: Chilli Flakes | H21: 0.02 | I21: ='Ingredient Cost'!D35 -> 9.4 | J21: =H21*I21 -> 0.188
A22: Per Kg | D22: =D21/B21 -> 8.0357895 | G22: Total | H22: =SUM(H18:H21) -> 9.52 | J22: =SUM(J18:J21) -> 76.528
A23: Red Onion Marmalade | B23: 0.475 | C23: =D22 -> 8.0357895 | D23: =B23*C23 -> 3.817 | G23: Per KG | J23: =J22/H22 -> 8.0386555
A24: Jar | B24: 1 | C24: ='Ingredient Cost'!D102 -> 0.23 | D24: =B24*C24 -> 0.23 | G24: SWROM | H24: 0.475 | I24: =J23 -> 8.0386555 | J24: =H24*I24 -> 3.8183613
A25: Lid | B25: 1 | C25: ='Ingredient Cost'!D103 -> 0.006 | D25: =B25*C25 -> 0.006 | G25: Jar | H25: 1 | I25: =C24 -> 0.23 | J25: =H25*I25 -> 0.23
A26: Label | B26: 1 | C26: 0.01 | D26: =B26*C26 -> 0.01 | G26: Label | H26: 1 | I26: 0.01 | J26: =H26*I26 -> 0.01
A27: Labour | B27: 60 | C27: 15 | D27: =C27/B27 -> 0.25 | G27: Lid | H27: 1 | I27: =C25 -> 0.006 | J27: =H27*I27 -> 0.006
G28: Labour | H28: 60 | I28: 15 | J28: =I28/H28 -> 0.25
A30: COST | D30: =SUM(D23:D27) -> 4.313
G31: COST | J31: =SUM(J24:J28) -> 4.3143613
A33: Red Onion Marmalade Case
B34: Weight | C34: Cost | D34: Total
A35: ROM | B35: 12 | C35: =D30 -> 4.313 | D35: =B35*C35 -> 51.756
A36: Case | B36: 1 | C36: ='Ingredient Cost'!D108 -> 0.2 | D36: =B36*C36 -> 0.2
A37: Label | B37: 1 | C37: 0.01 | D37: =C37/B37 -> 0.01
A38: Labour | B38: 20 | C38: 15 | D38: =C38/B38 -> 0.75
A43: COST | D43: =SUM(D35:D41) -> 52.716

Sheet Pastry Costing
A1: Kitchen Pastry Costs
A2: Change info in yellow boxes
A4: Product | B4: Cold Water Pastry- Meat Pies Batch | F4: Product | G4: Hot Water Pastry- Pork Pies Batch
A5: Date | B5: ….. | F5: Date | G5: …..
B6: Weight | C6: Cost | D6: Total | G6: Weight | H6: Cost | I6: Total
A7: Water | B7: 2.5 | F7: Water | G7: 2.5
A8: Fat/Butter | B8: 4 | C8: ='Ingredient Cost'!$D$6 -> 2.06 | D8: =B8*C8 -> 8.24 | F8: Fat/Butter | G8: 4 | H8: ='Ingredient Cost'!$D$6 -> 2.06 | I8: =G8*H8 -> 8.24
A9: Flour | B9: 8 | C9: ='Ingredient Cost'!$D$7 -> 0.62 | D9: =B9*C9 -> 4.96 | F9: Flour | G9: 8 | H9: ='Ingredient Cost'!$D$7 -> 0.62 | I9: =G9*H9 -> 4.96
A10: Salt | B10: 0.15 | C10: ='Ingredient Cost'!$D$8 -> 0.54 | D10: =B10*C10 -> 0.081 | F10: Salt | G10: 0.15 | H10: ='Ingredient Cost'!$D$8 -> 0.54 | I10: =G10*H10 -> 0.081
A12: Total Weight | B12: =B7+B8+B9+B10 -> 14.65 | D12: =SUM(D7:D10) -> 13.281 | F12: Total Weight | G12: =G7+G8+G9+G10 -> 14.65 | I12: =SUM(I7:I10) -> 13.281
A14: COST | D14: =D12/B12 -> 0.9065529 | F14: COST | I14: =I12/G12 -> 0.9065529
A16: Small bases | B16: 150 | F16: Mini | G16: 225
A17: Medium bases | B17: 106 | F17: Small | G17: 120
A18: Large | B18: 65 | F18: Medium | G18: 70
F19: 2lb | G19: 30
F20: Large | G20: 24
A22: PORK PIES PASTRY COST | B22: Pie base weight | C22: Cost Open | D22: Pie Lid weight | E22: Lid Cost | F22: Total Cost
A23: Mini | B23: 0.065 | C23: =B23*I14 -> 0.058925939 | D23: 0.02 | E23: =D23*I14 -> 0.018131058 | F23: =C23+E23 -> 0.077056997
A24: 10oz | B24: 0.12 | C24: =B24*I14 -> 0.10878635 | D24: 0.04 | E24: =D24*I14 -> 0.036262116 | F24: =C24+E24 -> 0.14504846
A25: 1lb | B25: 0.21 | C25: =B25*I14 -> 0.19037611 | D25: 0.06 | E25: =D25*I14 -> 0.054393174 | F25: =C25+E25 -> 0.24476928
A26: 2lb | B26: 0.445 | C26: =B26*I14 -> 0.40341604 | D26: 0.06 | E26: =D26*I14 -> 0.054393174 | F26: =C26+E26 -> 0.45780922
A27: 3lb | B27: 0.445 | C27: =B27*I14 -> 0.40341604 | D27: 0.165 | E27: =D27*I14 -> 0.14958123 | F27: =C27+E27 -> 0.55299727
A29: MEAT PIE PASTRY COST | B29: Pie base weight | C29: Cost Open | D29: Pie Lid weight | E29: Lid Cost | F29: Total Cost
A30: Individual | B30: 0.097 | C30: =B30*D14 -> 0.087935631 | D30: 0.04 | E30: =D30*C37 -> 0.12285906 | F30: =C30+E30 -> 0.21079469
A31: Medium | B31: 0.138 | C31: =B31*D14 -> 0.1251043 | D31: 0.08 | E31: =D31*H37 -> 0.21631 | F31: =C31+E31 -> 0.3414143
A32: Large | B32: 0.225 | C32: =B32*D14 -> 0.2039744 | D32: 0.165 | E32: =D32*'Ingredient Cost'!D9 -> 0.3201 | F32: =C32+E32 -> 0.5240744
A35: Small Lid | B35: Weight | C35: Cost | D35: Total | F35: Medium lists | G35: Weight | H35: Cost | I35: Total | K35: Mixed lids | L35: Weight | M35: Cost | N35: Total
A36: Total Weight and Cost | B36: 10.766 | C36: ='Ingredient Cost'!D9 -> 1.94 | D36: =B36*C36 -> 20.88604 | F36: Total Weight and Cost | G36: 10.704 | H36: =C36 -> 1.94 | I36: =G36*H36 -> 20.76576 | K36: Total Weight and Cost | L36: 10.832 | M36: =H36 -> 1.94 | N36: =L36*M36 -> 21.01408
A37: 170 lids | B37: =0.04*170 -> 6.8 | C37: =D36/B37 -> 3.0714765 | D37: =B37*C37 -> 20.88604 | F37: 96 lids | G37: =0.08*96 -> 7.68 | H37: =I36/G37 -> 2.703875 | I37: =G37*H37 -> 20.76576 | K37: 36 small | L37: =0.04*36 -> 1.44 | M37: =N40 -> 2.6007525 | N37: =L37*M37 -> 3.7450836
A38: Waste | B38: 3.046 | C38: =C36 -> 1.94 | D38: =B38*C38 -> 5.90924 | F38: Waste | G38: 2.98 | H38: =H36 -> 1.94 | I38: =G38*H38 -> 5.7812 | K38: 83 medium | L38: =0.08*83 -> 6.64 | M38: =N40 -> 2.6007525 | N38: =L38*M38 -> 17.268996
K39: Waste | L39: 2.36 | M39: =M36 -> 1.94 | N39: =L39*M39 -> 4.5784
N40: =N36/(L37+L38) -> 2.6007525

Sheet Jumbo Sausage Roll
A1: Grasmere Farm Manual
A2: Product Page
A3: Jumbo Sausage Roll
A5: Product | B5: Strip costing | G5: Product | H5: Strip costing
B6: Weight | C6: Cost | D6: Total | H6: Weight | I6: Cost | J6: Total
A7: Pukka Pasty | B7: 11.056 | C7: ='Ingredient Cost'!D9 -> 1.94 | D7: =B7*C7 -> 21.44864 | G7: Pukka Pasty | H7: 11.102 | I7: =C7 -> 1.94 | J7: =H7*I7 -> 21.53788
A8: Sausagemeat | B8: 12.321 | C8: ='Ingredient Cost'!D50 -> 56.25 | D8: =B8*C8 -> 693.05625 | G8: Sausagemeat | H8: 12.321 | I8: =C8 -> 56.25 | J8: =H8*I8 -> 693.05625
A9: Waste | B9: 1.298 | C9: =D14 -> 32.361289 | D9: =C9/B9 -> 24.931655 | G9: Waste | H9: 1.362 | I9: =J14 -> 32.391738 | J9: =I9/H9 -> 23.78248
A10: Labour | B10: 275 | C10: ='Ingredient Cost'!J3 -> 20 | D10: =C10/B10 -> 0.072727273 | G10: Labour | H10: 275 | I10: =C10 -> 20 | J10: =I10/H10 -> 0.072727273
A14: COST | D14: =(D7+D8)/(B7+B8-B9) -> 32.361289 | E14: per kg | G14: COST | J14: =(J7+J8)/(H7+H8-H9) -> 32.391738 | K14: per kg
D15: =(D7+D8)/148 -> 4.8277357 | E15: each | J15: =(J7+J8)/148 -> 4.8283387 | K15: each
A17: Product | B17: Raw Jumbo Sausage Roll boxed
B18: Weight | C18: Cost | D18: Total
A19: Sausage Roll | B19: 48 | C19: =D15 -> 4.8277357 | D19: =B19*C19 -> 231.73132
A20: Case | B20: 1 | C20: ='Ingredient Cost'!D108 -> 0.2 | D20: =B20*C20 -> 0.2 | N20: 0.115
A21: Cooking Paper | B21: 2 | C21: ='Ingredient Cost'!D86 -> 0.12 | D21: =B21*C21 -> 0.24
A22: Label | B22: 1 | C22: 0.01 | D22: =C22/B22 -> 0.01
A26: COST | D26: =SUM(D19:D23) -> 232.18132
A27: PER EACH | D27: =D26/48 -> 4.8371107
A28: Product | B28: Cooked Jumbo Sausage Roll Single Pack Case
B29: Weight | C29: Cost | D29: Total
A30: Jumbo Sausage Roll | B30: 10 | C30: =D15 -> 4.8277357 | D30: =B30*C30 -> 48.277357
A31: Packaging | B31: 10 | C31: ='Ingredient Cost'!D88 -> 0.09 | D31: =SUM(B31*C31) -> 0.9
A32: Case | B32: 1 | C32: ='Ingredient Cost'!D108 -> 0.2 | D32: =B32*C32 -> 0.2
A33: Label | C33: 0.01 | D33: =C33 -> 0.01
A34: Labour | B34: 200 | C34: =C10 -> 20 | D34: =C34/B34 -> 0.1
A37: COST | D37: =SUM(D30:D34) -> 49.487357
A38: PER EACH | D38: =D37/10 -> 4.9487357

Sheet Costings v2
B1: Kitchen Costings
B2: 46054
E4: Required Margin: | F4: 0.15 | G4: (Indirect Expenses (10%) + 5%) | I4: Van Sales Margin | J4: 0.3
B6: Product | C6: Category | D6: Sub-Category | E6: Size (Meat Pie) | F6: COGS | G6: Kitchen Margin | H6: Kitchen Price | I6: Van Sales Margin | J6: Minimum Price | K6: Minimum Price Incl. VAT
B7: Jumbo Sausage Rolls - Raw 48 case | C7: Sausage Roll | D7: Case | F7: ='Jumbo Sausage Roll v2'!I51 -> 23.978649 | G7: =F$4 -> 0.15 | H7: =F7*(G7+1) -> 27.575446 | I7: =J$4 -> 0.3 | J7: =H7*(1+$J$4) -> 35.84808 | K7: =Table1[[#This Row],[Minimum Price]]*1.2 -> 43.017696
B8: Jumbo Sausage Rolls - Cooked 10 per case | C8: Sausage Roll | D8: Case | F8: ='Jumbo Sausage Roll v2'!D51 -> 7.3918018 | G8: =F$4 -> 0.15 | H8: =F8*(G8+1) -> 8.5005721 | I8: =J$4 -> 0.3 | J8: =H8*(1+$J$4) -> 11.050744 | K8: =Table1[[#This Row],[Minimum Price]]*1.2 -> 13.260892
B9: Jumbo Sausage Roll - Retail | C9: Sausage Roll | D9: Individual | F9: ='Jumbo Sausage Roll v2'!D40 -> 0.71018018 | G9: =F$4 -> 0.15 | H9: =F9*(G9+1) -> 0.81670721 | I9: =J$4 -> 0.3 | J9: =H9*(1+$J$4) -> 1.0617194 | K9: =Table1[[#This Row],[Minimum Price]]*1.2 -> 1.2740632
B10: Twin Sausage Rolls - Retail | C10: Sausage Roll | D10: Individual | F10: ='Sausage Roll v2'!D40 -> 1.0386937 | G10: =F$4 -> 0.15 | H10: =F10*(G10+1) -> 1.1944977 | I10: =J$4 -> 0.3 | J10: =H10*(1+$J$4) -> 1.5528471 | K10: =Table1[[#This Row],[Minimum Price]]*1.2 -> 1.8634165
B11: Twin Sausage Rolls - Cooked 10 per case | C11: Sausage Roll | D11: Case | F11: ='Sausage Roll v2'!D51 -> 10.676937 | G11: =F$4 -> 0.15 | H11: =F11*(G11+1) -> 12.278477 | I11: =J$4 -> 0.3 | J11: =H11*(1+$J$4) -> 15.962021 | K11: =Table1[[#This Row],[Minimum Price]]*1.2 -> 19.154425
B12: Steak Pie - Cooked | C12: Meat Pie | D12: Individual | E12: Small | F12: ='Steak Pie v2'!D54 -> 1.387782 | G12: =F$4 -> 0.15 | H12: =F12*(G12+1) -> 1.5959493 | I12: =J$4 -> 0.3 | J12: =H12*(1+$J$4) -> 2.0747341 | K12: =Table1[[#This Row],[Minimum Price]]*1.2 -> 2.4896809
B13: Steak Pie - Cooked (not packaged) | C13: Meat Pie | D13: Individual | E13: Small | F13: ='Steak Pie v2'!D35+'Steak Pie v2'!D53 -> 1.237782 | G13: =F$4 -> 0.15 | H13: =F13*(G13+1) -> 1.4234493 | I13: =J$4 -> 0.3 | J13: =H13*(1+$J$4) -> 1.8504841 | K13: =Table1[[#This Row],[Minimum Price]]*1.2 -> 2.2205809
B14: Steak Pie - Cooked case of 6 | C14: Meat Pie | D14: Case | E14: Small | F14: ='Steak Pie v2'!D74 -> 8.6478031 | G14: =F$4 -> 0.15 | H14: =F14*(G14+1) -> 9.9449736 | I14: =J$4 -> 0.3 | J14: =H14*(1+$J$4) -> 12.928466 | K14: =Table1[[#This Row],[Minimum Price]]*1.2 -> 15.514159
B15: Steak Pie - Cooked case of 9 | C15: Meat Pie | D15: Case | E15: Small | F15: ='Steak Pie v2'!D65 -> 12.811149 | G15: =F$4 -> 0.15 | H15: =F15*(G15+1) -> 14.732822 | I15: =J$4 -> 0.3 | J15: =H15*(1+$J$4) -> 19.152668 | K15: =Table1[[#This Row],[Minimum Price]]*1.2 -> 22.983202
B16: Steak Pie - Frozen case of 12 | C16: Meat Pie | D16: Case | E16: Small | F16: ='Steak Pie v2'!D83 -> 15.174495 | G16: =F$4 -> 0.15 | H16: =F16*(G16+1) -> 17.450669 | I16: =J$4 -> 0.3 | J16: =H16*(1+$J$4) -> 22.68587 | K16: =Table1[[#This Row],[Minimum Price]]*1.2 -> 27.223044
B17: Steak Pie - Cooked | C17: Meat Pie | D17: Individual | E17: Medium | F17: ='Steak Pie v2'!I54 -> 2.5601668 | G17: =F$4 -> 0.15 | H17: =F17*(G17+1) -> 2.9441918 | I17: =J$4 -> 0.3 | J17: =H17*(1+$J$4) -> 3.8274494 | K17: =Table1[[#This Row],[Minimum Price]]*1.2 -> 4.5929393
B18: Steak Pie - Frozen | C18: Meat Pie | D18: Individual | E18: Medium | F18: ='Steak Pie v2'!I54 -> 2.5601668 | G18: =F$4 -> 0.15 | H18: =F18*(G18+1) -> 2.9441918 | I18: =J$4 -> 0.3 | J18: =H18*(1+$J$4) -> 3.8274494 | K18: =Table1[[#This Row],[Minimum Price]]*1.2 -> 4.5929393
B19: Steak Pie - Cooked Case of 4 | C19: Meat Pie | D19: Case | E19: Medium | F19: ='Steak Pie v2'!I65 -> 10.561778 | G19: =F$4 -> 0.15 | H19: =F19*(G19+1) -> 12.146045 | I19: =J$4 -> 0.3 | J19: =H19*(1+$J$4) -> 15.789859 | K19: =Table1[[#This Row],[Minimum Price]]*1.2 -> 18.94783
B20: Steak Pie - Frozen | C20: Meat Pie | D20: Individual | E20: Large | F20: ='Steak Pie v2'!N54 -> 5.3284461 | G20: =F$4 -> 0.15 | H20: =F20*(G20+1) -> 6.127713 | I20: =J$4 -> 0.3 | J20: =H20*(1+$J$4) -> 7.9660269 | K20: =Table1[[#This Row],[Minimum Price]]*1.2 -> 9.5592323
B21: Steak & Ale Pie - Cooked | C21: Meat Pie | D21: Individual | E21: Small | F21: ='Steak & Ale Pie v2'!D54 -> 1.4129884 | G21: =F$4 -> 0.15 | H21: =F21*(G21+1) -> 1.6249366 | I21: =J$4 -> 0.3 | J21: =H21*(1+$J$4) -> 2.1124176 | K21: =Table1[[#This Row],[Minimum Price]]*1.2 -> 2.5349011
B22: Steak & Ale Pie - Cooked case of 6 | C22: Meat Pie | D22: Case | E22: Small | F22: ='Steak & Ale Pie v2'!D74 -> 8.7990414 | G22: =F$4 -> 0.15 | H22: =F22*(G22+1) -> 10.118898 | I22: =J$4 -> 0.3 | J22: =H22*(1+$J$4) -> 13.154567 | K22: =Table1[[#This Row],[Minimum Price]]*1.2 -> 15.78548
B23: Steak & Ale Pie - Cooked case of 9 | C23: Meat Pie | D23: Case | E23: Small | F23: ='Steak & Ale Pie v2'!D65 -> 13.038007 | G23: =F$4 -> 0.15 | H23: =F23*(G23+1) -> 14.993707 | I23: =J$4 -> 0.3 | J23: =H23*(1+$J$4) -> 19.49182 | K23: =Table1[[#This Row],[Minimum Price]]*1.2 -> 23.390184
B24: Steak & Ale Pie - Cooked case of 12 | C24: Meat Pie | D24: Case | E24: Small | F24: ='Steak & Ale Pie v2'!D83 -> 17.276972 | G24: =F$4 -> 0.15 | H24: =F24*(G24+1) -> 19.868517 | I24: =J$4 -> 0.3 | J24: =H24*(1+$J$4) -> 25.829073 | K24: =Table1[[#This Row],[Minimum Price]]*1.2 -> 30.994887
B25: Steak & Ale Pie - Cooked | C25: Meat Pie | D25: Individual | E25: Medium | F25: ='Steak & Ale Pie v2'!I54 -> 2.6103842 | G25: =F$4 -> 0.15 | H25: =F25*(G25+1) -> 3.0019418 | I25: =J$4 -> 0.3 | J25: =H25*(1+$J$4) -> 3.9025243 | K25: =Table1[[#This Row],[Minimum Price]]*1.2 -> 4.6830292
B26: Steak & Ale Pie - Frozen | C26: Meat Pie | D26: Individual | E26: Medium | F26: ='Steak & Ale Pie v2'!I54 -> 2.6103842 | G26: =F$4 -> 0.15 | H26: =F26*(G26+1) -> 3.0019418 | I26: =J$4 -> 0.3 | J26: =H26*(1+$J$4) -> 3.9025243 | K26: =Table1[[#This Row],[Minimum Price]]*1.2 -> 4.6830292
B27: Steak & Ale Pie - Cooked case of 4 | C27: Meat Pie | D27: Case | E27: Medium | F27: ='Steak & Ale Pie v2'!I65 -> 10.762648 | G27: =F$4 -> 0.15 | H27: =F27*(G27+1) -> 12.377045 | I27: =J$4 -> 0.3 | J27: =H27*(1+$J$4) -> 16.090158 | K27: =Table1[[#This Row],[Minimum Price]]*1.2 -> 19.30819
B28: Steak & Ale Pie - Frozen | C28: Meat Pie | D28: Individual | E28: Large | F28: ='Steak & Ale Pie v2'!N54 -> 5.4730408 | G28: =F$4 -> 0.15 | H28: =F28*(G28+1) -> 6.2939969 | I28: =J$4 -> 0.3 | J28: =H28*(1+$J$4) -> 8.182196 | K28: =Table1[[#This Row],[Minimum Price]]*1.2 -> 9.8186351
B29: Steak & Kidney Pie - Cooked | C29: Meat Pie | D29: Individual | E29: Small | F29: ='Steak & Kidney Pie v2'!D54 -> 1.3250837 | G29: =F$4 -> 0.15 | H29: =F29*(G29+1) -> 1.5238462 | I29: =J$4 -> 0.3 | J29: =H29*(1+$J$4) -> 1.9810001 | K29: =Table1[[#This Row],[Minimum Price]]*1.2 -> 2.3772001
B30: Steak & Kidney Pie - Cooked case of 6 | C30: Meat Pie | D30: Case | E30: Small | F30: ='Steak & Kidney Pie v2'!D74 -> 8.2716131 | G30: =F$4 -> 0.15 | H30: =F30*(G30+1) -> 9.5123551 | I30: =J$4 -> 0.3 | J30: =H30*(1+$J$4) -> 12.366062 | K30: =Table1[[#This Row],[Minimum Price]]*1.2 -> 14.839274
B31: Steak & Kidney Pie - Cooked case of 9 | C31: Meat Pie | D31: Case | E31: Small | F31: ='Steak & Kidney Pie v2'!D65 -> 12.246864 | G31: =F$4 -> 0.15 | H31: =F31*(G31+1) -> 14.083894 | I31: =J$4 -> 0.3 | J31: =H31*(1+$J$4) -> 18.309062 | K31: =Table1[[#This Row],[Minimum Price]]*1.2 -> 21.970874
B32: Steak & Kidney Pie - Cooked case of 12 | C32: Meat Pie | D32: Case | E32: Small | F32: ='Steak & Kidney Pie v2'!D83 -> 16.222115 | G32: =F$4 -> 0.15 | H32: =F32*(G32+1) -> 18.655432 | I32: =J$4 -> 0.3 | J32: =H32*(1+$J$4) -> 24.252062 | K32: =Table1[[#This Row],[Minimum Price]]*1.2 -> 29.102474
B33: Steak & Kidney Pie - Cooked | C33: Meat Pie | D33: Individual | E33: Medium | F33: ='Steak & Kidney Pie v2'!I54 -> 2.4352562 | G33: =F$4 -> 0.15 | H33: =F33*(G33+1) -> 2.8005446 | I33: =J$4 -> 0.3 | J33: =H33*(1+$J$4) -> 3.640708 | K33: =Table1[[#This Row],[Minimum Price]]*1.2 -> 4.3688495
B34: Steak & Kidney Pie - Frozen | C34: Meat Pie | D34: Individual | E34: Medium | F34: ='Steak & Kidney Pie v2'!I54 -> 2.4352562 | G34: =F$4 -> 0.15 | H34: =F34*(G34+1) -> 2.8005446 | I34: =J$4 -> 0.3 | J34: =H34*(1+$J$4) -> 3.640708 | K34: =Table1[[#This Row],[Minimum Price]]*1.2 -> 4.3688495
B35: Steak & Kidney Pie - Cooked case of 4 | C35: Meat Pie | D35: Case | E35: Medium | F35: ='Steak & Kidney Pie v2'!I65 -> 10.062136 | G35: =F$4 -> 0.15 | H35: =F35*(G35+1) -> 11.571456 | I35: =J$4 -> 0.3 | J35: =H35*(1+$J$4) -> 15.042893 | K35: =Table1[[#This Row],[Minimum Price]]*1.2 -> 18.051472
B36: Steak & Kidney Pie - Frozen | C36: Meat Pie | D36: Individual | E36: Large | F36: ='Steak & Kidney Pie v2'!N54 -> 4.9687812 | G36: =F$4 -> 0.15 | H36: =F36*(G36+1) -> 5.7140983 | I36: =J$4 -> 0.3 | J36: =H36*(1+$J$4) -> 7.4283278 | K36: =Table1[[#This Row],[Minimum Price]]*1.2 -> 8.9139934
B37: Steak & Stilton Pie - Cooked | C37: Meat Pie | D37: Individual | E37: Small | F37: ='Steak & Stilton Pie v2'!D55 -> 1.5045816 | G37: =F$4 -> 0.15 | H37: =F37*(G37+1) -> 1.7302688 | I37: =J$4 -> 0.3 | J37: =H37*(1+$J$4) -> 2.2493494 | K37: =Table1[[#This Row],[Minimum Price]]*1.2 -> 2.6992193
B38: Steak & Stilton Pie - Cooked case of 6 | C38: Meat Pie | D38: Case | E38: Small | F38: ='Steak & Stilton Pie v2'!D75 -> 9.3486005 | G38: =F$4 -> 0.15 | H38: =F38*(G38+1) -> 10.750891 | I38: =J$4 -> 0.3 | J38: =H38*(1+$J$4) -> 13.976158 | K38: =Table1[[#This Row],[Minimum Price]]*1.2 -> 16.771389
B39: Steak & Stilton Pie - Cooked case of 9 | C39: Meat Pie | D39: Case | E39: Small | F39: ='Steak & Stilton Pie v2'!D66 -> 13.862345 | G39: =F$4 -> 0.15 | H39: =F39*(G39+1) -> 15.941697 | I39: =J$4 -> 0.3 | J39: =H39*(1+$J$4) -> 20.724206 | K39: =Table1[[#This Row],[Minimum Price]]*1.2 -> 24.869047
B40: Steak & Stilton Pie - Cooked case of 12 | C40: Meat Pie | D40: Case | E40: Small | F40: ='Steak & Stilton Pie v2'!D84 -> 18.37609 | G40: =F$4 -> 0.15 | H40: =F40*(G40+1) -> 21.132503 | I40: =J$4 -> 0.3 | J40: =H40*(1+$J$4) -> 27.472254 | K40: =Table1[[#This Row],[Minimum Price]]*1.2 -> 32.966705
B41: Steak & Stilton Pie - Cooked | C41: Meat Pie | D41: Individual | E41: Medium | F41: ='Steak & Stilton Pie v2'!I55 -> 2.7221628 | G41: =F$4 -> 0.15 | H41: =F41*(G41+1) -> 3.1304872 | I41: =J$4 -> 0.3 | J41: =H41*(1+$J$4) -> 4.0696334 | K41: =Table1[[#This Row],[Minimum Price]]*1.2 -> 4.8835601
B42: Steak & Stilton Pie - Frozen | C42: Meat Pie | D42: Individual | E42: Medium | F42: ='Steak & Stilton Pie v2'!I55 -> 2.7221628 | G42: =F$4 -> 0.15 | H42: =F42*(G42+1) -> 3.1304872 | I42: =J$4 -> 0.3 | J42: =H42*(1+$J$4) -> 4.0696334 | K42: =Table1[[#This Row],[Minimum Price]]*1.2 -> 4.8835601
B43: Steak & Stilton Pie - Cooked case of 4 | C43: Meat Pie | D43: Case | E43: Medium | F43: ='Steak & Stilton Pie v2'!I66 -> 11.209762 | G43: =F$4 -> 0.15 | H43: =F43*(G43+1) -> 12.891227 | I43: =J$4 -> 0.3 | J43: =H43*(1+$J$4) -> 16.758595 | K43: =Table1[[#This Row],[Minimum Price]]*1.2 -> 20.110314
B44: Steak & Stilton Pie - Frozen | C44: Meat Pie | D44: Individual | E44: Large | F44: ='Steak & Stilton Pie v2'!N55 -> 5.6609881 | G44: =F$4 -> 0.15 | H44: =F44*(G44+1) -> 6.5101363 | I44: =J$4 -> 0.3 | J44: =H44*(1+$J$4) -> 8.4631772 | K44: =Table1[[#This Row],[Minimum Price]]*1.2 -> 10.155813
B45: Chicken & Ham Pie - Cooked | C45: Meat Pie | D45: Individual | E45: Small | F45: ='C&H Pie v2'!D56 -> 1.1617267 | G45: =F$4 -> 0.15 | H45: =F45*(G45+1) -> 1.3359857 | I45: =J$4 -> 0.3 | J45: =H45*(1+$J$4) -> 1.7367814 | K45: =Table1[[#This Row],[Minimum Price]]*1.2 -> 2.0841376
B46: Chicken & Ham Pie - Cooked case of 6 | C46: Meat Pie | D46: Case | E46: Small | F46: ='C&H Pie v2'!D75 -> 7.2914711 | G46: =F$4 -> 0.15 | H46: =F46*(G46+1) -> 8.3851918 | I46: =J$4 -> 0.3 | J46: =H46*(1+$J$4) -> 10.900749 | K46: =Table1[[#This Row],[Minimum Price]]*1.2 -> 13.080899
B47: Chicken & Ham Pie - Cooked case of 9 | C47: Meat Pie | D47: Case | E47: Small | F47: ='C&H Pie v2'!D66 -> 10.776651 | G47: =F$4 -> 0.15 | H47: =F47*(G47+1) -> 12.393149 | I47: =J$4 -> 0.3 | J47: =H47*(1+$J$4) -> 16.111093 | K47: =Table1[[#This Row],[Minimum Price]]*1.2 -> 19.333312
B48: Chicken & Ham Pie - Cooked case of 12 | C48: Meat Pie | D48: Case | E48: Small | F48: ='C&H Pie v2'!D84 -> 14.261831 | G48: =F$4 -> 0.15 | H48: =F48*(G48+1) -> 16.401106 | I48: =J$4 -> 0.3 | J48: =H48*(1+$J$4) -> 21.321438 | K48: =Table1[[#This Row],[Minimum Price]]*1.2 -> 25.585725
B49: Chicken & Ham Pie - Cooked | C49: Meat Pie | D49: Individual | E49: Medium | F49: ='C&H Pie v2'!I56 -> 2.4826485 | G49: =F$4 -> 0.15 | H49: =F49*(G49+1) -> 2.8550458 | I49: =J$4 -> 0.3 | J49: =H49*(1+$J$4) -> 3.7115596 | K49: =Table1[[#This Row],[Minimum Price]]*1.2 -> 4.4538715
B50: Chicken & Ham Pie - Frozen | C50: Meat Pie | D50: Individual | E50: Medium | F50: ='C&H Pie v2'!I56 -> 2.4826485 | G50: =F$4 -> 0.15 | H50: =F50*(G50+1) -> 2.8550458 | I50: =J$4 -> 0.3 | J50: =H50*(1+$J$4) -> 3.7115596 | K50: =Table1[[#This Row],[Minimum Price]]*1.2 -> 4.4538715
B51: Chicken & Ham Pie - Cooked case of 4 | C51: Meat Pie | D51: Case | E51: Medium | F51: ='C&H Pie v2'!I66 -> 10.251705 | G51: =F$4 -> 0.15 | H51: =F51*(G51+1) -> 11.789461 | I51: =J$4 -> 0.3 | J51: =H51*(1+$J$4) -> 15.326299 | K51: =Table1[[#This Row],[Minimum Price]]*1.2 -> 18.391559
B52: Chicken & Ham Pie - Frozen | C52: Meat Pie | D52: Individual | E52: Large | F52: ='C&H Pie v2'!N56 -> 4.2382095 | G52: =F$4 -> 0.15 | H52: =F52*(G52+1) -> 4.873941 | I52: =J$4 -> 0.3 | J52: =H52*(1+$J$4) -> 6.3361233 | K52: =Table1[[#This Row],[Minimum Price]]*1.2 -> 7.6033479
B53: Chicken & Chorizo Pie - Cooked | C53: Meat Pie | D53: Individual | E53: Small | F53: ='C&C Pie v2'!D55 -> 1.1964942 | G53: =F$4 -> 0.15 | H53: =F53*(G53+1) -> 1.3759683 | I53: =J$4 -> 0.3 | J53: =H53*(1+$J$4) -> 1.7887588 | K53: =Table1[[#This Row],[Minimum Price]]*1.2 -> 2.1465106
B54: Chicken & Chorizo Pie - Cooked case of 6 | C54: Meat Pie | D54: Case | E54: Small | F54: ='C&C Pie v2'!D75 -> 7.8889651 | G54: =F$4 -> 0.15 | H54: =F54*(G54+1) -> 9.0723099 | I54: =J$4 -> 0.3 | J54: =H54*(1+$J$4) -> 11.794003 | K54: =Table1[[#This Row],[Minimum Price]]*1.2 -> 14.152803
B55: Chicken & Chorizo Pie - Cooked case of 9 | C55: Meat Pie | D55: Case | E55: Small | F55: ='C&C Pie v2'!D66 -> 11.478448 | G55: =F$4 -> 0.15 | H55: =F55*(G55+1) -> 13.200215 | I55: =J$4 -> 0.3 | J55: =H55*(1+$J$4) -> 17.160279 | K55: =Table1[[#This Row],[Minimum Price]]*1.2 -> 20.592335
B56: Chicken & Chorizo Pie - Cooked case of 12 | C56: Meat Pie | D56: Case | E56: Small | F56: ='C&C Pie v2'!D84 -> 15.06793 | G56: =F$4 -> 0.15 | H56: =F56*(G56+1) -> 17.32812 | I56: =J$4 -> 0.3 | J56: =H56*(1+$J$4) -> 22.526556 | K56: =Table1[[#This Row],[Minimum Price]]*1.2 -> 27.031867
B57: Chicken & Chorizo Pie - Cooked | C57: Meat Pie | D57: Individual | E57: Medium | F57: ='C&C Pie v2'!I55 -> 2.3663744 | G57: =F$4 -> 0.15 | H57: =F57*(G57+1) -> 2.7213305 | I57: =J$4 -> 0.3 | J57: =H57*(1+$J$4) -> 3.5377297 | K57: =Table1[[#This Row],[Minimum Price]]*1.2 -> 4.2452756
B58: Chicken & Chorizo Pie - Frozen | C58: Meat Pie | D58: Individual | E58: Medium | F58: ='C&C Pie v2'!I55 -> 2.3663744 | G58: =F$4 -> 0.15 | H58: =F58*(G58+1) -> 2.7213305 | I58: =J$4 -> 0.3 | J58: =H58*(1+$J$4) -> 3.5377297 | K58: =Table1[[#This Row],[Minimum Price]]*1.2 -> 4.2452756
B59: Chicken & Chorizo Pie - Cooked case of 4 | C59: Meat Pie | D59: Case | E59: Medium | F59: ='C&C Pie v2'!I66 -> 10.175498 | G59: =F$4 -> 0.15 | H59: =F59*(G59+1) -> 11.701822 | I59: =J$4 -> 0.3 | J59: =H59*(1+$J$4) -> 15.212369 | K59: =Table1[[#This Row],[Minimum Price]]*1.2 -> 18.254843
B60: Chicken & Chorizo Pie - Frozen | C60: Meat Pie | D60: Individual | E60: Large | F60: ='C&C Pie v2'!N55 -> 4.0056612 | G60: =F$4 -> 0.15 | H60: =F60*(G60+1) -> 4.6065104 | I60: =J$4 -> 0.3 | J60: =H60*(1+$J$4) -> 5.9884635 | K60: =Table1[[#This Row],[Minimum Price]]*1.2 -> 7.1861562
B61: Mini pack of 2 | C61: Pork Pie | D61: Case | E61: Mini | F61: ='Pork Pie v2'!D66 -> 1.4031861 | G61: =F$4 -> 0.15 | H61: =F61*(G61+1) -> 1.613664 | I61: =J$4 -> 0.3 | J61: =H61*(1+$J$4) -> 2.0977632 | K61: =Table1[[#This Row],[Minimum Price]]*1.2 -> 2.5173158
B62: Mini pack of 6 | C62: Pork Pie | D62: Case | E62: Mini | F62: ='Pork Pie v2'!I66 -> 4.0228915 | G62: =F$4 -> 0.15 | H62: =F62*(G62+1) -> 4.6263253 | I62: =J$4 -> 0.3 | J62: =H62*(1+$J$4) -> 6.0142228 | K62: =Table1[[#This Row],[Minimum Price]]*1.2 -> 7.2170674
B63: Small case of 5 | C63: Pork Pie | D63: Case | E63: Small | F63: ='Pork Pie v2'!D82 -> 6.2475856 | G63: =F$4 -> 0.15 | H63: =F63*(G63+1) -> 7.1847234 | I63: =J$4 -> 0.3 | J63: =H63*(1+$J$4) -> 9.3401404 | K63: =Table1[[#This Row],[Minimum Price]]*1.2 -> 11.208168
B64: Small case of 8 | C64: Pork Pie | D64: Case | E64: Small | F64: ='Pork Pie v2'!I82 -> 8.9821369 | G64: =F$4 -> 0.15 | H64: =F64*(G64+1) -> 10.329457 | I64: =J$4 -> 0.3 | J64: =H64*(1+$J$4) -> 13.428295 | K64: =Table1[[#This Row],[Minimum Price]]*1.2 -> 16.113954
B65: Medium case of 4 | C65: Pork Pie | D65: Case | E65: Medium | F65: ='Pork Pie v2'!D96 -> 10.04441 | G65: =F$4 -> 0.15 | H65: =F65*(G65+1) -> 11.551072 | I65: =J$4 -> 0.3 | J65: =H65*(1+$J$4) -> 15.016394 | K65: =Table1[[#This Row],[Minimum Price]]*1.2 -> 18.019672
B66: Medium case of 6 | C66: Pork Pie | D66: Case | E66: Medium | F66: ='Pork Pie v2'!I96 -> 14.371616 | G66: =F$4 -> 0.15 | H66: =F66*(G66+1) -> 16.527358 | I66: =J$4 -> 0.3 | J66: =H66*(1+$J$4) -> 21.485565 | K66: =Table1[[#This Row],[Minimum Price]]*1.2 -> 25.782679
B67: Pork Pie - 2LB | C67: Pork Pie | D67: Individual | E67: 2LB | F67: ='Pork Pie v2'!D55 -> 8.0236425 | G67: =F$4 -> 0.15 | H67: =F67*(G67+1) -> 9.2271889 | I67: =J$4 -> 0.3 | J67: =H67*(1+$J$4) -> 11.995346 | K67: =Table1[[#This Row],[Minimum Price]]*1.2 -> 14.394415
B68: Pork Pie - 3LB | C68: Pork Pie | D68: Individual | E68: 3LB | F68: ='Pork Pie v2'!I55 -> 14.118831 | G68: =F$4 -> 0.15 | H68: =F68*(G68+1) -> 16.236655 | I68: =J$4 -> 0.3 | J68: =H68*(1+$J$4) -> 21.107652 | K68: =Table1[[#This Row],[Minimum Price]]*1.2 -> 25.329182
B69: Pork Pie - Mini | C69: Pork Pie | D69: Individual | E69: Mini | F69: ='Pork Pie v2'!D42 -> 0.65492637 | G69: =F$4 -> 0.15 | H69: =F69*(G69+1) -> 0.75316532 | I69: =J$4 -> 0.3 | J69: =H69*(1+$J$4) -> 0.97911492 | K69: =Table1[[#This Row],[Minimum Price]]*1.2 -> 1.1749379
B70: Pork Pie - Small | C70: Pork Pie | D70: Individual | E70: Small | F70: ='Pork Pie v2'!I42 -> 0.91151711 | G70: =F$4 -> 0.15 | H70: =F70*(G70+1) -> 1.0482447 | I70: =J$4 -> 0.3 | J70: =H70*(1+$J$4) -> 1.3627181 | K70: =Table1[[#This Row],[Minimum Price]]*1.2 -> 1.6352617
B71: Pork Pie - Medium | C71: Pork Pie | D71: Individual | E71: Medium | F71: ='Pork Pie v2'!N42 -> 2.1036026 | G71: =F$4 -> 0.15 | H71: =F71*(G71+1) -> 2.419143 | I71: =J$4 -> 0.3 | J71: =H71*(1+$J$4) -> 3.1448859 | K71: =Table1[[#This Row],[Minimum Price]]*1.2 -> 3.7738631
B72: Whole Haslet | C72: Haslet | D72: Individual | F72: ='Whole Haslet v2'!D40 -> 2.1714141 | G72: =F$4 -> 0.15 | H72: =F72*(G72+1) -> 2.4971263 | I72: =J$4 -> 0.3 | J72: =H72*(1+$J$4) -> 3.2462641 | K72: =Table1[[#This Row],[Minimum Price]]*1.2 -> 3.895517
B73: Whole Haslet Case of 6 | C73: Haslet | D73: Case | F73: ='Whole Haslet v2'!D51 -> 13.318485 | G73: =F$4 -> 0.15 | H73: =F73*(G73+1) -> 15.316258 | I73: =J$4 -> 0.3 | J73: =H73*(1+$J$4) -> 19.911135 | K73: =Table1[[#This Row],[Minimum Price]]*1.2 -> 23.893362
B74: Sliced Haslet - 120g | C74: Haslet | D74: Individual | F74: ='Sliced Haslet - 120g'!D40 -> 1.1106734 | G74: =F$4 -> 0.15 | H74: =F74*(G74+1) -> 1.2772744 | I74: =J$4 -> 0.3 | J74: =H74*(1+$J$4) -> 1.6604567 | K74: =Table1[[#This Row],[Minimum Price]]*1.2 -> 1.9925481
B75: Sliced Haslet - 160g | C75: Haslet | D75: Individual | F75: ='Sliced Haslet - 160g'!D40 -> 1.3291919 | G75: =F$4 -> 0.15 | H75: =F75*(G75+1) -> 1.5285707 | I75: =J$4 -> 0.3 | J75: =H75*(1+$J$4) -> 1.9871419 | K75: =Table1[[#This Row],[Minimum Price]]*1.2 -> 2.3845703
B76: Sliced Haslet - 120g - Case of 6 | C76: Haslet | D76: Case | F76: ='Sliced Haslet - 120g'!D51 -> 6.9540404 | G76: =F$4 -> 0.15 | H76: =F76*(G76+1) -> 7.9971465 | I76: =J$4 -> 0.3 | J76: =H76*(1+$J$4) -> 10.39629 | K76: =Table1[[#This Row],[Minimum Price]]*1.2 -> 12.475548
B77: Sliced Haslet - 120g - Case of 12 | C77: Haslet | D77: Case | F77: ='Sliced Haslet - 120g'!D60 -> 13.618081 | G77: =F$4 -> 0.15 | H77: =F77*(G77+1) -> 15.660793 | I77: =J$4 -> 0.3 | J77: =H77*(1+$J$4) -> 20.359031 | K77: =Table1[[#This Row],[Minimum Price]]*1.2 -> 24.430837
B78: Sliced Haslet - 160g - Case of 6 | C78: Haslet | D78: Case | F78: ='Sliced Haslet - 160g'!D51 -> 8.2651515 | G78: =F$4 -> 0.15 | H78: =F78*(G78+1) -> 9.5049242 | I78: =J$4 -> 0.3 | J78: =H78*(1+$J$4) -> 12.356402 | K78: =Table1[[#This Row],[Minimum Price]]*1.2 -> 14.827682
B79: Sliced Haslet - 160g - Case of 12 | C79: Haslet | D79: Case | F79: ='Sliced Haslet - 160g'!D60 -> 16.240303 | G79: =F$4 -> 0.15 | H79: =F79*(G79+1) -> 18.676348 | I79: =J$4 -> 0.3 | J79: =H79*(1+$J$4) -> 24.279253 | K79: =Table1[[#This Row],[Minimum Price]]*1.2 -> 29.135104
B80: Scotch Egg | C80: Scotch Egg | D80: Individual | E80: Single | F80: ='Scoth Eggs v2'!D42 -> 0.87166667 | G80: =F$4 -> 0.15 | H80: =F80*(G80+1) -> 1.0024167 | I80: =J$4 -> 0.3 | J80: =H80*(1+$J$4) -> 1.3031417 | K80: =Table1[[#This Row],[Minimum Price]]*1.2 -> 1.56377
B81: Scotch Egg Case of 6 | C81: Scotch Egg | D81: Case | E81: Single | F81: ='Scoth Eggs v2'!D53 -> 5.52 | G81: =F$4 -> 0.15 | H81: =F81*(G81+1) -> 6.348 | I81: =J$4 -> 0.3 | J81: =H81*(1+$J$4) -> 8.2524 | K81: =Table1[[#This Row],[Minimum Price]]*1.2 -> 9.90288
B82: Scotch Egg Case of 9 | C82: Scotch Egg | D82: Case | E82: Single | F82: ='Scoth Eggs v2'!D62 -> 8.135 | G82: =F$4 -> 0.15 | H82: =F82*(G82+1) -> 9.35525 | I82: =J$4 -> 0.3 | J82: =H82*(1+$J$4) -> 12.161825 | K82: =Table1[[#This Row],[Minimum Price]]*1.2 -> 14.59419
B83: Scotch Egg | C83: Scotch Egg | D83: Individual | E83: Twin | F83: ='Scoth Eggs v2'!I42 -> 1.5933333 | G83: =F$4 -> 0.15 | H83: =F83*(G83+1) -> 1.8323333 | I83: =J$4 -> 0.3 | J83: =H83*(1+$J$4) -> 2.3820333 | K83: =Table1[[#This Row],[Minimum Price]]*1.2 -> 2.85844
B84: Scotch Egg Case of 6 | C84: Scotch Egg | D84: Case | E84: Twin | F84: ='Scoth Eggs v2'!I53 -> 9.85 | G84: =F$4 -> 0.15 | H84: =F84*(G84+1) -> 11.3275 | I84: =J$4 -> 0.3 | J84: =H84*(1+$J$4) -> 14.72575 | K84: =Table1[[#This Row],[Minimum Price]]*1.2 -> 17.6709
B85: Scotch Egg Case of 9 | C85: Scotch Egg | D85: Case | E85: Twin | F85: ='Scoth Eggs v2'!I62 -> 14.63 | G85: =F$4 -> 0.15 | H85: =F85*(G85+1) -> 16.8245 | I85: =J$4 -> 0.3 | J85: =H85*(1+$J$4) -> 21.87185 | K85: =Table1[[#This Row],[Minimum Price]]*1.2 -> 26.24622

Sheet Sliced Haslet - 120g
A1: Grasmere Farm
A2: Product Costings
A3: Sliced Haslet - 120g
A4: INGREDIENTS | B4: . All allergens in BOLD.
A17: Ingredient Cost
B19: Cost | C19: Yield | D19: Total | F19: Shrinkage Calculation
A20: Sausage Meat | B20: ='Ingredient Cost'!D57 -> 61.36 | C20: 108 | D20: =B20/C20 -> 0.56814815 | F20: Start Weight | G20: =6*0.454 -> 2.724
A21: Vale Fat | B21: ='Ingredient Cost'!D78 -> 2.25 | C21: 0.2 | D21: =C21/B21 -> 0.088888889 | F21: Cook Shrinkage (90%) | G21: =G20*0.9 -> 2.4516
D22: =SUM(D20:D21) -> 0.65703704 | F22: Slice Yielf (90%) | G22: =G21*0.9 -> 2.20644
F23: Packs per Haslet | G23: =G22/0.12 -> 18.387 | H23: 18 | I23: per haslet | J23: =H23*6 -> 108 | K23: per tray
A25: Individual Packaged Products (excl. Labour)
A27: Individual
B28: Weight | C28: Cost | D28: Total
A29: Ingredient Cost | B29: 1 | C29: =D22 -> 0.65703704 | D29: =B29*C29 -> 0.65703704
A30: Packaging | B30: 1 | C30: ='Ingredient Cost'!D88 -> 0.09 | D30: =C30*B30 -> 0.09
A31: COST | D31: =SUM(D29:D30) -> 0.74703704
A34: Individual Packaged Products (incl. Labour) | D34: = | E34: COGS
A36: Individual
B37: Weight | C37: Cost | D37: Total
A38: Packaged Product Cost | B38: 1 | C38: =D31 -> 0.74703704 | D38: =B38*C38 -> 0.74703704
A39: Labour | B39: 55 | C39: ='Ingredient Cost'!$B$113 -> 20 | D39: =C39/B39 -> 0.36363636
A40: COST | D40: =SUM(D38:D39) -> 1.1106734
B42: Labour Percentage | D42: =D39/D38 -> 0.48677153
A43: CASES
A45: Case of 6
B46: Weight | C46: Cost | D46: Total
A47: Product Cost | B47: 6 | C47: =D40 -> 1.1106734 | D47: =B47*C47 -> 6.6640404
A48: Case Packaging | B48: 1 | C48: ='Ingredient Cost'!$D$108 -> 0.2 | D48: =B48*C48 -> 0.2
A49: Labour | B49: 250 | C49: =$C$39 -> 20 | D49: =C49/B49 -> 0.08
A50: Box end label | B50: 1 | C50: 0.01 | D50: =B50*C50 -> 0.01
A51: COST | D51: =SUM(D47:D50) -> 6.9540404
A52: PER EACH | D52: =D51/6 -> 1.1590067
A54: Case of 12
B55: Weight | C55: Cost | D55: Total
A56: Product Cost | B56: 12 | C56: =D40 -> 1.1106734 | D56: =B56*C56 -> 13.328081
A57: Case Packaging | B57: 1 | C57: ='Ingredient Cost'!$D$108 -> 0.2 | D57: =B57*C57 -> 0.2
A58: Labour | B58: 250 | C58: =$C$39 -> 20 | D58: =C58/B58 -> 0.08
A59: Box end label | B59: 1 | C59: 0.01 | D59: =B59*C59 -> 0.01
A60: COST | D60: =SUM(D56:D59) -> 13.618081
A61: PER EACH | D61: =D60/12 -> 1.1348401

Sheet Sliced Haslet - 160g
A1: Grasmere Farm
A2: Product Costings
A3: Sliced Haslet - 160g
A4: INGREDIENTS | B4: . All allergens in BOLD.
A17: Ingredient Cost
B19: Cost | C19: Yield | D19: Total | F19: Shrinkage Calculation
A20: Sausage Meat | B20: ='Ingredient Cost'!D57 -> 61.36 | C20: 78 | D20: =B20/C20 -> 0.78666667 | F20: Start Weight | G20: =6*0.454 -> 2.724
A21: Vale Fat | B21: ='Ingredient Cost'!D78 -> 2.25 | C21: 0.2 | D21: =C21/B21 -> 0.088888889 | F21: Cook Shrinkage (90%) | G21: =G20*0.9 -> 2.4516
D22: =SUM(D20:D21) -> 0.87555556 | F22: Slice Yielf (90%) | G22: =G21*0.9 -> 2.20644
F23: Packs per Haslet | G23: =G22/0.165 -> 13.372364 | H23: 13 | I23: per haslet | J23: =13*6 -> 78 | K23: per tray
A25: Individual Packaged Products (excl. Labour)
A27: Individual
B28: Weight | C28: Cost | D28: Total
A29: Ingredient Cost | B29: 1 | C29: =D22 -> 0.87555556 | D29: =B29*C29 -> 0.87555556
A30: Packaging | B30: 1 | C30: ='Ingredient Cost'!D88 -> 0.09 | D30: =C30*B30 -> 0.09
A31: COST | D31: =SUM(D29:D30) -> 0.96555556
A34: Individual Packaged Products (incl. Labour) | D34: = | E34: COGS
A36: Individual
B37: Weight | C37: Cost | D37: Total
A38: Packaged Product Cost | B38: 1 | C38: =D31 -> 0.96555556 | D38: =B38*C38 -> 0.96555556
A39: Labour | B39: 55 | C39: ='Ingredient Cost'!$B$113 -> 20 | D39: =C39/B39 -> 0.36363636
A40: COST | D40: =SUM(D38:D39) -> 1.3291919
B42: Labour Percentage | D42: =D39/D38 -> 0.37660843
A43: CASES
A45: Case of 6
B46: Weight | C46: Cost | D46: Total
A47: Product Cost | B47: 6 | C47: =D40 -> 1.3291919 | D47: =B47*C47 -> 7.9751515
A48: Case Packaging | B48: 1 | C48: ='Ingredient Cost'!$D$108 -> 0.2 | D48: =B48*C48 -> 0.2
A49: Labour | B49: 250 | C49: =$C$39 -> 20 | D49: =C49/B49 -> 0.08
A50: Box end label | B50: 1 | C50: 0.01 | D50: =B50*C50 -> 0.01
A51: COST | D51: =SUM(D47:D50) -> 8.2651515
A52: PER EACH | D52: =D51/6 -> 1.3775253
A54: Case of 12
B55: Weight | C55: Cost | D55: Total
A56: Product Cost | B56: 12 | C56: =D40 -> 1.3291919 | D56: =B56*C56 -> 15.950303
A57: Case Packaging | B57: 1 | C57: ='Ingredient Cost'!$D$108 -> 0.2 | D57: =B57*C57 -> 0.2
A58: Labour | B58: 250 | C58: =$C$39 -> 20 | D58: =C58/B58 -> 0.08
A59: Box end label | B59: 1 | C59: 0.01 | D59: =B59*C59 -> 0.01
A60: COST | D60: =SUM(D56:D59) -> 16.240303
A61: PER EACH | D61: =D60/12 -> 1.3533586

Sheet Whole Haslet v2
A1: Grasmere Farm
A2: Product Costings
A3: Whole Haslet
A4: INGREDIENTS | B4: . All allergens in BOLD.
A17: Ingredient Cost
B19: Cost | C19: Yield | D19: Total
A20: Sausage Meat | B20: ='Ingredient Cost'!D57 -> 61.36 | C20: 36 | D20: =B20/C20 -> 1.7044444
A21: Vale Fat | B21: ='Ingredient Cost'!D78 -> 2.25 | C21: 0.03 | D21: =C21/B21 -> 0.013333333
D22: =SUM(D20:D21) -> 1.7177778
A25: Individual Packaged Products (excl. Labour)
A27: Individual
B28: Weight | C28: Cost | D28: Total
A29: Ingredient Cost | B29: 1 | C29: =D22 -> 1.7177778 | D29: =B29*C29 -> 1.7177778
A30: Packaging | B30: 1 | C30: ='Ingredient Cost'!D88 -> 0.09 | D30: =C30*B30 -> 0.09
A31: COST | D31: =SUM(D29:D30) -> 1.8077778
A34: Individual Packaged Products (incl. Labour) | D34: = | E34: COGS
A36: Individual
B37: Weight | C37: Cost | D37: Total
A38: Packaged Product Cost | B38: 1 | C38: =D31 -> 1.8077778 | D38: =B38*C38 -> 1.8077778
A39: Labour | B39: 55 | C39: ='Ingredient Cost'!$B$113 -> 20 | D39: =C39/B39 -> 0.36363636
A40: COST | D40: =SUM(D38:D39) -> 2.1714141
B42: Labour Percentage | D42: =D39/D38 -> 0.20115103
A43: CASES
A45: Case of 6
B46: Weight | C46: Cost | D46: Total
A47: Product Cost | B47: 6 | C47: =D40 -> 2.1714141 | D47: =B47*C47 -> 13.028485
A48: Case Packaging | B48: 1 | C48: ='Ingredient Cost'!D108 -> 0.2 | D48: =B48*C48 -> 0.2
A49: Labour | B49: 250 | C49: =C39 -> 20 | D49: =C49/B49 -> 0.08
A50: Box end label | B50: 1 | C50: 0.01 | D50: =B50*C50 -> 0.01
A51: COST | D51: =SUM(D47:D50) -> 13.318485
A52: PER EACH | D52: =D51/6 -> 2.2197475

Sheet Scoth Eggs v2
A1: Grasmere Farm
A2: Product Costings
A3: Scotch Eggs
A4: INGREDIENTS | B4: . All allergens in BOLD.
A17: Ingredient Cost
B19: Cost | C19: Yield | D19: Total
A20: Scotch Meat | B20: ='Ingredient Cost'!D54 -> 0.34 | C20: 1 | D20: =B20/C20 -> 0.34
A21: Egg | B21: ='Ingredient Cost'!D16 -> 0.27 | C21: 1 | D21: =B21/C21 -> 0.27
A22: Crumb | B22: ='Ingredient Cost'!D17 -> 1.26 | C22: 60 | D22: =B22/C22 -> 0.021
A23: Egg Wash / Flour | B23: ='Ingredient Cost'!D7 -> 0.62 | C23: 30 | D23: =B23/C23 -> 0.020666667
D24: =SUM(D20:D23) -> 0.65166667
A27: Individual Packaged Products (excl. Labour)
A29: Individual | F29: Twin
B30: Weight | C30: Cost | D30: Total | G30: Weight | H30: Cost | I30: Total
A31: Ingredient Cost | B31: 1 | C31: =D24 -> 0.65166667 | D31: =B31*C31 -> 0.65166667 | F31: Ingredient Cost | G31: 2 | H31: =D24 -> 0.65166667 | I31: =G31*H31 -> 1.3033333
A32: Packaging | B32: 1 | C32: 0.02 | D32: =C32*B32 -> 0.02 | F32: Packaging | G32: 1 | H32: ='Ingredient Cost'!D88 -> 0.09 | I32: =H32*G32 -> 0.09
A33: COST | D33: =SUM(D31:D32) -> 0.67166667 | F33: COST | I33: =SUM(I31:I32) -> 1.3933333
A36: Individual Packaged Products (incl. Labour) | D36: = | E36: COGS
A38: Individual | F38: Twin
B39: Weight | C39: Cost | D39: Total | G39: Weight | H39: Cost | I39: Total
A40: Packaged Product Cost | B40: 1 | C40: =D33 -> 0.67166667 | D40: =B40*C40 -> 0.67166667 | F40: Packaged Product Cost | G40: 1 | H40: =I33 -> 1.3933333 | I40: =G40*H40 -> 1.3933333
A41: Labour | B41: 100 | C41: ='Ingredient Cost'!$B$113 -> 20 | D41: =C41/B41 -> 0.2 | F41: Labour | G41: 100 | H41: ='Ingredient Cost'!$B$113 -> 20 | I41: =H41/G41 -> 0.2
A42: COST | D42: =SUM(D40:D41) -> 0.87166667 | F42: COST | I42: =SUM(I40:I41) -> 1.5933333
B44: Labour Percentage | D44: =D41/D40 -> 0.29776675
A45: CASES
A47: Individual x6 | F47: Twin x6
B48: Weight | C48: Cost | D48: Total | G48: Weight | H48: Cost | I48: Total
A49: Product Cost | B49: 6 | C49: =D42 -> 0.87166667 | D49: =B49*C49 -> 5.23 | F49: Product Cost | G49: 6 | H49: =I42 -> 1.5933333 | I49: =G49*H49 -> 9.56
A50: Case Packaging | B50: 1 | C50: ='Ingredient Cost'!D108 -> 0.2 | D50: =B50*C50 -> 0.2 | F50: Case Packaging | G50: 1 | H50: ='Ingredient Cost'!D108 -> 0.2 | I50: =G50*H50 -> 0.2
A51: Labour | B51: 250 | C51: =C41 -> 20 | D51: =C51/B51 -> 0.08 | F51: Labour | G51: 250 | H51: =C41 -> 20 | I51: =H51/G51 -> 0.08
A52: Box end label | B52: 1 | C52: 0.01 | D52: =B52*C52 -> 0.01 | F52: Box end label | G52: 1 | H52: 0.01 | I52: =G52*H52 -> 0.01
A53: COST | D53: =SUM(D49:D52) -> 5.52 | F53: COST | I53: =SUM(I49:I52) -> 9.85
A54: PER EACH | D54: =D53/6 -> 0.92 | F54: PER EACH | I54: =I53/6 -> 1.6416667
A56: Individual x9 | F56: Twin x9
B57: Weight | C57: Cost | D57: Total | G57: Weight | H57: Cost | I57: Total
A58: Product Cost | B58: 9 | C58: =D42 -> 0.87166667 | D58: =B58*C58 -> 7.845 | F58: Product Cost | G58: 9 | H58: =I42 -> 1.5933333 | I58: =G58*H58 -> 14.34
A59: Case Packaging | B59: 1 | C59: ='Ingredient Cost'!D108 -> 0.2 | D59: =B59*C59 -> 0.2 | F59: Case Packaging | G59: 1 | H59: ='Ingredient Cost'!D108 -> 0.2 | I59: =G59*H59 -> 0.2
A60: Labour | B60: 250 | C60: =C41 -> 20 | D60: =C60/B60 -> 0.08 | F60: Labour | G60: 250 | H60: =C41 -> 20 | I60: =H60/G60 -> 0.08
A61: Box end label | B61: 1 | C61: 0.01 | D61: =B61*C61 -> 0.01 | F61: Box end label | G61: 1 | H61: 0.01 | I61: =G61*H61 -> 0.01
A62: COST | D62: =SUM(D58:D61) -> 8.135 | F62: COST | I62: =SUM(I58:I61) -> 14.63
A63: PER EACH | D63: =D62/9 -> 0.90388889 | F63: PER EACH | I63: =I62/9 -> 1.6255556

Sheet Jumbo Sausage Roll v2
A1: Grasmere Farm
A2: Product Costings
A3: Jumbo Sausage Roll
A4: INGREDIENTS | B4: . All allergens in BOLD.
A17: Ingredient Cost
B19: Cost | C19: Yield | D19: Total
A20: Strips | B20: 56.25 | C20: 180 | D20: =B20/C20 -> 0.3125
A21: Pukka Pastry (roll) | B21: 20.87 | C21: 148 | D21: =B21/C21 -> 0.14101351
D22: =SUM(D20:D21) -> 0.45351351
A25: Individual Packaged Products (excl. Labour)
A27: Small - Cooked
B28: Weight | C28: Cost | D28: Total
A29: Ingredient Cost | B29: 1 | C29: =D22 -> 0.45351351 | D29: =B29*C29 -> 0.45351351
A30: Packaging | B30: 1 | C30: 0.09 | D30: =C30*B30 -> 0.09
A31: COST | D31: =SUM(D29:D30) -> 0.54351351
A34: Individual Packaged Products (incl. Labour) | D34: = | E34: COGS
A36: Jumbo
B37: Weight | C37: Cost | D37: Total
A38: Packaged Product Cost | B38: 1 | C38: =D31 -> 0.54351351 | D38: =B38*C38 -> 0.54351351
A39: Labour | B39: 120 | C39: ='Ingredient Cost'!$B$113 -> 20 | D39: =C39/B39 -> 0.16666667
A40: COST | D40: =SUM(D38:D39) -> 0.71018018
B42: Labour Percentage | D42: =D39/D38 -> 0.30664678
A43: CASES
A45: 10 per case | F45: 48* Box
B46: Weight | C46: Cost | D46: Total | G46: Weight | H46: Cost | I46: Total
A47: Product Cost | B47: 10 | C47: =D40 -> 0.71018018 | D47: =B47*C47 -> 7.1018018 | F47: Product Cost | G47: 48 | H47: =D22 -> 0.45351351 | I47: =G47*H47 -> 21.768649
A48: Case Packaging | B48: 1 | C48: ='Ingredient Cost'!D108 -> 0.2 | D48: =B48*C48 -> 0.2 | F48: Case Packaging | G48: 1 | H48: ='Ingredient Cost'!D108 -> 0.2 | I48: =G48*H48 -> 0.2
A49: Labour | B49: 250 | C49: =C39 -> 20 | D49: =C49/B49 -> 0.08 | F49: Labour | G49: 40 | H49: =C39 -> 20 | I49: =G49/H49 -> 2
A50: Box end label | B50: 1 | C50: 0.01 | D50: =B50*C50 -> 0.01 | F50: Box end label | G50: 1 | H50: 0.01 | I50: =G50*H50 -> 0.01
A51: COST | D51: =SUM(D47:D50) -> 7.3918018 | F51: COST | I51: =SUM(I47:I50) -> 23.978649
A52: PER EACH | D52: =D51/9 -> 0.82131131 | F52: PER EACH | I52: =I51/48 -> 0.49955518

Sheet Sausage Roll
A1: Grasmere Farm Manual
A2: Product Page
A3: Sausage Roll
A4: INGREDIENTS | B4: . All allergens in BOLD.
A16: Product | B16: Raw Small Sausage Roll | F16: Product | G16: Raw Small Sausage Roll boxed | K16: Product | L16: Raw Flavoured Sausage Roll boxed
B17: Weight | C17: Cost | D17: Total | G17: Weight | H17: Cost | I17: Total | L17: Weight | M17: Cost | N17: Total
A18: Sausage Strip | B18: 0.091 | C18: ='Ingredient Cost'!D50 -> 56.25 | D18: =B18*C18 -> 5.11875 | F18: Sausage Roll | G18: 60 | H18: =D24 -> 5.2107645 | I18: =G18*H18 -> 312.64587 | K18: Sausage Roll | L18: 32 | M18: =D24 -> 5.2107645 | N18: =L18*M18 -> 166.74447
A19: Pukka Pasty | B19: 0.024 | C19: ='Ingredient Cost'!D9 -> 1.94 | D19: =B19*C19 -> 0.04656 | F19: Case | G19: 1 | H19: ='Ingredient Cost'!D109 -> 0.27 | I19: =G19*H19 -> 0.27 | K19: Case | L19: 1 | M19: ='Ingredient Cost'!D108 -> 0.2 | N19: =L19*M19 -> 0.2
A20: Labour | B20: 330 | C20: 15 | D20: =C20/B20 -> 0.045454545 | F20: Cooking Paper | G20: 2 | H20: ='Ingredient Cost'!D86 -> 0.12 | I20: =G20*H20 -> 0.24 | K20: Cooking Paper | L20: 2 | M20: ='Ingredient Cost'!D86 -> 0.12 | N20: =L20*M20 -> 0.24
F21: Label | G21: 1 | H21: 0.01 | I21: =H21/G21 -> 0.01 | K21: Label | L21: 1 | M21: 0.01 | N21: =M21/L21 -> 0.01
F22: Labour | G22: 6 | H22: 15 | I22: =H22/G22 -> 2.5 | K22: Labour | L22: 8 | M22: 15 | N22: =M22/L22 -> 1.875
A24: COST | D24: =SUM(D18:D20) -> 5.2107645
F25: COST | I25: =SUM(I18:I22) -> 315.66587 | K25: COST | N25: =SUM(N18:N22) -> 169.06947
F26: PER EACH | I26: =I25/60 -> 5.2610979 | K26: PER EACH | N26: =N25/32 -> 5.2834208
A28: Product | B28: Cooked Small Sausage Roll Twin Pack
B29: Weight | C29: Cost | D29: Total
A30: Twin Packs | B30: 8 | C30: =D24*2 -> 10.421529 | D30: =B30*C30 -> 83.372233
A31: Cooking Paper | C31: ='Ingredient Cost'!D86 -> 0.12 | D31: =C31 -> 0.12
A32: Packaging | B32: 8 | C32: ='Ingredient Cost'!D90 -> 0.22 | D32: =B32*C32 -> 1.76
A33: Case | C33: ='Ingredient Cost'!D109 -> 0.27 | D33: =C33 -> 0.27
A34: Label | C34: 0.05 | D34: =C34 -> 0.05
A35: Labour | B35: 20 | C35: 15 | D35: =C35/B35 -> 0.75
B37: =SUM(B30:B32) -> 16 | D37: =SUM(D30:D32) -> 85.252233
A39: COST | D39: =D37 -> 85.252233
A40: PER TWIN PACK | D40: =D39/8 -> 10.656529

Sheet Bacon Puff
A1: Grasmere Farm Manual
A2: Product Page
A3: Bacon & Cheese Puff
A4: INGREDIENTS | B4: . All allergens in BOLD.
A16: Product | B16: Raw Bacon & Cheese Puff | G16: Product | H16: Raw Bacon & Cheese Puff boxed
B17: Weight | C17: Cost | D17: Total | H17: Weight | I17: Cost | J17: Total
A18: Smoked Bacon | B18: 0.025 | C18: 2.9 | D18: =B18*C18 -> 0.0725 | G18: Puff | H18: 28 | I18: =D26 -> 0.44894 | J18: =H18*I18 -> 12.57032
A19: Cheese | B19: 0.018 | C19: ='Ingredient Cost'!D42 -> 0.17 | D19: =B19*C19 -> 0.00306 | G19: Case | H19: 1 | I19: ='Ingredient Cost'!D108 -> 0.2 | J19: =H19*I19 -> 0.2
A20: Tomato Pureee | B20: 0.01 | C20: ='Ingredient Cost'!D43 -> 0.31 | D20: =B20*C20 -> 0.0031 | G20: Cooking Paper | H20: 2 | I20: ='Ingredient Cost'!D86 -> 0.12 | J20: =H20*I20 -> 0.24
A21: Pasty | B21: 0.062 | C21: ='Ingredient Cost'!D9 -> 1.94 | D21: =B21*C21 -> 0.12028 | G21: Labour | I21: 15 | J21: =I21/H21 -> #DIV/0!
A22: Labour | B22: 60 | C22: 15 | D22: =C22/B22 -> 0.25
A26: COST | D26: =SUM(D18:D22) -> 0.44894 | G26: COST | J26: =SUM(J18:J20) -> 13.01032
G27: PER EACH | J27: =J26/48 -> 0.27104833
A28: Product | B28: Raw Large Bacon & Cheese Puff | G28: Product | H28: Raw Large Bacon & Cheese Puff boxed
B29: Weight | C29: Cost | D29: Total | H29: Weight | I29: Cost | J29: Total
A30: Smoked Bacon | B30: 0.032 | D30: =B30*C30 -> 0 | G30: Puff | H30: 28 | I30: =D37 -> 0.966 | J30: =H30*I30 -> 27.048
A31: Cheese | B31: 234 | D31: =B31*C31 -> 0 | G31: Case | H31: 1 | I31: ='Ingredient Cost'!D109 -> 0.27 | J31: =H31*I31 -> 0.27
A32: Tomato Pureee | B32: 0.013 | D32: =B32*C32 -> 0 | G32: Cooking Paper | H32: 2 | I32: ='Ingredient Cost'!D97 -> 0.2 | J32: =H32*I32 -> 0.4
A33: Pasty | B33: 0.08 | C33: ='Ingredient Cost'!D20 -> 8.95 | D33: =B33*C33 -> 0.716 | G33: Labour | I33: 15 | J33: =I33/H33 -> #DIV/0!
A34: Labour | B34: 60 | C34: 15 | D34: =C34/B34 -> 0.25
A37: COST | D37: =SUM(D30:D34) -> 0.966 | G37: COST | J37: =SUM(J30:J32) -> 27.718
G38: PER EACH | J38: =J37/48 -> 0.57745833

Sheet Chorizo Puff
A1: Grasmere Farm Manual
A2: Product Page
A3: Chorizo Puff
A4: INGREDIENTS | B4: . All allergens in BOLD.
A16: Product | B16: Raw Chorizo Puff | G16: Product | H16: Raw Chorizo & Cheese Puff boxed
B17: Weight | C17: Cost | D17: Total | H17: Weight | I17: Cost | J17: Total
A18: Chorizo | B18: 0.025 | C18: 6 | D18: =B18*C18 -> 0.15 | G18: Puff | H18: 28 | I18: =D26 -> 0.52028 | J18: =H18*I18 -> 14.56784
A19: Cheese | B19: 0.018 | D19: =B19*C19 -> 0 | G19: Case | H19: 1 | I19: ='Ingredient Cost'!D108 -> 0.2 | J19: =H19*I19 -> 0.2
A20: Tomato Pureee | B20: 0.01 | D20: =C20/B20 -> 0 | G20: Cooking Paper | H20: 2 | I20: ='Ingredient Cost'!D86 -> 0.12 | J20: =H20*I20 -> 0.24
A21: Pasty | B21: 0.062 | C21: ='Ingredient Cost'!D9 -> 1.94 | D21: =B21*C21 -> 0.12028 | G21: Labour | I21: 15 | J21: =I21/H21 -> #DIV/0!
A22: Labour | B22: 60 | C22: 15 | D22: =C22/B22 -> 0.25
A26: COST | D26: =SUM(D18:D22) -> 0.52028 | G26: COST | J26: =SUM(J18:J20) -> 15.00784
G27: PER EACH | J27: =J26/48 -> 0.31266333

Sheet Onion Puff
A1: Grasmere Farm Manual
A2: Product Page
A3: Chorizo Puff
A4: INGREDIENTS | B4: . All allergens in BOLD.
A16: Product | B16: Raw Chorizo Puff | G16: Product | H16: Raw Chorizo & Cheese Puff boxed
B17: Weight | C17: Cost | D17: Total | H17: Weight | I17: Cost | J17: Total
A18: Onion | B18: 0.025 | C18: ='Ingredient Cost'!D34 -> 5.27 | D18: =B18*C18 -> 0.13175 | G18: Puff | H18: 28 | I18: =D26 -> 0.50203 | J18: =H18*I18 -> 14.05684
A19: Cheese | B19: 0.018 | D19: =B19*C19 -> 0 | G19: Case | H19: 1 | I19: ='Ingredient Cost'!D108 -> 0.2 | J19: =H19*I19 -> 0.2
A20: Tomato Pureee | B20: 0.01 | D20: =C20/B20 -> 0 | G20: Cooking Paper | H20: 2 | I20: ='Ingredient Cost'!D86 -> 0.12 | J20: =H20*I20 -> 0.24
A21: Pasty | B21: 0.062 | C21: ='Ingredient Cost'!D9 -> 1.94 | D21: =B21*C21 -> 0.12028 | G21: Labour | I21: 15 | J21: =I21/H21 -> #DIV/0!
A22: Labour | B22: 60 | C22: 15 | D22: =C22/B22 -> 0.25
A26: COST | D26: =SUM(D18:D22) -> 0.50203 | G26: COST | J26: =SUM(J18:J20) -> 14.49684
G27: PER EACH | J27: =J26/48 -> 0.3020175

Sheet Pork Pie v2
A1: Grasmere Farm
A2: Product Costings
A3: Pork Pie
A4: INGREDIENTS | B4: . All allergens in BOLD.
A16: Sub-recipes
A18: Seasoning | F18: Pork Pie Meat | K18: Hot Water Pastry | P18: Pork Pie Meat from Butchery
B19: Weight | C19: Cost | D19: Total | G19: Weight | H19: Cost | I19: Total | L19: Weight | M19: Cost | N19: Total | Q19: Cost | R19: Units per tray | S19: Cost per unit
A20: Salt | B20: 5 | C20: ='Ingredient Cost'!$D$8 -> 0.54 | D20: =B20*C20 -> 2.7 | F20: Pork Pie Meat | G20: 14.25 | H20: ='Ingredient Cost'!$D$47 -> 21.25 | I20: =G20*H20 -> 302.8125 | K20: Water | L20: 2.5 | P20: Mini | Q20: 52.5 | R20: 259 | S20: =Q20/R20 -> 0.2027027
A21: White Pepper | B21: 1.7 | C21: ='Ingredient Cost'!$D$10 -> 11 | D21: =B21*C21 -> 18.7 | F21: Seasoning | G21: 0.4 | H21: =$D$25 -> 43.987 | I21: =G21*H21 -> 17.5948 | K21: Fat/Butter | L21: 4 | M21: ='Ingredient Cost'!$D$6 -> 2.06 | N21: =L21*M21 -> 8.24 | P21: Small | Q21: 52.5 | R21: 101 | S21: =Q21/R21 -> 0.51980198
A22: Jelly | B22: 1.1 | C22: ='Ingredient Cost'!$D$79 -> 17.85 | D22: =B22*C22 -> 19.635 | K22: Flour | L22: 8 | M22: ='Ingredient Cost'!$D$7 -> 0.62 | N22: =L22*M22 -> 4.96 | P22: Med | Q22: 52.5 | R22: 50 | S22: =Q22/R22 -> 1.05
A23: Maize | B23: 0.08 | C23: ='Ingredient Cost'!$D$25 -> 36.9 | D23: =B23*C23 -> 2.952 | K23: Salt | L23: 0.15 | M23: ='Ingredient Cost'!$D$8 -> 0.54 | N23: =L23*M23 -> 0.081
A24: Mustard | B24: 0.08 | C24: ='Ingredient Cost'!$D$23 -> 9.37 | D24: =B24*C24 -> 0.7496
A25: Total Weight | B25: =SUM(B20:B24) -> 7.96 | D25: =SUM(D20:D23) -> 43.987 | F25: Total Weight | G25: =SUM(G20:G24) -> 14.65 | I25: =SUM(I20:I23) -> 320.4073 | K25: Total Weight | L25: =L20+L21+L22+L23 -> 14.65 | N25: =SUM(N20:N23) -> 13.281
A27: COST | D27: =D25/B25 -> 5.526005 | F27: COST | I27: =I25/G25 -> 21.870805 | K27: COST | N27: =N25/L25 -> 0.9065529
A29: COGS
A31: Mini | F31: Small | K31: Medium
B32: Weight | C32: Cost | D32: Total | G32: Weight | H32: Cost | I32: Total | L32: Weight | M32: Cost | N32: Total
A33: Pastry Base | C33: ='Pastry Costing'!$C$23 -> 0.058925939 | D33: =C33 -> 0.058925939 | F33: Pastry Base | H33: ='Pastry Costing'!$C$24 -> 0.10878635 | I33: =H33 -> 0.10878635 | K33: Pastry Base | M33: ='Pastry Costing'!$C$25 -> 0.19037611 | N33: =M33 -> 0.19037611
A34: Pork Meat | D34: =S20 -> 0.2027027 | F34: Pork Meat | I34: =S21 -> 0.51980198 | K34: Pork Meat | N34: =S22 -> 1.05
A35: Jelly | B35: 0.01 | C35: ='Ingredient Cost'!$D$79 -> 17.85 | D35: =B35*C35 -> 0.1785 | F35: Jelly | G35: 0.02 | H35: 0 | I35: =G35*H35 -> 0 | K35: Jelly | L35: 0.03 | M35: ='Ingredient Cost'!$D$79 -> 17.85 | N35: =L35*M35 -> 0.5355
A36: Pastry Lid | C36: ='Pastry Costing'!$E$23 -> 0.018131058 | D36: =C36 -> 0.018131058 | F36: Pastry Lid | H36: ='Pastry Costing'!$E$24 -> 0.036262116 | I36: =H36 -> 0.036262116 | K36: Pastry Lid | M36: ='Pastry Costing'!$E$25 -> 0.054393174 | N36: =M36 -> 0.054393174
A37: Foil | C37: ='Ingredient Cost'!$D$98 -> 0.02 | D37: =C37 -> 0.02 | F37: Foil | H37: ='Ingredient Cost'!$D$99 -> 0.07 | I37: =H37 -> 0.07 | K37: Foil | M37: ='Ingredient Cost'!$D$100 -> 0.08 | N37: =M37 -> 0.08
A38: Labour | B38: 240 | C38: 20 | D38: =C38/B38 -> 0.083333333 | F38: Labour | G38: 240 | H38: 20 | I38: =H38/G38 -> 0.083333333 | K38: Labour | L38: 200 | M38: 20 | N38: =M38/L38 -> 0.1
A39: Packaging | B39: 1 | C39: 0.01 | D39: =C39/B39 -> 0.01 | F39: Packaging | G39: 1 | H39: 0.01 | I39: =H39/G39 -> 0.01 | K39: Packaging | L39: 1 | M39: 0.01 | N39: =M39/L39 -> 0.01
A40: Labour (packing) | B40: 240 | C40: 20 | D40: =C40/B40 -> 0.083333333 | F40: Labour (packing) | G40: 240 | H40: 20 | I40: =H40/G40 -> 0.083333333 | K40: Labour (packing) | L40: 240 | M40: 20 | N40: =M40/L40 -> 0.083333333
A42: COST | D42: =SUM(D33:D40) -> 0.65492637 | F42: COST | I42: =SUM(I33:I41) -> 0.91151711 | K42: COST | N42: =SUM(N33:N40) -> 2.1036026
A44: 2LB | F44: 3LB
B45: Weight | C45: Cost | D45: Total | G45: Weight | H45: Cost | I45: Total
A46: Pastry Base | C46: ='Pastry Costing'!$C$26 -> 0.40341604 | D46: =C46 -> 0.40341604 | F46: Pastry Base | H46: ='Pastry Costing'!$C$27 -> 0.40341604 | I46: =H46 -> 0.40341604
A47: Pork Meat | B47: 0.1 | C47: 52.5 | D47: =B47*C47 -> 5.25 | F47: Pork Meat | G47: 0.2 | H47: 52.5 | I47: =G47*H47 -> 10.5
A48: Jelly | B48: 0.05 | C48: ='Ingredient Cost'!$D$79 -> 17.85 | D48: =B48*C48 -> 0.8925 | F48: Jelly | G48: 0.05 | H48: ='Ingredient Cost'!$D$79 -> 17.85 | I48: =G48*H48 -> 0.8925
A49: Pastry Lid | C49: ='Pastry Costing'!$E$26 -> 0.054393174 | D49: =C49 -> 0.054393174 | F49: Pastry Lid | H49: ='Pastry Costing'!$E$27 -> 0.14958123 | I49: =H49 -> 0.14958123
A50: Labour | B50: 16 | C50: 20 | D50: =C50/B50 -> 1.25 | F50: Labour | G50: 10 | H50: 20 | I50: =H50/G50 -> 2
A51: Foil | C51: ='Ingredient Cost'!$D$100 -> 0.08 | D51: =C51 -> 0.08 | F51: Foil | H51: ='Ingredient Cost'!$D$100 -> 0.08 | I51: =H51 -> 0.08
A52: Packaging | B52: 1 | C52: 0.01 | D52: =C52/B52 -> 0.01 | F52: Packaging | G52: 1 | H52: 0.01 | I52: =H52/G52 -> 0.01
A53: Labour (packing) | B53: 240 | C53: 20 | D53: =C53/B53 -> 0.083333333 | F53: Labour (packing) | G53: 240 | H53: 20 | I53: =H53/G53 -> 0.083333333
A55: COST | D55: =SUM(D46:D53) -> 8.0236425 | F55: COST | I55: =SUM(I46:I54) -> 14.118831
A58: CASES
A60: Mini pack of 2 | F60: Mini pack of 6
B61: Weight | C61: Cost | D61: Total | G61: Weight | H61: Cost | I61: Total
A62: Pie | B62: 2 | C62: =D42 -> 0.65492637 | D62: =B62*C62 -> 1.3098527 | F62: Pie | G62: 6 | H62: =D42 -> 0.65492637 | I62: =G62*H62 -> 3.9295582
A63: Packaging | B63: 1 | C63: 0.01 | D63: =C63/B63 -> 0.01 | F63: Packaging | G63: 1 | H63: 0.01 | I63: =H63/G63 -> 0.01
A64: Labour (packing) | B64: 240 | C64: 20 | D64: =C64/B64 -> 0.083333333 | F64: Labour (packing) | G64: 240 | H64: 20 | I64: =H64/G64 -> 0.083333333
A66: COST | D66: =SUM(D57:D64) -> 1.4031861 | F66: COST | I66: =SUM(I57:I64) -> 4.0228915
A71: Small - Case of 5 | F71: Small - Case of 8
B72: Weight | C72: Cost | D72: Total | G72: Weight | H72: Cost | I72: Total
A73: Pie | B73: 5 | C73: =$I$42 -> 0.91151711 | D73: =B73*C73 -> 4.5575856 | F73: Pie | G73: 8 | H73: =$I$42 -> 0.91151711 | I73: =G73*H73 -> 7.2921369
A74: Cooking Paper | B74: 1 | C74: ='Ingredient Cost'!$D$86 -> 0.12 | D74: =B74*C74 -> 0.12 | F74: Cooking Paper | G74: 1 | H74: ='Ingredient Cost'!$D$86 -> 0.12 | I74: =G74*H74 -> 0.12
A75: Packaging | B75: 5 | C75: ='Ingredient Cost'!$D$89 -> 0.06 | D75: =B75*C75 -> 0.3 | F75: Packaging | G75: 5 | H75: ='Ingredient Cost'!$D$89 -> 0.06 | I75: =G75*H75 -> 0.3
A76: Case | B76: 1 | C76: ='Ingredient Cost'!$D$109 -> 0.27 | D76: =B76*C76 -> 0.27 | F76: Case | G76: 1 | H76: ='Ingredient Cost'!$D$109 -> 0.27 | I76: =G76*H76 -> 0.27
A77: Labour | B77: 20 | C77: 20 | D77: =C77/B77 -> 1 | F77: Labour | G77: 20 | H77: 20 | I77: =H77/G77 -> 1
A82: COST | D82: =D73+D74+D75+D76+D77 -> 6.2475856 | F82: COST | I82: =I73+I74+I75+I76+I77 -> 8.9821369
A83: PER EACH | D83: =D82/5 -> 1.2495171 | F83: PER EACH | I83: =I82/8 -> 1.1227671
A85: Medium - Case of 4 | F85: Medium - Case of 6
B86: Weight | C86: Cost | D86: Total | G86: Weight | H86: Cost | I86: Total
A87: Pie | B87: 4 | C87: =N42 -> 2.1036026 | D87: =B87*C87 -> 8.4144105 | F87: Pie | G87: 6 | H87: =N42 -> 2.1036026 | I87: =G87*H87 -> 12.621616
A88: Cooking Paper | B88: 1 | C88: ='Ingredient Cost'!$D$86 -> 0.12 | D88: =B88*C88 -> 0.12 | F88: Cooking Paper | G88: 1 | H88: ='Ingredient Cost'!$D$86 -> 0.12 | I88: =G88*H88 -> 0.12
A89: Packaging | B89: 4 | C89: ='Ingredient Cost'!$D$89 -> 0.06 | D89: =B89*C89 -> 0.24 | F89: Packaging | G89: 6 | H89: ='Ingredient Cost'!$D$89 -> 0.06 | I89: =G89*H89 -> 0.36
A90: Case | B90: 1 | C90: ='Ingredient Cost'!$D$109 -> 0.27 | D90: =B90*C90 -> 0.27 | F90: Case | G90: 1 | H90: ='Ingredient Cost'!$D$109 -> 0.27 | I90: =G90*H90 -> 0.27
A91: Labour | B91: 20 | C91: 20 | D91: =C91/B91 -> 1 | F91: Labour | G91: 20 | H91: 20 | I91: =H91/G91 -> 1
A96: COST | D96: =D87+D88+D89+D90+D91 -> 10.04441 | F96: COST | I96: =I87+I88+I89+I90+I91 -> 14.371616
A97: PER EACH | D97: =D96/4 -> 2.5111026 | F97: PER EACH | I97: =I96/6 -> 2.3952693

Sheet 1lb Pork Pie
A1: Grasmere Farm Manual
A2: Product Page
A3: Pork Pies
A4: INGREDIENTS | B4: . All allergens in BOLD.
A16: Product | B16: Pork Pie Seasoning | F16: Product | G16: Pork Pie Meat Mix | K16: Product | L16: Pork Pie Meat & Stilton Mix | U16: 240
B17: Weight | C17: Cost | D17: Total | G17: Weight | H17: Cost | I17: Total | L17: Weight | M17: Cost | N17: Total | U17: 480
A18: Salt | B18: 5 | C18: ='Ingredient Cost'!$D$8 -> 0.54 | D18: =B18*C18 -> 2.7 | F18: Pork Pie Meat | G18: 14.25 | H18: ='Ingredient Cost'!$D$47 -> 21.25 | I18: =G18*H18 -> 302.8125 | K18: Pork Pie Meat | L18: 14.25 | M18: ='Ingredient Cost'!$D$47 -> 21.25 | N18: =L18*M18 -> 302.8125 | U18: 240
A19: White Pepper | B19: 1.7 | C19: ='Ingredient Cost'!$D$10 -> 11 | D19: =B19*C19 -> 18.7 | F19: Seasoning | G19: 0.4 | H19: =$D$25 -> 5.526005 | I19: =G19*H19 -> 2.210402 | K19: Seasoning | L19: 0.4 | M19: =$I$25 -> 20.820676 | N19: =L19*M19 -> 8.3282704 | U19: 200
A20: Jelly | B20: 1.1 | C20: ='Ingredient Cost'!$D$79 -> 17.85 | D20: =B20*C20 -> 19.635 | K20: Stilton | L20: 1.1 | M20: ='Ingredient Cost'!$D$18 -> 4.75 | N20: =L20*M20 -> 5.225 | U20: 12
A21: Maize | B21: 0.08 | C21: ='Ingredient Cost'!$D$25 -> 36.9 | D21: =B21*C21 -> 2.952 | U21: 10
A22: Mustard | B22: 0.08 | C22: ='Ingredient Cost'!$D$23 -> 9.37 | D22: =B22*C22 -> 0.7496
B23: =SUM(B18:B22) -> 7.96 | D23: =SUM(D18:D21) -> 43.987 | G23: =SUM(G18:G22) -> 14.65 | I23: =SUM(I18:I21) -> 305.0229 | L23: =SUM(L18:L22) -> 15.75 | N23: =SUM(N18:N21) -> 316.36577
A25: COST | D25: =D23/B23 -> 5.526005 | F25: COST | I25: =I23/G23 -> 20.820676 | K25: COST | N25: =N23/L23 -> 20.086716
A27: Product | B27: Mini Pork Pie Stilton | F27: Product | G27: Mini Pork Pie lided | K27: Product | L27: Small | P27: Product | Q27: Small with Stilton | U27: Product | V27: Medium | Z27: Product | AA27: Medium lided with Stilton | AE27: Product | AF27: 2lb | AJ27: Product | AK27: 3lb
B28: Weight | C28: Cost | D28: Total | G28: Weight | H28: Cost | I28: Total | L28: Weight | M28: Cost | N28: Total | Q28: Weight | R28: Cost | S28: Total | V28: Weight | W28: Cost | X28: Total | AA28: Weight | AB28: Cost | AC28: Total | AF28: Weight | AG28: Cost | AH28: Total | AK28: Weight | AL28: Cost | AM28: Total
A29: Pastry Base | C29: ='Pastry Costing'!$C$23 -> 0.058925939 | D29: =C29 -> 0.058925939 | F29: Pastry Base | H29: ='Pastry Costing'!$C$23 -> 0.058925939 | I29: =H29 -> 0.058925939 | K29: Pastry Base | M29: ='Pastry Costing'!$C$24 -> 0.10878635 | N29: =M29 -> 0.10878635 | P29: Pastry Base | R29: ='Pastry Costing'!$C$24 -> 0.10878635 | S29: =R29 -> 0.10878635 | U29: Pastry Base | W29: ='Pastry Costing'!$C$25 -> 0.19037611 | X29: =W29 -> 0.19037611 | Z29: Pastry Base | AB29: ='Pastry Costing'!C25 -> 0.19037611 | AC29: =AB29 -> 0.19037611 | AE29: Pastry Base | AG29: ='Pastry Costing'!$C$26 -> 0.40341604 | AH29: =AG29 -> 0.40341604 | AJ29: Pastry Base | AL29: ='Pastry Costing'!$C$27 -> 0.40341604 | AM29: =AL29 -> 0.40341604
A30: Pork Meat | B30: 0.055 | C30: =$I$25 -> 20.820676 | D30: =B30*C30 -> 1.1451372 | F30: Pork Meat | G30: 0.055 | H30: =$I$25 -> 20.820676 | I30: =G30*H30 -> 1.1451372 | K30: Pork Meat | L30: 0.14 | M30: =$I$25 -> 20.820676 | N30: =L30*M30 -> 2.9148946 | P30: Pork Meat | Q30: 0.14 | R30: =$N$25 -> 20.086716 | S30: =Q30*R30 -> 2.8121402 | U30: Pork Meat | V30: 0.28 | W30: =$I$25 -> 20.820676 | X30: =V30*W30 -> 5.8297893 | Z30: Pork Meat | AA30: 0.28 | AB30: =N25 -> 20.086716 | AC30: =AA30*AB30 -> 5.6242804 | AE30: Pork Meat | AF30: 0.45 | AG30: =$I$25 -> 20.820676 | AH30: =AF30*AG30 -> 9.3693042 | AJ30: Pork Meat | AK30: 0.6 | AL30: =$I$25 -> 20.820676 | AM30: =AK30*AL30 -> 12.492406
A31: Stilton | B31: 0.015 | C31: ='Ingredient Cost'!$D$18 -> 4.75 | D31: =B31*C31 -> 0.07125 | F31: Jelly | G31: 0.01 | H31: ='Ingredient Cost'!$D$79 -> 17.85 | I31: =G31*H31 -> 0.1785 | K31: Jelly | L31: 0.02 | M31: 0 | N31: =L31*M31 -> 0 | P31: Jelly | Q31: 0.02 | R31: ='Ingredient Cost'!$D$79 -> 17.85 | S31: =Q31*R31 -> 0.357 | U31: Jelly | V31: 0.03 | W31: ='Ingredient Cost'!$D$79 -> 17.85 | X31: =V31*W31 -> 0.5355 | Z31: Jelly | AA31: 0.03 | AB31: ='Ingredient Cost'!D79 -> 17.85 | AC31: =AA31*AB31 -> 0.5355 | AE31: Jelly | AF31: 0.05 | AG31: ='Ingredient Cost'!$D$79 -> 17.85 | AH31: =AF31*AG31 -> 0.8925 | AJ31: Jelly | AK31: 0.05 | AL31: ='Ingredient Cost'!$D$79 -> 17.85 | AM31: =AK31*AL31 -> 0.8925
A32: Foil | B32: 1 | C32: ='Ingredient Cost'!$D$98 -> 0.02 | D32: =B32*C32 -> 0.02 | F32: Pastry Lid | H32: ='Pastry Costing'!$E$23 -> 0.018131058 | I32: =H32 -> 0.018131058 | K32: Pastry Lid | M32: ='Pastry Costing'!$E$24 -> 0.036262116 | N32: =M32 -> 0.036262116 | P32: Pastry Lid | R32: ='Pastry Costing'!$E$24 -> 0.036262116 | S32: =R32 -> 0.036262116 | U32: Pastry Lid | W32: ='Pastry Costing'!$E$25 -> 0.054393174 | X32: =W32 -> 0.054393174 | Z32: Pastry Lid | AB32: ='Pastry Costing'!E25 -> 0.054393174 | AC32: =AB32 -> 0.054393174 | AE32: Pastry Lid | AG32: ='Pastry Costing'!$E$26 -> 0.054393174 | AH32: =AG32 -> 0.054393174 | AJ32: Pastry Lid | AL32: ='Pastry Costing'!$E$27 -> 0.14958123 | AM32: =AL32 -> 0.14958123
A33: Labour | B33: 240 | C33: 15 | D33: =C33/B33 -> 0.0625 | F33: Foil | H33: ='Ingredient Cost'!$D$98 -> 0.02 | I33: =H33 -> 0.02 | K33: Foil | M33: ='Ingredient Cost'!$D$99 -> 0.07 | N33: =M33 -> 0.07 | P33: Foil | R33: ='Ingredient Cost'!$D$99 -> 0.07 | S33: =R33 -> 0.07 | U33: Foil | W33: ='Ingredient Cost'!$D$100 -> 0.08 | X33: =W33 -> 0.08 | Z33: Foil | AB33: ='Ingredient Cost'!D100 -> 0.08 | AC33: =AB33 -> 0.08 | AE33: Labour | AF33: 16 | AG33: 15 | AH33: =AG33/AF33 -> 0.9375 | AJ33: Labour | AK33: 10 | AL33: 15 | AM33: =AL33/AK33 -> 1.5
A34: Packaging | B34: 1 | C34: 0.01 | D34: =C34/B34 -> 0.01 | F34: Labour | G34: 240 | H34: 15 | I34: =H34/G34 -> 0.0625 | K34: Labour | L34: 240 | M34: 15 | N34: =M34/L34 -> 0.0625 | P34: Labour | Q34: 240 | R34: 15 | S34: =R34/Q34 -> 0.0625 | U34: Labour | V34: 200 | W34: 15 | X34: =W34/V34 -> 0.075 | Z34: Labour | AA34: 200 | AB34: 15 | AC34: =AB34/AA34 -> 0.075 | AE34: Foil | AG34: ='Ingredient Cost'!$D$100 -> 0.08 | AH34: =AG34 -> 0.08 | AJ34: Foil | AL34: ='Ingredient Cost'!$D$100 -> 0.08 | AM34: =AL34 -> 0.08
A35: Labour (packing) | B35: 240 | C35: 15 | D35: =C35/B35 -> 0.0625 | F35: Packaging | G35: 1 | H35: 0.01 | I35: =H35/G35 -> 0.01 | K35: Packaging | L35: 1 | M35: 0.01 | N35: =M35/L35 -> 0.01 | U35: Packaging | V35: 1 | W35: 0.01 | X35: =W35/V35 -> 0.01 | AE35: Packaging | AF35: 1 | AG35: 0.01 | AH35: =AG35/AF35 -> 0.01 | AJ35: Packaging | AK35: 1 | AL35: 0.01 | AM35: =AL35/AK35 -> 0.01
F36: Labour (packing) | G36: 240 | H36: 15 | I36: =H36/G36 -> 0.0625 | K36: Labour (packing) | L36: 240 | M36: 15 | N36: =M36/L36 -> 0.0625 | U36: Labour (packing) | V36: 240 | W36: 15 | X36: =W36/V36 -> 0.0625 | AE36: Labour (packing) | AF36: 240 | AG36: 15 | AH36: =AG36/$AF$36 -> 0.0625 | AJ36: Labour (packing) | AK36: 240 | AL36: 15 | AM36: =AL36/$AF$36 -> 0.0625
A38: COST | D38: =SUM(D29:D35) -> 1.4303131 | F38: COST | I38: =SUM(I29:I36) -> 1.5556942 | K38: COST | N38: =SUM(N29:N36) -> 3.2649431 | P38: COST | S38: =SUM(S29:S36) -> 3.4466886 | U38: COST | X38: =SUM(X29:X36) -> 6.8375585 | Z38: COST | AC38: =SUM(AC29:AC36) -> 6.5595496 | AE38: COST | AH38: =SUM(AH29:AH34) -> 11.737113 | AJ38: COST | AM38: =SUM(AM29:AM37) -> 15.590403
A40: Product | B40: Mini Pork Pie ROM
B41: Weight | C41: Cost | D41: Total | K41: Product | L41: Small Case of 5 | U41: Product | V41: Medium Case of 4 | Z41: Product | AA41: Medium topped
A42: Pastry Base | C42: ='Pastry Costing'!$C$23 -> 0.058925939 | D42: =C42 -> 0.058925939 | L42: Weight | M42: Cost | N42: Total | V42: Weight | W42: Cost | X42: Total | AA42: Weight | AB42: Cost | AC42: Total
A43: Pork Meat | B43: 0.055 | C43: =$I$25 -> 20.820676 | D43: =B43*C43 -> 1.1451372 | K43: Pie | L43: 5 | M43: =$N$38 -> 3.2649431 | N43: =L43*M43 -> 16.324715 | U43: Pie | V43: 4 | W43: =$X$38 -> 6.8375585 | X43: =V43*W43 -> 27.350234 | Z43: Pastry Base | AB43: ='Pastry Costing'!C39 -> 0 | AC43: =AB43 -> 0
A44: ROM | B44: 0.01 | C44: =ROM!$D$22 -> 8.0357895 | D44: =B44*C44 -> 0.080357895 | K44: Cooking Paper | L44: 1 | M44: ='Ingredient Cost'!$D$86 -> 0.12 | N44: =L44*M44 -> 0.12 | U44: Cooking Paper | V44: 1 | W44: ='Ingredient Cost'!$D$86 -> 0.12 | X44: =V44*W44 -> 0.12 | Z44: Pork Meat | AA44: 0.28 | AB44: =N39 -> 0 | AC44: =AA44*AB44 -> 0
A45: Foil | B45: 1 | C45: ='Ingredient Cost'!$D$98 -> 0.02 | D45: =B45*C45 -> 0.02 | K45: Packaging | L45: 5 | M45: ='Ingredient Cost'!$D$89 -> 0.06 | N45: =L45*M45 -> 0.3 | U45: Packaging | V45: 4 | W45: ='Ingredient Cost'!$D$90 -> 0.22 | X45: =V45*W45 -> 0.88 | Z45: Jelly | AA45: 0.03 | AB45: ='Ingredient Cost'!D93 -> 0.04 | AC45: =AA45*AB45 -> 0.0012
A46: Labour | B46: 240 | C46: 15 | D46: =C46/B46 -> 0.0625 | K46: Case | L46: 1 | M46: ='Ingredient Cost'!$D$109 -> 0.27 | N46: =L46*M46 -> 0.27 | U46: Case | V46: 1 | W46: ='Ingredient Cost'!$D$109 -> 0.27 | X46: =V46*W46 -> 0.27 | Z46: Pastry Lid | AB46: ='Pastry Costing'!E39 -> 0 | AC46: =AB46 -> 0
A47: Packaging | B47: 1 | C47: 0.01 | D47: =C47/B47 -> 0.01 | K47: Labour | L47: 20 | M47: 15 | N47: =M47/L47 -> 0.75 | U47: Labour | V47: 20 | W47: 15 | X47: =W47/V47 -> 0.75 | Z47: Foil | AB47: ='Ingredient Cost'!D117 -> 0 | AC47: =AB47 -> 0
A48: Labour (packing) | B48: 240 | C48: 15 | D48: =C48/B48 -> 0.0625 | Z48: Labour | AA48: 200 | AB48: 15 | AC48: =AB48/AA48 -> 0.075
A51: COST | D51: =SUM(D42:D48) -> 1.439421
K52: COST | N52: =N43+N44+N45+N46+N47 -> 17.764715 | U52: COST | X52: =X43+X44+X45+X46+X47 -> 29.370234 | Z52: COST | AC52: =SUM(AC43:AC50) -> 0.0762
A53: Product | B53: Mini Pork Pie ROM & Stilton | K53: PER EACH | N53: =N52/5 -> 3.5529431 | U53: PER EACH | X53: =X52/4 -> 7.3425585
B54: Weight | C54: Cost | D54: Total
A55: Pastry Base | C55: ='Pastry Costing'!$C$23 -> 0.058925939 | D55: =C55 -> 0.058925939
A56: Pork Meat | B56: 0.055 | C56: =$I$25 -> 20.820676 | D56: =B56*C56 -> 1.1451372
A57: ROM | B57: 0.01 | D57: =C57 -> 0
A58: Stilton | B58: 0.01 | C58: ='Ingredient Cost'!D18 -> 4.75 | D58: =B58*C58 -> 0.0475
A59: Foil | B59: 1 | C59: ='Ingredient Cost'!D98 -> 0.02 | D59: =B59*C59 -> 0.02
A60: Labour | B60: 240 | C60: 15 | D60: =C60/B60 -> 0.0625
A61: Packaging | B61: 1 | C61: 0.01 | D61: =C61/B61 -> 0.01
A62: Labour (packing) | B62: 240 | C62: 15 | D62: =C62/B62 -> 0.0625
A65: COST | D65: =SUM(D55:D61) -> 1.3440631
A67: Product | B67: Mini Pork Pie Lincs Poacher & Apple Chutney
B68: Weight | C68: Cost | D68: Total
A69: Pastry Base | C69: ='Pastry Costing'!C23 -> 0.058925939 | D69: =C69 -> 0.058925939
A70: Pork Meat | B70: 0.055 | C70: =I25 -> 20.820676 | D70: =B70*C70 -> 1.1451372
A71: Cheese | B71: 0.01 | C71: ='Ingredient Cost'!D19 -> 25.2 | D71: =B71*C71 -> 0.252
A72: Chutney | B72: 0.01 | C72: ='Ingredient Cost'!D36 -> 7.01 | D72: =B72*C72 -> 0.0701
A73: Foil | B73: 1 | C73: ='Ingredient Cost'!D98 -> 0.02 | D73: =B73*C73 -> 0.02
A74: Labour | B74: 240 | C74: 15 | D74: =C74/B74 -> 0.0625
A75: Packaging | B75: 1 | C75: 0.01 | D75: =C75/B75 -> 0.01
A76: Labour (packing) | B76: 240 | C76: 15 | D76: =C76/B76 -> 0.0625
A79: COST | D79: =SUM(D69:D75) -> 1.6186631
A81: Product | B81: Mini Pork Pie Spiced Apricot Chutney
B82: Weight | C82: Cost | D82: Total
A83: Pastry Base | C83: ='Pastry Costing'!C23 -> 0.058925939 | D83: =C83 -> 0.058925939
A84: Pork Meat | B84: 0.055 | C84: =I25 -> 20.820676 | D84: =B84*C84 -> 1.1451372
A85: Chutney | B85: 0.02 | C85: ='Ingredient Cost'!D36 -> 7.01 | D85: =B85*C85 -> 0.1402
A86: Foil | B86: 1 | C86: ='Ingredient Cost'!D98 -> 0.02 | D86: =B86*C86 -> 0.02
A87: Labour | B87: 240 | C87: 15 | D87: =C87/B87 -> 0.0625
A88: Packaging | B88: 1 | C88: 0.01 | D88: =C88/B88 -> 0.01
A89: Labour (packing) | B89: 240 | C89: 15 | D89: =C89/B89 -> 0.0625
A92: COST | D92: =SUM(D83:D88) -> 1.4367631

Sheet Hunters Pie
A1: Grasmere Farm Manual
A2: Product Page
A3: Hunter's Pie
A4: INGREDIENTS | B4: . All allergens in BOLD.
A16: Product | B16: Hunter's Pie Meat Mix
B17: Weight | C17: Cost | D17: Total
A18: Game Meat | B18: 6.3 | C18: ='Ingredient Cost'!D69 -> 0 | D18: =B18*C18 -> 0
A19: Lincs Saus Meat | B19: 6.3 | C19: ='Ingredient Cost'!D50 -> 56.25 | D19: =B19*C19 -> 354.375
A20: Red Wine | B20: 0.75 | D20: =B20*C20 -> 0
A21: Rusk | B21: 0.3 | C21: ='Ingredient Cost'!D27 -> 1.18 | D21: =B21*C21 -> 0.354
A22: Black Pepper | B22: 0.05 | C22: ='Ingredient Cost'!D10 -> 11 | D22: =B22*C22 -> 0.55
A23: Salt | B23: 0.02 | C23: ='Ingredient Cost'!D8 -> 0.54
B24: =SUM(B18:B23) -> 13.72 | D24: =SUM(D18:D21) -> 354.729
A26: COST | D26: =D24/B24 -> 25.854883
A28: Product | B28: Hunter's Pie | AE28: Product | AF28: 2lb | AJ28: Product | AK28: 3lb
B29: Weight | C29: Cost | D29: Total | AF29: Weight | AG29: Cost | AH29: Total | AK29: Weight | AL29: Cost | AM29: Total
A30: Pastry Base | B30: ='Pastry Costing'!B24 -> 0.12 | C30: ='Pastry Costing'!I14 -> 0.9065529 | D30: =B30*C30 -> 0.10878635 | AE30: Pastry Base | AG30: ='Pastry Costing'!C26 -> 0.40341604 | AH30: =AG30 -> 0.40341604 | AJ30: Pastry Base | AL30: ='Pastry Costing'!C27 -> 0.40341604 | AM30: =AL30 -> 0.40341604
A31: Meat | B31: 0.14 | C31: =D26 -> 25.854883 | D31: =B31*C31 -> 3.6196837 | AE31: Pork Meat | AF31: 0.45 | AG31: =I26 -> 0 | AH31: =AF31*AG31 -> 0 | AJ31: Pork Meat | AK31: 0.6 | AL31: =I26 -> 0 | AM31: =AK31*AL31 -> 0
A32: Jelly | B32: 0.02 | C32: ='Ingredient Cost'!D79 -> 17.85 | D32: =B32*C32 -> 0.357 | AE32: Jelly | AF32: 0.05 | AG32: ='Ingredient Cost'!D79 -> 17.85 | AH32: =AF32*AG32 -> 0.8925 | AJ32: Jelly | AK32: 0.05 | AL32: ='Ingredient Cost'!D79 -> 17.85 | AM32: =AK32*AL32 -> 0.8925
A33: Pastry Lid | B33: ='Pastry Costing'!D24 -> 0.04 | C33: ='Pastry Costing'!I14 -> 0.9065529 | D33: =B33*C33 -> 0.036262116 | AE33: Pastry Lid | AG33: ='Pastry Costing'!E26 -> 0.054393174 | AH33: =AG33 -> 0.054393174 | AJ33: Pastry Lid | AL33: ='Pastry Costing'!E27 -> 0.14958123 | AM33: =AL33 -> 0.14958123
A34: Cranberry | B34: 0.05 | C34: ='Ingredient Cost'!D38 -> 4.08 | D34: =B34*C34 -> 0.204 | AE34: Labour | AF34: 16 | AG34: 15 | AH34: =AG34/AF34 -> 0.9375 | AJ34: Labour | AK34: 10 | AL34: 15 | AM34: =AL34/AK34 -> 1.5
A35: Labour | B35: 16 | C35: 15 | D35: =C35/B35 -> 0.9375
A36: Packaging | B36: 1 | C36: 0.05 | D36: =C36/B36 -> 0.05
A39: COST | D39: =SUM(D30:D35) -> 5.2632321 | AE39: COST | AH39: =SUM(AH30:AH35) -> 2.2878092 | AJ39: COST | AM39: =SUM(AM30:AM35) -> 2.9454973

Sheet Sausage Roll v2
A1: Grasmere Farm
A2: Product Costings
A3: Jumbo Sausage Roll
A4: INGREDIENTS | B4: . All allergens in BOLD.
A17: Ingredient Cost
B19: Cost | C19: Yield | D19: Total
A20: Strips | B20: 56.25 | C20: 225 | D20: =B20/C20 -> 0.25
A21: Pukka Pastry (roll) | B21: 20.87 | C21: 148 | D21: =B21/C21 -> 0.14101351
D22: =SUM(D20:D21) -> 0.39101351
A25: Individual Packaged Products (excl. Labour)
A27: Small - Cooked
B28: Weight | C28: Cost | D28: Total
A29: Ingredient Cost | B29: 1 | C29: =D22*2 -> 0.78202703 | D29: =B29*C29 -> 0.78202703
A30: Packaging | B30: 1 | C30: 0.09 | D30: =C30*B30 -> 0.09
A31: COST | D31: =SUM(D29:D30) -> 0.87202703
A34: Individual Packaged Products (incl. Labour) | D34: = | E34: COGS
A36: Twin
B37: Weight | C37: Cost | D37: Total
A38: Packaged Product Cost | B38: 1 | C38: =D31 -> 0.87202703 | D38: =B38*C38 -> 0.87202703
A39: Labour | B39: 120 | C39: ='Ingredient Cost'!$B$113 -> 20 | D39: =C39/B39 -> 0.16666667
A40: COST | D40: =SUM(D38:D39) -> 1.0386937
B42: Labour Percentage | D42: =D39/D38 -> 0.19112557
A43: CASES
A45: 10 per case
B46: Weight | C46: Cost | D46: Total
A47: Product Cost | B47: 10 | C47: =D40 -> 1.0386937 | D47: =B47*C47 -> 10.386937
A48: Case Packaging | B48: 1 | C48: ='Ingredient Cost'!D108 -> 0.2 | D48: =B48*C48 -> 0.2
A49: Labour | B49: 250 | C49: =C39 -> 20 | D49: =C49/B49 -> 0.08
A50: Box end label | B50: 1 | C50: 0.01 | D50: =B50*C50 -> 0.01
A51: COST | D51: =SUM(D47:D50) -> 10.676937
A52: PER EACH | D52: =D51/9 -> 1.1863263

Sheet Steak Pie v2
A1: Grasmere Farm
A2: Product Costings
A3: Steak Pie
A4: INGREDIENTS | B4: . All allergens in BOLD.
A16: Sub-recipes
A18: Filling | F18: Cold Water Pastry
B19: Weight | C19: Cost | D19: Total | G19: Weight | H19: Cost | I19: Total
A20: Cooked Beef | B20: 3 | C20: ='Ingredient Cost'!$D$59 -> 8.5 | D20: =B20*C20 -> 25.5 | F20: Water | G20: 2.5
A21: Beef Juice/Water | B21: 2.2 | C21: 0 | D21: =B21*C21 -> 0 | F21: Fat/Butter | G21: 4 | H21: ='Ingredient Cost'!$D$6 -> 2.06 | I21: =G21*H21 -> 8.24
A22: Gravy Mix CW 111020 | B22: 0.45 | C22: ='Ingredient Cost'!$D$21 -> 8.9 | D22: =B22*C22 -> 4.005 | F22: Flour | G22: 8 | H22: ='Ingredient Cost'!$D$7 -> 0.62 | I22: =G22*H22 -> 4.96
A23: Total | B23: =SUM(B20:B22) -> 5.65 | D23: =SUM(D20:D22) -> 29.505 | F23: Salt | G23: 0.15 | H23: ='Ingredient Cost'!$D$8 -> 0.54 | I23: =G23*H23 -> 0.081
F24: Total | G24: =G20+G21+G22+G23 -> 14.65 | I24: =SUM(I20:I23) -> 13.281
A26: COST/kg | D26: =D23/B23 -> 5.2221239 | F26: COST/kg | I26: =I24/G24 -> 0.9065529
A28: Ingredient
A30: Small | F30: Medium | K30: Large
B31: Weight | C31: Cost | D31: Total | G31: Weight | H31: Cost | I31: Total | L31: Weight | M31: Cost | N31: Total
A32: Filling | B32: 0.129 | C32: =$D$26 -> 5.2221239 | D32: =B32*C32 -> 0.67365398 | F32: Filling | G32: 0.257 | H32: =$D$26 -> 5.2221239 | I32: =G32*H32 -> 1.3420858 | K32: Filling | L32: 0.74 | M32: =$D$26 -> 5.2221239 | N32: =L32*M32 -> 3.8643717
A33: Pastry | B33: 1 | C33: ='Pastry Costing'!$F$30 -> 0.21079469 | D33: =C33 -> 0.21079469 | F33: Pastry | G33: 1 | H33: ='Pastry Costing'!$F$31 -> 0.3414143 | I33: =H33 -> 0.3414143 | K33: Pastry | L33: 1 | M33: ='Pastry Costing'!$F$32 -> 0.5240744 | N33: =M33 -> 0.5240744
A34: Egg Glaze | B34: 1 | C34: ='Ingredient Cost'!$D$11 -> 0.02 | D34: =B34*C34 -> 0.02 | F34: Egg Glaze | G34: 1 | H34: ='Ingredient Cost'!$D$11 -> 0.02 | I34: =H34 -> 0.02 | K34: Egg Glaze | L34: 1 | M34: ='Ingredient Cost'!$D$11 -> 0.02 | N34: =L34*M34 -> 0.02
A35: COST | D35: =SUM(D32:D34) -> 0.90444867 | F35: COST | I35: =SUM(I32:I34) -> 1.7035001 | K35: COST | N35: =SUM(N32:N34) -> 4.4084461
A37: Individual Packaged Products (excl. Labour)
A39: Small - Cooked | F39: Medium | K39: Large
B40: Weight | C40: Cost | D40: Total | G40: Weight | H40: Cost | I40: Total | L40: Weight | M40: Cost | N40: Total
A41: Ingredient Cost | B41: 1 | C41: =$D$35 -> 0.90444867 | D41: =B41*C41 -> 0.90444867 | F41: Ingredient Cost | G41: 1 | H41: =$I$35 -> 1.7035001 | I41: =G41*H41 -> 1.7035001 | K41: Ingredient Cost | L41: 1 | M41: =$N$35 -> 4.4084461 | N41: =L41*M41 -> 4.4084461
A42: Foil | B42: 1 | C42: ='Ingredient Cost'!$D$95 -> 0.09 | D42: =B42*C42 -> 0.09 | F42: Foil | G42: 1 | H42: ='Ingredient Cost'!$D$83 -> 0.07 | I42: =G42*H42 -> 0.07 | K42: Foil | L42: 1 | M42: ='Ingredient Cost'!$D$83 -> 0.07 | N42: =L42*M42 -> 0.07
A43: Packaging | B43: 1 | C43: ='Ingredient Cost'!$D$89 -> 0.06 | D43: =B43*C43 -> 0.06 | F43: Packaging | G43: 1 | H43: 0.22 | I43: =H43*G43 -> 0.22 | K43: Packaging | L43: 1 | M43: 0.3 | N43: 0.3
F44: Label | G44: 1 | H44: 0.15 | I44: 0.15 | K44: Label | L44: 1 | M44: 0.15 | N44: 0.15
A45: COST | D45: =SUM(D41:D43) -> 1.0544487 | F45: COST | I45: =SUM(I41:I44) -> 2.1435001 | K45: COST | N45: =SUM(N41:N44) -> 4.9284461
A48: Individual Packaged Products (incl. Labour) | D48: = | E48: COGS
A50: Small | F50: Medium | K50: Large
B51: Weight | C51: Cost | D51: Total | G51: Weight | H51: Cost | I51: Total | L51: Weight | M51: Cost | N51: Total
A52: Packaged Product Cost | B52: 1 | C52: =$D$45 -> 1.0544487 | D52: =B52*C52 -> 1.0544487 | F52: Packaged Product Cost | G52: 1 | H52: =$I$45 -> 2.1435001 | I52: =G52*H52 -> 2.1435001 | K52: Packaged Product Cost | L52: 1 | M52: =$N$45 -> 4.9284461 | N52: =L52*M52 -> 4.9284461
A53: Labour | B53: 60 | C53: ='Ingredient Cost'!$B$113 -> 20 | D53: =C53/B53 -> 0.33333333 | F53: Labour | G53: 48 | H53: ='Ingredient Cost'!$B$113 -> 20 | I53: =H53/G53 -> 0.41666667 | K53: Labour | L53: 50 | M53: ='Ingredient Cost'!$B$113 -> 20 | N53: =M53/L53 -> 0.4
A54: COST | D54: =SUM(D52:D53) -> 1.387782 | F54: COST | I54: =SUM(I52:I53) -> 2.5601668 | K54: COST | N54: =SUM(N52:N53) -> 5.3284461
B56: Labour Percentage | D56: =D$53/D$52 -> 0.31612097 | G56: Labour Percentage | I56: =I$53/I$52 -> 0.19438612 | L56: Labour Percentage | N56: =N$53/N$52 -> 0.081161484
A57: CASES
A59: Small (9 per case) | F59: Medium (4 per case)
B60: Weight | C60: Cost | D60: Total | G60: Weight | H60: Cost | I60: Total
A61: Product Cost | B61: 9 | C61: =D54 -> 1.387782 | D61: =B61*C61 -> 12.490038 | F61: Product Cost | G61: 4 | H61: =I54 -> 2.5601668 | I61: =G61*H61 -> 10.240667
A62: Case Packaging | B62: 1 | C62: ='Ingredient Cost'!D108 -> 0.2 | D62: =B62*C62 -> 0.2 | F62: Case Packaging | G62: 1 | H62: =C62 -> 0.2 | I62: =G62*H62 -> 0.2
A63: Labour | B63: 180 | C63: =C53 -> 20 | D63: =C63/B63 -> 0.11111111 | F63: Labour | G63: 180 | H63: =C53 -> 20 | I63: =H63/G63 -> 0.11111111
A64: Box end label | B64: 1 | C64: 0.01 | D64: =B64*C64 -> 0.01 | F64: Box end label | G64: 1 | H64: 0.01 | I64: =G64*H64 -> 0.01
A65: COST | D65: =SUM(D61:D64) -> 12.811149 | F65: COST | I65: =SUM(I61:I64) -> 10.561778
A66: PER EACH | D66: =D65/9 -> 1.423461 | F66: PER EACH | I66: =I65/4 -> 2.6404446
A68: Small (6 per case)
B69: Weight | C69: Cost | D69: Total
A70: Product Cost | B70: 6 | C70: =D54 -> 1.387782 | D70: =B70*C70 -> 8.326692
A71: Case Packaging | B71: 1 | C71: ='Ingredient Cost'!D108 -> 0.2 | D71: =B71*C71 -> 0.2
A72: Labour | B72: 180 | C72: 20 | D72: =C72/B72 -> 0.11111111
A73: Box end label | B73: 1 | C73: 0.01 | D73: =B73*C73 -> 0.01
A74: COST | D74: =SUM(D70:D73) -> 8.6478031
A75: PER EACH | D75: =D74/6 -> 1.4413005
A77: Frozen Small (case of 12)
B78: Weight | C78: Cost | D78: Total
A79: Product Cost | B79: 12 | C79: =(D35+D53) -> 1.237782 | D79: =B79*C79 -> 14.853384
A80: Case Packaging | B80: 1 | C80: 0.2 | D80: =B80*C80 -> 0.2
A81: Labour | B81: 180 | C81: 20 | D81: =C81/B81 -> 0.11111111
A82: Box end label | B82: 1 | C82: 0.01 | D82: =B82*C82 -> 0.01
A83: COST | D83: =SUM(D79:D82) -> 15.174495
A84: PER EACH | D84: =D83/6 -> 2.5290825

Sheet Steak & Ale Pie
A1: Grasmere Farm Manual
A2: Product Page
A3: Steak & Ale Pie
A4: INGREDIENTS | B4: . All allergens in BOLD.
A16: Product | B16: Steak & Ale Pie Filling
B17: Weight | C17: Cost | D17: Total
A18: Cooked Beef | B18: 3 | C18: ='Ingredient Cost'!D59 -> 8.5 | D18: =B18*C18 -> 25.5
A19: Ale | B19: 0.8 | C19: ='Ingredient Cost'!D29 -> 1.38 | D19: =B19*C19 -> 1.104
A20: Beef Juice/Water | B20: 1.4 | C20: 0 | D20: =B20*C20 -> 0
A21: Gravey Mix CW 111020 | B21: 0.45 | C21: ='Ingredient Cost'!D21 -> 8.9 | D21: =B21*C21 -> 4.005
B24: =SUM(B18:B22) -> 5.65 | D24: =SUM(D18:D22) -> 30.609
A26: COST | D26: =D24/B24 -> 5.4175221
A28: Product | B28: Raw Steak & Ale Pie Small | F28: Product | G28: Raw Steak & Ale Pie Medium | K28: Product | L28: Raw Steak & Ale Pie Large
A29: Date | B29: ….. | F29: Date | G29: ….. | K29: Date | L29: …..
A30: Supplier | B30: …… | F30: Supplier | G30: …… | K30: Supplier | L30: ……
A31: Staff Member | B31: …… | F31: Staff Member | G31: …… | K31: Staff Member | L31: ……
B32: Weight | C32: Cost | D32: Total | G32: Weight | H32: Cost | I32: Total | L32: Weight | M32: Cost | N32: Total
A33: Steak & Ale Pie Filling | B33: 0.129 | C33: =D26 -> 5.4175221 | D33: =B33*C33 -> 0.69886035 | F33: Steak & Ale Pie Filling | G33: 0.257 | H33: =D26 -> 5.4175221 | I33: =G33*H33 -> 1.3923032 | K33: Steak & Ale Pie Filling | L33: 0.74 | M33: =D26 -> 5.4175221 | N33: =L33*M33 -> 4.0089664
A34: Pastry | C34: ='Pastry Costing'!F30 -> 0.21079469 | D34: =C34 -> 0.21079469 | F34: Pasty | H34: ='Pastry Costing'!F31 -> 0.3414143 | I34: =H34 -> 0.3414143 | K34: Pasty | M34: ='Pastry Costing'!F32 -> 0.5240744 | N34: =M34 -> 0.5240744
A35: Foil | C35: ='Ingredient Cost'!D95 -> 0.09 | D35: =C35 -> 0.09 | F35: Foil | H35: ='Ingredient Cost'!D96 -> 0.12 | I35: =H35 -> 0.12 | K35: Foil | M35: ='Ingredient Cost'!D97 -> 0.2 | N35: =M35 -> 0.2
A36: Egg Glaze | C36: ='Ingredient Cost'!C35 -> 0 | D36: =B36*C36 -> 0 | F36: Egg Glaze | H36: ='Ingredient Cost'!H35 -> 0 | I36: =G36*H36 -> 0 | K36: Egg Glaze | M36: ='Ingredient Cost'!M35 -> 0 | N36: =L36*M36 -> 0
A37: Labour | B37: 90 | C37: ='Steak Pie v2'!C53 -> 20 | D37: =C37/B37 -> 0.22222222 | F37: Labour | G37: 48 | H37: =C37 -> 20 | I37: =H37/G37 -> 0.41666667 | K37: Labour | L37: 32 | M37: =C37 -> 20 | N37: =M37/L37 -> 0.625
A40: COST | D40: =SUM(D33:D37) -> 1.2218773 | F40: COST | I40: =SUM(I33:I37) -> 2.2703842 | K40: COST | N40: =SUM(N33:N37) -> 5.3580408
A44: Product | B44: Cooked Steak Pie Small Case | F44: Product | G44: Cooked Steak Pie Medium Case
B45: Weight | C45: Cost | D45: Total | G45: Weight | H45: Cost | I45: Total
A46: Pie | B46: 9 | C46: =D40 -> 1.2218773 | D46: =B46*C46 -> 10.996895 | F46: Pie | G46: 6 | H46: =I40 -> 2.2703842 | I46: =G46*H46 -> 13.622305
A47: Cooking Paper | B47: 1 | C47: ='Ingredient Cost'!D86 -> 0.12 | D47: =B47*C47 -> 0.12 | F47: Cooking Paper | G47: 1 | H47: =C47 -> 0.12 | I47: =G47*H47 -> 0.12
A48: Packaging | B48: 9 | C48: ='Ingredient Cost'!D90 -> 0.22 | D48: =B48*C48 -> 1.98 | F48: Packaging | G48: 6 | H48: ='Steak Pie v2'!#REF! -> #REF! | I48: =G48*H48 -> #REF!
A49: Case | B49: 1 | C49: ='Ingredient Cost'!D108 -> 0.2 | D49: =B49*C49 -> 0.2 | F49: Case | G49: 1 | H49: =C49 -> 0.2 | I49: =G49*H49 -> 0.2
A50: Labour | B50: 20 | C50: {=_xlfn.ANCHORARRAY(C37)} -> #NAME? | D50: =C50/B50 -> #NAME? | F50: Labour | G50: 20 | H50: 18 | I50: =H50/G50 -> 0.9
F51: Label | G51: 6 | H51: ='Steak Pie v2'!H64 -> 0.01 | I51: =G51*H51 -> 0.06
F52: Box end label | G52: 6 | H52: 0.01 | I52: =G52*H52 -> 0.06
A55: COST | D55: =D46+D47+D48+D49+D50 -> #NAME? | F55: COST | I55: =I46+I47+I48+I49+I50+I51+I52 -> #REF!
A56: PER EACH | D56: =D55/9 -> #NAME? | F56: PER EACH | I56: =I55/6 -> #REF!

Sheet Steak & Ale Pie v2
A1: Grasmere Farm
A2: Product Costings
A3: Steak & Ale Pie
A4: INGREDIENTS | B4: . All allergens in BOLD.
A16: Sub-recipes
A18: Filling | F18: Cold Water Pastry
B19: Weight | C19: Cost | D19: Total | G19: Weight | H19: Cost | I19: Total
A20: Cooked Beef | B20: 3 | C20: ='Ingredient Cost'!$D$59 -> 8.5 | D20: =B20*C20 -> 25.5 | F20: Water | G20: 2.5
A21: Beef Juice/Water | B21: 1.4 | C21: 0 | D21: =B21*C21 -> 0 | F21: Fat/Butter | G21: 4 | H21: ='Ingredient Cost'!$D$6 -> 2.06 | I21: =G21*H21 -> 8.24
A22: Gravy Mix CW 111020 | B22: 0.45 | C22: ='Ingredient Cost'!$D$21 -> 8.9 | D22: =B22*C22 -> 4.005 | F22: Flour | G22: 8 | H22: ='Ingredient Cost'!$D$7 -> 0.62 | I22: =G22*H22 -> 4.96
A23: Ale | B23: 0.8 | C23: ='Ingredient Cost'!D29 -> 1.38 | D23: =B23*C23 -> 1.104 | F23: Salt | G23: 0.15 | H23: ='Ingredient Cost'!$D$8 -> 0.54 | I23: =G23*H23 -> 0.081
A24: Total | B24: =SUM(B20:B23) -> 5.65 | D24: =SUM(D20:D23) -> 30.609 | F24: Total | G24: =G20+G21+G22+G23 -> 14.65 | I24: =SUM(I20:I23) -> 13.281
A26: COST/kg | D26: =D24/B24 -> 5.4175221 | F26: COST/kg | I26: =I24/G24 -> 0.9065529
A28: Ingredient
A30: Small | F30: Medium | K30: Large
B31: Weight | C31: Cost | D31: Total | G31: Weight | H31: Cost | I31: Total | L31: Weight | M31: Cost | N31: Total
A32: Filling | B32: 0.129 | C32: =$D$26 -> 5.4175221 | D32: =B32*C32 -> 0.69886035 | F32: Filling | G32: 0.257 | H32: =$D$26 -> 5.4175221 | I32: =G32*H32 -> 1.3923032 | K32: Filling | L32: 0.74 | M32: =$D$26 -> 5.4175221 | N32: =L32*M32 -> 4.0089664
A33: Pastry | B33: 1 | C33: ='Pastry Costing'!$F$30 -> 0.21079469 | D33: =C33 -> 0.21079469 | F33: Pastry | G33: 1 | H33: ='Pastry Costing'!$F$31 -> 0.3414143 | I33: =H33 -> 0.3414143 | K33: Pastry | L33: 1 | M33: ='Pastry Costing'!$F$32 -> 0.5240744 | N33: =M33 -> 0.5240744
A34: Egg Glaze | B34: 1 | C34: ='Ingredient Cost'!$D$11 -> 0.02 | D34: =B34*C34 -> 0.02 | F34: Egg Glaze | G34: 1 | H34: ='Ingredient Cost'!$D$11 -> 0.02 | I34: =H34 -> 0.02 | K34: Egg Glaze | L34: 1 | M34: ='Ingredient Cost'!$D$11 -> 0.02 | N34: =L34*M34 -> 0.02
A35: COST | D35: =SUM(D32:D34) -> 0.92965504 | F35: COST | I35: =SUM(I32:I34) -> 1.7537175 | K35: COST | N35: =SUM(N32:N34) -> 4.5530408
A37: Individual Packaged Products (excl. Labour)
A39: Small - Cooked | F39: Medium | K39: Large
B40: Weight | C40: Cost | D40: Total | G40: Weight | H40: Cost | I40: Total | L40: Weight | M40: Cost | N40: Total
A41: Ingredient Cost | B41: 1 | C41: =$D$35 -> 0.92965504 | D41: =B41*C41 -> 0.92965504 | F41: Ingredient Cost | G41: 1 | H41: =$I$35 -> 1.7537175 | I41: =G41*H41 -> 1.7537175 | K41: Ingredient Cost | L41: 1 | M41: =$N$35 -> 4.5530408 | N41: =L41*M41 -> 4.5530408
A42: Foil | B42: 1 | C42: ='Ingredient Cost'!$D$95 -> 0.09 | D42: =B42*C42 -> 0.09 | F42: Foil | G42: 1 | H42: ='Ingredient Cost'!$D$83 -> 0.07 | I42: =G42*H42 -> 0.07 | K42: Foil | L42: 1 | M42: ='Ingredient Cost'!$D$83 -> 0.07 | N42: =L42*M42 -> 0.07
A43: Packaging | B43: 1 | C43: ='Ingredient Cost'!$D$89 -> 0.06 | D43: =B43*C43 -> 0.06 | F43: Packaging | G43: 1 | H43: 0.22 | I43: =H43*G43 -> 0.22 | K43: Packaging | L43: 1 | M43: 0.3 | N43: 0.3
F44: Label | G44: 1 | H44: 0.15 | I44: 0.15 | K44: Label | L44: 1 | M44: 0.15 | N44: 0.15
A45: COST | D45: =SUM(D41:D43) -> 1.079655 | F45: COST | I45: =SUM(I41:I44) -> 2.1937175 | K45: COST | N45: =SUM(N41:N44) -> 5.0730408
A48: Individual Packaged Products (incl. Labour) | D48: = | E48: COGS
A50: Small | F50: Medium | K50: Large
B51: Weight | C51: Cost | D51: Total | G51: Weight | H51: Cost | I51: Total | L51: Weight | M51: Cost | N51: Total
A52: Packaged Product Cost | B52: 1 | C52: =$D$45 -> 1.079655 | D52: =B52*C52 -> 1.079655 | F52: Packaged Product Cost | G52: 1 | H52: =$I$45 -> 2.1937175 | I52: =G52*H52 -> 2.1937175 | K52: Packaged Product Cost | L52: 1 | M52: =$N$45 -> 5.0730408 | N52: =L52*M52 -> 5.0730408
A53: Labour | B53: 60 | C53: ='Ingredient Cost'!$B$113 -> 20 | D53: =C53/B53 -> 0.33333333 | F53: Labour | G53: 48 | H53: ='Ingredient Cost'!$B$113 -> 20 | I53: =H53/G53 -> 0.41666667 | K53: Labour | L53: 50 | M53: ='Ingredient Cost'!$B$113 -> 20 | N53: =M53/L53 -> 0.4
A54: COST | D54: =SUM(D52:D53) -> 1.4129884 | F54: COST | I54: =SUM(I52:I53) -> 2.6103842 | K54: COST | N54: =SUM(N52:N53) -> 5.4730408
B56: Labour Percentage | D56: =D$53/D$52 -> 0.30874059 | G56: Labour Percentage | I56: =I$53/I$52 -> 0.18993634 | L56: Labour Percentage | N56: =N$53/N$52 -> 0.078848174
A57: CASES
A59: Small (9 per case) | F59: Medium (4 per case)
B60: Weight | C60: Cost | D60: Total | G60: Weight | H60: Cost | I60: Total
A61: Product Cost | B61: 9 | C61: =D54 -> 1.4129884 | D61: =B61*C61 -> 12.716895 | F61: Product Cost | G61: 4 | H61: =I54 -> 2.6103842 | I61: =G61*H61 -> 10.441537
A62: Case Packaging | B62: 1 | C62: ='Ingredient Cost'!D108 -> 0.2 | D62: =B62*C62 -> 0.2 | F62: Case Packaging | G62: 1 | H62: =C62 -> 0.2 | I62: =G62*H62 -> 0.2
A63: Labour | B63: 180 | C63: =C53 -> 20 | D63: =C63/B63 -> 0.11111111 | F63: Labour | G63: 180 | H63: =C53 -> 20 | I63: =H63/G63 -> 0.11111111
A64: Box end label | B64: 1 | C64: 0.01 | D64: =B64*C64 -> 0.01 | F64: Box end label | G64: 1 | H64: 0.01 | I64: =G64*H64 -> 0.01
A65: COST | D65: =SUM(D61:D64) -> 13.038007 | F65: COST | I65: =SUM(I61:I64) -> 10.762648
A66: PER EACH | D66: =D65/9 -> 1.4486674 | F66: PER EACH | I66: =I65/4 -> 2.6906619
A68: Small (6 per case)
B69: Weight | C69: Cost | D69: Total
A70: Product Cost | B70: 6 | C70: =D54 -> 1.4129884 | D70: =B70*C70 -> 8.4779303
A71: Case Packaging | B71: 1 | C71: =C62 -> 0.2 | D71: =B71*C71 -> 0.2
A72: Labour | B72: 180 | C72: 20 | D72: =C72/B72 -> 0.11111111
A73: Box end label | B73: 1 | C73: 0.01 | D73: =B73*C73 -> 0.01
A74: COST | D74: =SUM(D70:D73) -> 8.7990414
A75: PER EACH | D75: =D74/6 -> 1.4665069
A77: Small (12 per case)
B78: Weight | C78: Cost | D78: Total
A79: Product Cost | B79: 12 | C79: =D54 -> 1.4129884 | D79: =B79*C79 -> 16.955861
A80: Case Packaging | B80: 1 | C80: =C62 -> 0.2 | D80: =B80*C80 -> 0.2
A81: Labour | B81: 180 | C81: 20 | D81: =C81/B81 -> 0.11111111
A82: Box end label | B82: 1 | C82: 0.01 | D82: =B82*C82 -> 0.01
A83: COST | D83: =SUM(D79:D82) -> 17.276972
A84: PER EACH | D84: =D83/12 -> 1.4397476

Sheet Steak & Kidney Pie
A1: Grasmere Farm Manual
A2: Product Page
A3: Steak & Kidney Pie
A4: INGREDIENTS | B4: . All allergens in BOLD.
A16: Product | B16: Steak & Kidney Pie Filling
B17: Weight | C17: Cost | D17: Total
A18: Cooked Beef | B18: 3 | C18: ='Ingredient Cost'!D59 -> 8.5 | D18: =B18*C18 -> 25.5
A19: Beef Juice/Water/Kidney | B19: 2.2 | C19: 0 | D19: =B19*C19 -> 0
A20: Gravey Mix CW 111020 | B20: 0.45 | C20: ='Ingredient Cost'!D21 -> 8.9 | D20: =B20*C20 -> 4.005
A21: Cooked Kidney | B21: 1 | C21: ='Ingredient Cost'!D61 -> 4 | D21: =B21*C21 -> 4
B23: =SUM(B18:B21) -> 6.65 | D23: =SUM(D18:D21) -> 33.505
A25: COST | D25: =D23/B23 -> 5.0383459
A28: Product | B28: Raw Steak & Kidney Pie Small | F28: Product | G28: Raw Steak & Kidney Pie Medium | K28: Product | L28: Raw Steak & Kidney Pie Large
B29: Weight | C29: Cost | D29: Total | G29: Weight | H29: Cost | I29: Total | L29: Weight | M29: Cost | N29: Total
A30: Steak & Kidney Pie Filling | B30: 0.129 | C30: =D25 -> 5.0383459 | D30: =B30*C30 -> 0.64994662 | F30: Steak & Kidney Pie Filling | G30: 0.257 | H30: =C30 -> 5.0383459 | I30: =G30*H30 -> 1.2948549 | K30: Steak & Kidney Pie Filling | L30: 0.74 | M30: =C30 -> 5.0383459 | N30: =L30*M30 -> 3.7283759
A31: Pasty | C31: ='Pastry Costing'!F30 -> 0.21079469 | D31: =C31 -> 0.21079469 | F31: Pasty | H31: ='Pastry Costing'!F31 -> 0.3414143 | I31: =H31 -> 0.3414143 | K31: Pasty | M31: ='Pastry Costing'!F32 -> 0.5240744 | N31: =M31 -> 0.5240744
A32: Egg Glaze | C32: ='Ingredient Cost'!C38 -> 0 | D32: =B32*C32 -> 0 | F32: Egg Glaze | H32: =C32 -> 0 | I32: =H32 -> 0 | K32: Egg Glaze | M32: ='Ingredient Cost'!M38 -> 0 | N32: =L32*M32 -> 0
A33: Foil | B33: 1 | C33: ='Ingredient Cost'!D95 -> 0.09 | D33: =B33*C33 -> 0.09 | F33: Foil | G33: 1 | H33: ='Ingredient Cost'!D96 -> 0.12 | I33: =G33*H33 -> 0.12 | K33: Foil | L33: 1 | M33: ='Ingredient Cost'!D97 -> 0.2 | N33: =L33*M33 -> 0.2
A34: Labour | B34: 90 | C34: ='Steak Pie v2'!C53 -> 20 | D34: =C34/B34 -> 0.22222222 | F34: Labour | G34: 48 | H34: =C34 -> 20 | I34: =H34/G34 -> 0.41666667 | K34: Labour | L34: 32 | M34: =C34 -> 20 | N34: =M34/L34 -> 0.625
A37: COST | D37: =D30+D31+D32+D33+D34 -> 1.1729635 | F37: COST | I37: =I30+I31+I32+I33+I34 -> 2.1729359 | K37: COST | N37: =N30+N31+N32+N33+N34 -> 5.0774503
A40: Product | B40: Cooked Steak & Kidney Pie Small Case | F40: Product | G40: Cooked Steak & Kidney Pie Medium Case
B41: Weight | C41: Cost | D41: Total | G41: Weight | H41: Cost | I41: Total
A42: Pie | B42: 9 | C42: =D37 -> 1.1729635 | D42: =B42*C42 -> 10.556672 | F42: Pie | G42: 6 | H42: =I37 -> 2.1729359 | I42: =G42*H42 -> 13.037615
A43: Cooking Paper | B43: 1 | C43: ='Ingredient Cost'!D88 -> 0.09 | D43: =B43*C43 -> 0.09 | F43: Cooking Paper | G43: 1 | H43: =C43 -> 0.09 | I43: =G43*H43 -> 0.09
A44: Packaging | B44: 9 | C44: ='Ingredient Cost'!D90 -> 0.22 | D44: =B44*C44 -> 1.98 | F44: Packaging | G44: 6 | H44: 0.1 | I44: =G44*H44 -> 0.6
A45: Case | B45: 1 | C45: ='Ingredient Cost'!D108 -> 0.2 | D45: =B45*C45 -> 0.2 | F45: Case | G45: 1 | H45: =C45 -> 0.2 | I45: =G45*H45 -> 0.2
A46: Labour | B46: 20 | C46: =C34 -> 20 | D46: =C46/B46 -> 1 | F46: Labour | G46: 20 | H46: =C34 -> 20 | I46: =H46/G46 -> 1
F47: Label | G47: 6 | H47: ='Steak Pie v2'!H64 -> 0.01 | I47: =G47*H47 -> 0.06
F48: Box end label | G48: 6 | H48: 0.01 | I48: =G48*H48 -> 0.06
A51: COST | D51: =D42+D43+D44+D45+D46 -> 13.826672 | F51: COST | I51: =I42+I43+I44+I45+I46+I47+I48 -> 15.047615
A52: PER EACH | D52: =D51/9 -> 1.5362969 | F52: PER EACH | I52: =I51/6 -> 2.5079359

Sheet Steak & Kidney Pie v2
A1: Grasmere Farm
A2: Product Costings
A3: Steak & Kidney Pie
A4: INGREDIENTS | B4: . All allergens in BOLD.
A16: Sub-recipes
A18: Filling | F18: Cold Water Pastry
B19: Weight | C19: Cost | D19: Total | G19: Weight | H19: Cost | I19: Total
A20: Cooked Beef | B20: 3 | C20: ='Ingredient Cost'!$D$59 -> 8.5 | D20: =B20*C20 -> 25.5 | F20: Water | G20: 2.5
A21: Beef Juice/Water | B21: 2.2 | C21: 0 | D21: =B21*C21 -> 0 | F21: Fat/Butter | G21: 4 | H21: ='Ingredient Cost'!$D$6 -> 2.06 | I21: =G21*H21 -> 8.24
A22: Gravy Mix CW 111020 | B22: 0.45 | C22: ='Ingredient Cost'!$D$21 -> 8.9 | D22: =B22*C22 -> 4.005 | F22: Flour | G22: 8 | H22: ='Ingredient Cost'!$D$7 -> 0.62 | I22: =G22*H22 -> 4.96
A23: Kidney | B23: 1 | C23: 1.99 | D23: =B23*C23 -> 1.99 | F23: Salt | G23: 0.15 | H23: ='Ingredient Cost'!$D$8 -> 0.54 | I23: =G23*H23 -> 0.081
A24: Total | B24: =SUM(B20:B23) -> 6.65 | D24: =SUM(D20:D23) -> 31.495 | F24: Total | G24: =G20+G21+G22+G23 -> 14.65 | I24: =SUM(I20:I23) -> 13.281
A26: COST/kg | D26: =D24/B24 -> 4.7360902 | F26: COST/kg | I26: =I24/G24 -> 0.9065529
A28: Ingredient
A30: Small | F30: Medium | K30: Large
B31: Weight | C31: Cost | D31: Total | G31: Weight | H31: Cost | I31: Total | L31: Weight | M31: Cost | N31: Total
A32: Filling | B32: 0.129 | C32: =$D$26 -> 4.7360902 | D32: =B32*C32 -> 0.61095564 | F32: Filling | G32: 0.257 | H32: =$D$26 -> 4.7360902 | I32: =G32*H32 -> 1.2171752 | K32: Filling | L32: 0.74 | M32: =$D$26 -> 4.7360902 | N32: =L32*M32 -> 3.5047068
A33: Pastry | B33: 1 | C33: ='Pastry Costing'!$F$30 -> 0.21079469 | D33: =C33 -> 0.21079469 | F33: Pastry | G33: 1 | H33: ='Pastry Costing'!$F$31 -> 0.3414143 | I33: =H33 -> 0.3414143 | K33: Pastry | L33: 1 | M33: ='Pastry Costing'!$F$32 -> 0.5240744 | N33: =M33 -> 0.5240744
A34: Egg Glaze | B34: 1 | C34: ='Ingredient Cost'!$D$11 -> 0.02 | D34: =B34*C34 -> 0.02 | F34: Egg Glaze | G34: 1 | H34: ='Ingredient Cost'!$D$11 -> 0.02 | I34: =H34 -> 0.02 | K34: Egg Glaze | L34: 1 | M34: ='Ingredient Cost'!$D$11 -> 0.02 | N34: =L34*M34 -> 0.02
A35: COST | D35: =SUM(D32:D34) -> 0.84175033 | F35: COST | I35: =SUM(I32:I34) -> 1.5785895 | K35: COST | N35: =SUM(N32:N34) -> 4.0487812
A37: Individual Packaged Products (excl. Labour)
A39: Small - Cooked | F39: Medium | K39: Large
B40: Weight | C40: Cost | D40: Total | G40: Weight | H40: Cost | I40: Total | L40: Weight | M40: Cost | N40: Total
A41: Ingredient Cost | B41: 1 | C41: =$D$35 -> 0.84175033 | D41: =B41*C41 -> 0.84175033 | F41: Ingredient Cost | G41: 1 | H41: =$I$35 -> 1.5785895 | I41: =G41*H41 -> 1.5785895 | K41: Ingredient Cost | L41: 1 | M41: =$N$35 -> 4.0487812 | N41: =L41*M41 -> 4.0487812
A42: Foil | B42: 1 | C42: ='Ingredient Cost'!$D$95 -> 0.09 | D42: =B42*C42 -> 0.09 | F42: Foil | G42: 1 | H42: ='Ingredient Cost'!$D$83 -> 0.07 | I42: =G42*H42 -> 0.07 | K42: Foil | L42: 1 | M42: ='Ingredient Cost'!$D$83 -> 0.07 | N42: =L42*M42 -> 0.07
A43: Packaging | B43: 1 | C43: ='Ingredient Cost'!$D$89 -> 0.06 | D43: =B43*C43 -> 0.06 | F43: Packaging | G43: 1 | H43: 0.22 | I43: =H43*G43 -> 0.22 | K43: Packaging | L43: 1 | M43: 0.3 | N43: 0.3
F44: Label | G44: 1 | H44: 0.15 | I44: 0.15 | K44: Label | L44: 1 | M44: 0.15 | N44: 0.15
A45: COST | D45: =SUM(D41:D43) -> 0.99175033 | F45: COST | I45: =SUM(I41:I44) -> 2.0185895 | K45: COST | N45: =SUM(N41:N44) -> 4.5687812
A48: Individual Packaged Products (incl. Labour) | D48: = | E48: COGS
A50: Small | F50: Medium | K50: Large
B51: Weight | C51: Cost | D51: Total | G51: Weight | H51: Cost | I51: Total | L51: Weight | M51: Cost | N51: Total
A52: Packaged Product Cost | B52: 1 | C52: =$D$45 -> 0.99175033 | D52: =B52*C52 -> 0.99175033 | F52: Packaged Product Cost | G52: 1 | H52: =$I$45 -> 2.0185895 | I52: =G52*H52 -> 2.0185895 | K52: Packaged Product Cost | L52: 1 | M52: =$N$45 -> 4.5687812 | N52: =L52*M52 -> 4.5687812
A53: Labour | B53: 60 | C53: ='Ingredient Cost'!$B$113 -> 20 | D53: =C53/B53 -> 0.33333333 | F53: Labour | G53: 48 | H53: ='Ingredient Cost'!$B$113 -> 20 | I53: =H53/G53 -> 0.41666667 | K53: Labour | L53: 50 | M53: ='Ingredient Cost'!$B$113 -> 20 | N53: =M53/L53 -> 0.4
A54: COST | D54: =SUM(D52:D53) -> 1.3250837 | F54: COST | I54: =SUM(I52:I53) -> 2.4352562 | K54: COST | N54: =SUM(N52:N53) -> 4.9687812
B56: Labour Percentage | D56: =D$53/D$52 -> 0.3361061 | G56: Labour Percentage | I56: =I$53/I$52 -> 0.20641476 | L56: Labour Percentage | N56: =N$53/N$52 -> 0.087550702
A57: CASES
A59: Small (9 per case) | F59: Medium (4 per case)
B60: Weight | C60: Cost | D60: Total | G60: Weight | H60: Cost | I60: Total
A61: Product Cost | B61: 9 | C61: =D54 -> 1.3250837 | D61: =B61*C61 -> 11.925753 | F61: Product Cost | G61: 4 | H61: =I54 -> 2.4352562 | I61: =G61*H61 -> 9.7410246
A62: Case Packaging | B62: 1 | C62: ='Ingredient Cost'!D108 -> 0.2 | D62: =B62*C62 -> 0.2 | F62: Case Packaging | G62: 1 | H62: =C62 -> 0.2 | I62: =G62*H62 -> 0.2
A63: Labour | B63: 180 | C63: =C53 -> 20 | D63: =C63/B63 -> 0.11111111 | F63: Labour | G63: 180 | H63: =C53 -> 20 | I63: =H63/G63 -> 0.11111111
A64: Box end label | B64: 1 | C64: 0.01 | D64: =B64*C64 -> 0.01 | F64: Box end label | G64: 1 | H64: 0.01 | I64: =G64*H64 -> 0.01
A65: COST | D65: =SUM(D61:D64) -> 12.246864 | F65: COST | I65: =SUM(I61:I64) -> 10.062136
A66: PER EACH | D66: =D65/9 -> 1.3607627 | F66: PER EACH | I66: =I65/4 -> 2.5155339
A68: Small (6 per case)
B69: Weight | C69: Cost | D69: Total
A70: Product Cost | B70: 6 | C70: =D54 -> 1.3250837 | D70: =B70*C70 -> 7.950502
A71: Case Packaging | B71: 1 | C71: =C62 -> 0.2 | D71: =B71*C71 -> 0.2
A72: Labour | B72: 180 | C72: 20 | D72: =C72/B72 -> 0.11111111
A73: Box end label | B73: 1 | C73: 0.01 | D73: =B73*C73 -> 0.01
A74: COST | D74: =SUM(D70:D73) -> 8.2716131
A75: PER EACH | D75: =D74/6 -> 1.3786022
A77: Small (12 per case)
B78: Weight | C78: Cost | D78: Total
A79: Product Cost | B79: 12 | C79: =D54 -> 1.3250837 | D79: =B79*C79 -> 15.901004
A80: Case Packaging | B80: 1 | C80: =C62 -> 0.2 | D80: =B80*C80 -> 0.2
A81: Labour | B81: 180 | C81: 20 | D81: =C81/B81 -> 0.11111111
A82: Box end label | B82: 1 | C82: 0.01 | D82: =B82*C82 -> 0.01
A83: COST | D83: =SUM(D79:D82) -> 16.222115
A84: PER EACH | D84: =D83/12 -> 1.3518429

Sheet Steak & Stilton Pie
A1: Grasmere Farm Manual
A2: Product Page
A3: Steak & Stilton Pie
A4: INGREDIENTS | B4: . All allergens in BOLD.
A16: Product | B16: Steak & Stilton Pie Filling
B17: Weight | C17: Cost | D17: Total
A18: Cooked Beef | B18: 3 | C18: ='Ingredient Cost'!D59 -> 8.5 | D18: =B18*C18 -> 25.5
A19: Beef Juice/Water | B19: 2.2 | C19: 0 | D19: =B19*C19 -> 0
A20: Gravy Mix CW 111020 | B20: 0.45 | C20: 8.9 | D20: =B20*C20 -> 4.005
B23: =SUM(B18:B21) -> 5.65 | D23: =SUM(D18:D21) -> 29.505
A25: COST | D25: =D23/B23 -> 5.2221239
A28: Product | B28: Raw Steak & Stilton Pie Small | F28: Product | G28: Raw Steak & Stilton Pie Medium | K28: Product | L28: Raw Steak & Stilton Pie Large
B29: Weight | C29: Cost | D29: Total | G29: Weight | H29: Cost | I29: Total | L29: Weight | M29: Cost | N29: Total
A30: Steak & Stilton Pie Filling | B30: 0.129 | C30: =D25 -> 5.2221239 | D30: =B30*C30 -> 0.67365398 | F30: Steak & Stilton Pie Filling | G30: 0.257 | H30: =D25 -> 5.2221239 | I30: =G30*H30 -> 1.3420858 | K30: Steak & Stilton Pie Filling | L30: 0.74 | M30: =D25 -> 5.2221239 | N30: =L30*M30 -> 3.8643717
A31: Stilton | B31: 0.015 | C31: ='Ingredient Cost'!D18 -> 4.75 | D31: =B31*C31 -> 0.07125 | F31: Stilton | G31: 0.03 | H31: =C31 -> 4.75 | I31: =G31*H31 -> 0.1425 | K31: Stilton | L31: 0.05 | M31: =C31 -> 4.75 | N31: =L31*M31 -> 0.2375
A32: Pasty | C32: ='Pastry Costing'!F30 -> 0.21079469 | D32: =C32 -> 0.21079469 | F32: Pasty | H32: ='Pastry Costing'!F31 -> 0.3414143 | I32: =H32 -> 0.3414143 | K32: Pasty | M32: ='Pastry Costing'!F32 -> 0.5240744 | N32: =M32 -> 0.5240744
A33: Foil | B33: 1 | C33: ='Ingredient Cost'!D95 -> 0.09 | D33: =B33*C33 -> 0.09 | F33: Foil | H33: ='Ingredient Cost'!D96 -> 0.12 | I33: =H33 -> 0.12 | K33: Foil | M33: ='Ingredient Cost'!D97 -> 0.2 | N33: =M33 -> 0.2
A34: Egg Glaze | C34: ='Ingredient Cost'!C35 -> 0 | D34: =B34*C34 -> 0 | F34: Egg Glaze | H34: ='Ingredient Cost'!H35 -> 0 | I34: =G34*H34 -> 0 | K34: Egg Glaze | M34: ='Ingredient Cost'!M35 -> 0 | N34: =L34*M34 -> 0
A35: Labour | B35: 90 | C35: ='Steak Pie v2'!C53 -> 20 | D35: =C35/B35 -> 0.22222222 | F35: Labour | G35: 48 | H35: =C35 -> 20 | I35: =H35/G35 -> 0.41666667 | L35: 32 | M35: =C35 -> 20 | N35: =M35/L35 -> 0.625
A38: COST | D38: =SUM(D30:D35) -> 1.2679209 | F38: COST | I38: =SUM(I30:I35) -> 2.3626668 | K38: COST | N38: =SUM(N30:N35) -> 5.4509461
A41: Product | B41: Cooked Steak & Stilton Pie Small Case | F41: Product | G41: Cooked Steak & Stilton Pie Medium Case
B42: Weight | C42: Cost | D42: Total | G42: Weight | H42: Cost | I42: Total
A43: Pie | B43: 9 | C43: =D38 -> 1.2679209 | D43: =B43*C43 -> 11.411288 | F43: Pie | G43: 6 | H43: =I38 -> 2.3626668 | I43: =G43*H43 -> 14.176001
A44: Cooking Paper | B44: 1 | C44: ='Ingredient Cost'!D86 -> 0.12 | D44: =B44*C44 -> 0.12 | F44: Cooking Paper | G44: 1 | H44: =C44 -> 0.12 | I44: =G44*H44 -> 0.12
A45: Packaging | B45: 9 | C45: ='Ingredient Cost'!D90 -> 0.22 | D45: =B45*C45 -> 1.98 | F45: Packaging | G45: 6 | H45: 0.1 | I45: =G45*H45 -> 0.6
A46: Case | B46: 1 | C46: ='Ingredient Cost'!D108 -> 0.2 | D46: =B46*C46 -> 0.2 | F46: Case | G46: 1 | H46: =C46 -> 0.2 | I46: =G46*H46 -> 0.2
A47: Labour | B47: 20 | C47: =C35 -> 20 | D47: =C47/B47 -> 1 | F47: Labour | G47: 20 | H47: =C35 -> 20 | I47: =H47/G47 -> 1
F48: Label | G48: 6 | H48: ='Steak Pie v2'!H64 -> 0.01 | I48: =G48*H48 -> 0.06
F49: Box end label | G49: 6 | H49: 0.01 | I49: =G49*H49 -> 0.06
A52: COST | D52: =D43+D44+D45+D46+D47 -> 14.711288 | F52: COST | I52: =I43+I44+I45+I46+I47+I48+I49 -> 16.216001
A53: PER EACH | D53: =D52/9 -> 1.6345876 | F53: PER EACH | I53: =I52/6 -> 2.7026668

Sheet Steak & Stilton Pie v2
A1: Grasmere Farm
A2: Product Costings
A3: Steak & Kidney Pie
A4: INGREDIENTS | B4: . All allergens in BOLD.
A16: Sub-recipes
A18: Filling | F18: Cold Water Pastry
B19: Weight | C19: Cost | D19: Total | G19: Weight | H19: Cost | I19: Total
A20: Cooked Beef | B20: 3 | C20: ='Ingredient Cost'!$D$59 -> 8.5 | D20: =B20*C20 -> 25.5 | F20: Water | G20: 2.5
A21: Beef Juice/Water | B21: 2.2 | C21: 0 | D21: =B21*C21 -> 0 | F21: Fat/Butter | G21: 4 | H21: ='Ingredient Cost'!$D$6 -> 2.06 | I21: =G21*H21 -> 8.24
A22: Gravy Mix CW 111020 | B22: 0.45 | C22: ='Ingredient Cost'!$D$21 -> 8.9 | D22: =B22*C22 -> 4.005 | F22: Flour | G22: 8 | H22: ='Ingredient Cost'!$D$7 -> 0.62 | I22: =G22*H22 -> 4.96
A23: Total | B23: =SUM(B20:B22) -> 5.65 | D23: =SUM(D20:D23) -> 31.495 | F23: Salt | G23: 0.15 | H23: ='Ingredient Cost'!$D$8 -> 0.54 | I23: =G23*H23 -> 0.081
F24: Total | G24: =G20+G21+G22+G23 -> 14.65 | I24: =SUM(I20:I23) -> 13.281
A26: COST/kg | D26: =31.5/5.65 -> 5.5752212 | F26: COST/kg | I26: =I24/G24 -> 0.9065529
A28: Ingredient
A30: Small | F30: Medium | K30: Large
B31: Weight | C31: Cost | D31: Total | G31: Weight | H31: Cost | I31: Total | L31: Weight | M31: Cost | N31: Total
A32: Filling | B32: 0.129 | C32: =$D$26 -> 5.5752212 | D32: =B32*C32 -> 0.71920354 | F32: Filling | G32: 0.257 | H32: =$D$26 -> 5.5752212 | I32: =G32*H32 -> 1.4328319 | K32: Filling | L32: 0.74 | M32: =$D$26 -> 5.5752212 | N32: =L32*M32 -> 4.1256637
A33: Stilton | B33: 0.015 | C33: ='Ingredient Cost'!D18 -> 4.75 | D33: =B33*C33 -> 0.07125 | F33: Silton | G33: 0.015 | H33: ='Ingredient Cost'!D18 -> 4.75 | I33: =G33*H33 -> 0.07125 | K33: Stilton | L33: 0.015 | M33: ='Ingredient Cost'!D18 -> 4.75 | N33: =L33*M33 -> 0.07125
A34: Pastry | B34: 1 | C34: ='Pastry Costing'!$F$30 -> 0.21079469 | D34: =C34 -> 0.21079469 | F34: Pastry | G34: 1 | H34: ='Pastry Costing'!$F$31 -> 0.3414143 | I34: =H34 -> 0.3414143 | K34: Pastry | L34: 1 | M34: ='Pastry Costing'!$F$32 -> 0.5240744 | N34: =M34 -> 0.5240744
A35: Egg Glaze | B35: 1 | C35: ='Ingredient Cost'!$D$11 -> 0.02 | D35: =B35*C35 -> 0.02 | F35: Egg Glaze | G35: 1 | H35: ='Ingredient Cost'!$D$11 -> 0.02 | I35: =H35 -> 0.02 | K35: Egg Glaze | L35: 1 | M35: ='Ingredient Cost'!$D$11 -> 0.02 | N35: =L35*M35 -> 0.02
A36: COST | D36: =SUM(D32:D35) -> 1.0212482 | F36: COST | I36: =SUM(I32:I35) -> 1.8654962 | K36: COST | N36: =SUM(N32:N35) -> 4.7409881
A38: Individual Packaged Products (excl. Labour)
A40: Small - Cooked | F40: Medium | K40: Large
B41: Weight | C41: Cost | D41: Total | G41: Weight | H41: Cost | I41: Total | L41: Weight | M41: Cost | N41: Total
A42: Ingredient Cost | B42: 1 | C42: =$D$36 -> 1.0212482 | D42: =B42*C42 -> 1.0212482 | F42: Ingredient Cost | G42: 1 | H42: =$I$36 -> 1.8654962 | I42: =G42*H42 -> 1.8654962 | K42: Ingredient Cost | L42: 1 | M42: =$N$36 -> 4.7409881 | N42: =L42*M42 -> 4.7409881
A43: Foil | B43: 1 | C43: ='Ingredient Cost'!$D$95 -> 0.09 | D43: =B43*C43 -> 0.09 | F43: Foil | G43: 1 | H43: ='Ingredient Cost'!$D$83 -> 0.07 | I43: =G43*H43 -> 0.07 | K43: Foil | L43: 1 | M43: ='Ingredient Cost'!$D$83 -> 0.07 | N43: =L43*M43 -> 0.07
A44: Packaging | B44: 1 | C44: ='Ingredient Cost'!$D$89 -> 0.06 | D44: =B44*C44 -> 0.06 | F44: Packaging | G44: 1 | H44: 0.22 | I44: =H44*G44 -> 0.22 | K44: Packaging | L44: 1 | M44: 0.3 | N44: 0.3
F45: Label | G45: 1 | H45: 0.15 | I45: 0.15 | K45: Label | L45: 1 | M45: 0.15 | N45: 0.15
A46: COST | D46: =SUM(D42:D44) -> 1.1712482 | F46: COST | I46: =SUM(I42:I45) -> 2.3054962 | K46: COST | N46: =SUM(N42:N45) -> 5.2609881
A49: Individual Packaged Products (incl. Labour) | D49: = | E49: COGS
A51: Small | F51: Medium | K51: Large
B52: Weight | C52: Cost | D52: Total | G52: Weight | H52: Cost | I52: Total | L52: Weight | M52: Cost | N52: Total
A53: Packaged Product Cost | B53: 1 | C53: =$D$46 -> 1.1712482 | D53: =B53*C53 -> 1.1712482 | F53: Packaged Product Cost | G53: 1 | H53: =$I$46 -> 2.3054962 | I53: =G53*H53 -> 2.3054962 | K53: Packaged Product Cost | L53: 1 | M53: =$N$46 -> 5.2609881 | N53: =L53*M53 -> 5.2609881
A54: Labour | B54: 60 | C54: ='Ingredient Cost'!$B$113 -> 20 | D54: =C54/B54 -> 0.33333333 | F54: Labour | G54: 48 | H54: ='Ingredient Cost'!$B$113 -> 20 | I54: =H54/G54 -> 0.41666667 | K54: Labour | L54: 50 | M54: ='Ingredient Cost'!$B$113 -> 20 | N54: =M54/L54 -> 0.4
A55: COST | D55: =SUM(D53:D54) -> 1.5045816 | F55: COST | I55: =SUM(I53:I54) -> 2.7221628 | K55: COST | N55: =SUM(N53:N54) -> 5.6609881
B57: Labour Percentage | D57: =D$54/D$53 -> 0.28459666 | G57: Labour Percentage | I57: =I$54/I$53 -> 0.18072755 | L57: Labour Percentage | N57: =N$54/N$53 -> 0.076031344
A58: CASES
A60: Small (9 per case) | F60: Medium (4 per case)
B61: Weight | C61: Cost | D61: Total | G61: Weight | H61: Cost | I61: Total
A62: Product Cost | B62: 9 | C62: =D55 -> 1.5045816 | D62: =B62*C62 -> 13.541234 | F62: Product Cost | G62: 4 | H62: =I55 -> 2.7221628 | I62: =G62*H62 -> 10.888651
A63: Case Packaging | B63: 1 | C63: ='Ingredient Cost'!D108 -> 0.2 | D63: =B63*C63 -> 0.2 | F63: Case Packaging | G63: 1 | H63: =C63 -> 0.2 | I63: =G63*H63 -> 0.2
A64: Labour | B64: 180 | C64: =C54 -> 20 | D64: =C64/B64 -> 0.11111111 | F64: Labour | G64: 180 | H64: =C54 -> 20 | I64: =H64/G64 -> 0.11111111
A65: Box end label | B65: 1 | C65: 0.01 | D65: =B65*C65 -> 0.01 | F65: Box end label | G65: 1 | H65: 0.01 | I65: =G65*H65 -> 0.01
A66: COST | D66: =SUM(D62:D65) -> 13.862345 | F66: COST | I66: =SUM(I62:I65) -> 11.209762
A67: PER EACH | D67: =D66/9 -> 1.5402606 | F67: PER EACH | I67: =I66/4 -> 2.8024406
A69: Small (6 per case)
B70: Weight | C70: Cost | D70: Total
A71: Product Cost | B71: 6 | C71: =D55 -> 1.5045816 | D71: =B71*C71 -> 9.0274894
A72: Case Packaging | B72: 1 | C72: =C63 -> 0.2 | D72: =B72*C72 -> 0.2
A73: Labour | B73: 180 | C73: 20 | D73: =C73/B73 -> 0.11111111
A74: Box end label | B74: 1 | C74: 0.01 | D74: =B74*C74 -> 0.01
A75: COST | D75: =SUM(D71:D74) -> 9.3486005
A76: PER EACH | D76: =D75/6 -> 1.5581001
A78: Small (12 per case)
B79: Weight | C79: Cost | D79: Total
A80: Product Cost | B80: 12 | C80: =D55 -> 1.5045816 | D80: =B80*C80 -> 18.054979
A81: Case Packaging | B81: 1 | C81: =C63 -> 0.2 | D81: =B81*C81 -> 0.2
A82: Labour | B82: 180 | C82: 20 | D82: =C82/B82 -> 0.11111111
A83: Box end label | B83: 1 | C83: 0.01 | D83: =B83*C83 -> 0.01
A84: COST | D84: =SUM(D80:D83) -> 18.37609
A85: PER EACH | D85: =D84/12 -> 1.5313408

Sheet C&H Pie v2
A1: Grasmere Farm
A2: Product Costings
A3: Chicken & Ham Pie
A4: INGREDIENTS | B4: . All allergens in BOLD.
A16: Sub-recipes
A18: Filling | F18: Cold Water Pastry
B19: Weight | C19: Cost | D19: Total | G19: Weight | H19: Cost | I19: Total
A20: Cooked Chicken | B20: 1.25 | C20: ='Ingredient Cost'!D62 -> 7.55 | D20: =B20*C20 -> 9.4375 | F20: Water | G20: 2.5
A21: Cooked Gammon | B21: 0.75 | C21: 4.66 | D21: =B21*C21 -> 3.495 | F21: Fat/Butter | G21: 4 | H21: ='Ingredient Cost'!$D$6 -> 2.06 | I21: =G21*H21 -> 8.24
A22: Milk & Stock | B22: 2.25 | C22: ='Ingredient Cost'!D12 -> 0.74 | D22: =B22*C22 -> 1.665 | F22: Flour | G22: 8 | H22: ='Ingredient Cost'!$D$7 -> 0.62 | I22: =G22*H22 -> 4.96
A23: Sauce Mix CW 110715 | B23: 0.375 | C23: ='Ingredient Cost'!D20 -> 8.95 | D23: =B23*C23 -> 3.35625 | F23: Salt | G23: 0.15 | H23: ='Ingredient Cost'!$D$8 -> 0.54 | I23: =G23*H23 -> 0.081
B24: =SUM(B20:B23) -> 4.625 | D24: =SUM(D20:D23) -> 17.95375 | F24: Total | G24: =G20+G21+G22+G23 -> 14.65 | I24: =SUM(I20:I23) -> 13.281
A26: COST | D26: =D24/B24 -> 3.8818919 | F26: COST/kg | I26: =I24/G24 -> 0.9065529
A28: Ingredient
A30: Small | F30: Medium | K30: Large
B31: Weight | C31: Cost | D31: Total | G31: Weight | H31: Cost | I31: Total | L31: Weight | M31: Cost | N31: Total
A32: C&H Filling Mix | B32: 0.105 | C32: =$D$26 -> 3.8818919 | D32: =B32*C32 -> 0.40759865 | F32: C&H Filling Mix | G32: 0.3 | H32: =$D$26 -> 3.8818919 | I32: =G32*H32 -> 1.1645676 | K32: C&H Filling Mix | L32: 0.6 | M32: =$D$26 -> 3.8818919 | N32: =L32*M32 -> 2.3291351
A33: Premium Sausage | B33: 0.03 | C33: ='Ingredient Cost'!$D$52 -> 2 | D33: =B33*C33 -> 0.06 | F33: Premium Sausage | G33: 0.06 | H33: ='Ingredient Cost'!$D$52 -> 2 | I33: =G33*H33 -> 0.12 | K33: Premium Sausage | L33: 0.12 | M33: ='Ingredient Cost'!$D$52 -> 2 | N33: =L33*M33 -> 0.24
A34: Pastry | C34: ='Pastry Costing'!F34 -> 0 | D34: ='Pastry Costing'!F30 -> 0.21079469 | F34: Pasty | H34: ='Pastry Costing'!K34 -> 0 | I34: ='Pastry Costing'!F31 -> 0.3414143 | K34: Pasty | M34: ='Pastry Costing'!P34 -> 0 | N34: ='Pastry Costing'!F32 -> 0.5240744
A35: Foil | C35: ='Ingredient Cost'!$D$95 -> 0.09 | D35: =C35 -> 0.09 | F35: Foil | H35: ='Ingredient Cost'!$D$95 -> 0.09 | I35: =H35 -> 0.09 | K35: Foil | M35: ='Ingredient Cost'!$D$95 -> 0.09 | N35: =M35 -> 0.09
A36: Egg Glaze | C36: ='Ingredient Cost'!$C$36 -> 0 | D36: =B36*C36 -> 0 | F36: Egg Glaze | H36: ='Ingredient Cost'!$C$36 -> 0 | I36: =G36*H36 -> 0 | K36: Egg Glaze | M36: ='Ingredient Cost'!$C$36 -> 0 | N36: =L36*M36 -> 0
A37: COST | D37: =SUM(D32:D34) -> 0.67839334 | F37: COST | I37: =SUM(I32:I34) -> 1.6259819 | K37: COST | N37: =SUM(N32:N34) -> 3.0932095
A39: Individual Packaged Products (excl. Labour)
A41: Small - Cooked | F41: Medium | K41: Large
B42: Weight | C42: Cost | D42: Total | G42: Weight | H42: Cost | I42: Total | L42: Weight | M42: Cost | N42: Total
A43: Ingredient Cost | B43: 1 | C43: =$D$37 -> 0.67839334 | D43: =B43*C43 -> 0.67839334 | F43: Ingredient Cost | G43: 1 | H43: =$I$37 -> 1.6259819 | I43: =G43*H43 -> 1.6259819 | K43: Ingredient Cost | L43: 1 | M43: =$N$37 -> 3.0932095 | N43: =L43*M43 -> 3.0932095
A44: Foil | B44: 1 | C44: ='Ingredient Cost'!$D$95 -> 0.09 | D44: =B44*C44 -> 0.09 | F44: Foil | G44: 1 | H44: ='Ingredient Cost'!$D$83 -> 0.07 | I44: =G44*H44 -> 0.07 | K44: Foil | L44: 1 | M44: ='Ingredient Cost'!$D$83 -> 0.07 | N44: =L44*M44 -> 0.07
A45: Packaging | B45: 1 | C45: ='Ingredient Cost'!$D$89 -> 0.06 | D45: =B45*C45 -> 0.06 | F45: Packaging | G45: 1 | H45: 0.22 | I45: =H45*G45 -> 0.22 | K45: Packaging | L45: 1 | M45: 0.3 | N45: 0.3
F46: Label | G46: 1 | H46: 0.15 | I46: 0.15 | K46: Label | L46: 1 | M46: 0.15 | N46: 0.15
A47: COST | D47: =SUM(D43:D45) -> 0.82839334 | F47: COST | I47: =SUM(I43:I46) -> 2.0659819 | K47: COST | N47: =SUM(N43:N46) -> 3.6132095
A50: Individual Packaged Products (incl. Labour) | D50: = | E50: COGS
A52: Small | F52: Medium | K52: Large
B53: Weight | C53: Cost | D53: Total | G53: Weight | H53: Cost | I53: Total | L53: Weight | M53: Cost | N53: Total
A54: Packaged Product Cost | B54: 1 | C54: =$D$47 -> 0.82839334 | D54: =B54*C54 -> 0.82839334 | F54: Packaged Product Cost | G54: 1 | H54: =$I$47 -> 2.0659819 | I54: =G54*H54 -> 2.0659819 | K54: Packaged Product Cost | L54: 1 | M54: =$N$47 -> 3.6132095 | N54: =L54*M54 -> 3.6132095
A55: Labour | B55: 60 | C55: ='Ingredient Cost'!$B$113 -> 20 | D55: =C55/B55 -> 0.33333333 | F55: Labour | G55: 48 | H55: ='Ingredient Cost'!$B$113 -> 20 | I55: =H55/G55 -> 0.41666667 | K55: Labour | L55: 32 | M55: ='Ingredient Cost'!$B$113 -> 20 | N55: =M55/L55 -> 0.625
A56: COST | D56: =SUM(D54:D55) -> 1.1617267 | F56: COST | I56: =SUM(I54:I55) -> 2.4826485 | K56: COST | N56: =SUM(N54:N55) -> 4.2382095
B58: Labour Percentage | D58: =D$55/D$54 -> 0.40238534 | G58: Labour Percentage | I58: =I$55/I$54 -> 0.20167973 | L58: Labour Percentage | N58: =N$55/N$54 -> 0.17297641
A59: CASES
A60: Small (9 per case) | F60: Medium (4 per case)
B61: Weight | C61: Cost | D61: Total | G61: Weight | H61: Cost | I61: Total
A62: Product Cost | B62: 9 | C62: =D56 -> 1.1617267 | D62: =B62*C62 -> 10.45554 | F62: Product Cost | G62: 4 | H62: =I56 -> 2.4826485 | I62: =G62*H62 -> 9.9305941
A63: Case Packaging | B63: 1 | C63: ='Ingredient Cost'!D108 -> 0.2 | D63: =B63*C63 -> 0.2 | F63: Case Packaging | G63: 1 | H63: =C63 -> 0.2 | I63: =G63*H63 -> 0.2
A64: Labour | B64: 180 | C64: =C55 -> 20 | D64: =C64/B64 -> 0.11111111 | F64: Labour | G64: 180 | H64: =C55 -> 20 | I64: =H64/G64 -> 0.11111111
A65: Box end label | B65: 1 | C65: 0.01 | D65: =B65*C65 -> 0.01 | F65: Box end label | G65: 1 | H65: 0.01 | I65: =G65*H65 -> 0.01
A66: COST | D66: =SUM(D62:D65) -> 10.776651 | F66: COST | I66: =SUM(I62:I65) -> 10.251705
A67: PER EACH | D67: =D66/9 -> 1.1974057 | F67: PER EACH | I67: =I66/4 -> 2.5629263
A69: Small (6 per case)
B70: Weight | C70: Cost | D70: Total
A71: Product Cost | B71: 6 | C71: =D56 -> 1.1617267 | D71: =B71*C71 -> 6.97036
A72: Case Packaging | B72: 1 | C72: =C63 -> 0.2 | D72: =B72*C72 -> 0.2
A73: Labour | B73: 180 | C73: 20 | D73: =C73/B73 -> 0.11111111
A74: Box end label | B74: 1 | C74: 0.01 | D74: =B74*C74 -> 0.01
A75: COST | D75: =SUM(D71:D74) -> 7.2914711
A76: PER EACH | D76: =D75/6 -> 1.2152452
A78: Small (12 per case)
B79: Weight | C79: Cost | D79: Total
A80: Product Cost | B80: 12 | C80: =D56 -> 1.1617267 | D80: =B80*C80 -> 13.94072
A81: Case Packaging | B81: 1 | C81: =C63 -> 0.2 | D81: =B81*C81 -> 0.2
A82: Labour | B82: 180 | C82: 20 | D82: =C82/B82 -> 0.11111111
A83: Box end label | B83: 1 | C83: 0.01 | D83: =B83*C83 -> 0.01
A84: COST | D84: =SUM(D80:D83) -> 14.261831
A85: PER EACH | D85: =D84/12 -> 1.1884859

Sheet C&H Pie
A1: Grasmere Farm Manual
A2: Product Page
A3: Chicken & Ham Pie
A4: INGREDIENTS | B4: 2
A16: Product | B16: Chicken & Ham Pie Filling
B17: Weight | C17: Cost | D17: Total
A18: Cooked Chicken | B18: 1.25 | C18: ='Ingredient Cost'!D62 -> 7.55 | D18: =B18*C18 -> 9.4375
A19: Cooked Gammon | B19: 0.75 | C19: 4.66 | D19: =B19*C19 -> 3.495
A20: Milk & Stock | B20: 2.25 | C20: ='Ingredient Cost'!D12 -> 0.74 | D20: =B20*C20 -> 1.665
A21: Sauce Mix CW 110715 | B21: 0.375 | C21: ='Ingredient Cost'!D20 -> 8.95 | D21: =B21*C21 -> 3.35625
B22: =SUM(B18:B21) -> 4.625 | D22: =SUM(D18:D21) -> 17.95375
A24: COST | D24: =D22/B22 -> 3.8818919
A26: Product | B26: Chicken & Ham Pie Small | F26: Product | G26: Chicken & Ham Pie Medium | K26: Product | L26: Chicken & Ham Pie Large
B27: Weight | C27: Cost | D27: Total | G27: Weight | H27: Cost | I27: Total | L27: Weight | M27: Cost | N27: Total
A28: C&H Filling Mix | B28: 0.105 | C28: =$D$24 -> 3.8818919 | D28: =B28*C28 -> 0.40759865 | F28: C&H Filling Mix | G28: 0.3 | H28: =$D$24 -> 3.8818919 | I28: =G28*H28 -> 1.1645676 | K28: C&H Filling Mix | L28: 0.6 | M28: =$D$24 -> 3.8818919 | N28: =L28*M28 -> 2.3291351
A29: Premium Sausage | B29: 0.03 | C29: ='Ingredient Cost'!$D$52 -> 2 | D29: =B29*C29 -> 0.06 | F29: Premium Sausage | G29: 0.06 | H29: ='Ingredient Cost'!$D$52 -> 2 | I29: =G29*H29 -> 0.12 | K29: Premium Sausage | L29: 0.12 | M29: ='Ingredient Cost'!$D$52 -> 2 | N29: =L29*M29 -> 0.24
A30: Pastry | C30: ='Pastry Costing'!F30 -> 0.21079469 | D30: ='Pastry Costing'!F30 -> 0.21079469 | F30: Pasty | H30: ='Pastry Costing'!K30 -> 0 | I30: ='Pastry Costing'!F31 -> 0.3414143 | K30: Pasty | M30: ='Pastry Costing'!P30 -> 0 | N30: ='Pastry Costing'!F32 -> 0.5240744
A31: Foil | C31: ='Ingredient Cost'!$D$95 -> 0.09 | D31: =C31 -> 0.09 | F31: Foil | H31: ='Ingredient Cost'!$D$95 -> 0.09 | I31: =H31 -> 0.09 | K31: Foil | M31: ='Ingredient Cost'!$D$95 -> 0.09 | N31: =M31 -> 0.09
A32: Egg Glaze | C32: ='Ingredient Cost'!$C$36 -> 0 | D32: =B32*C32 -> 0 | F32: Egg Glaze | H32: ='Ingredient Cost'!$C$36 -> 0 | I32: =G32*H32 -> 0 | K32: Egg Glaze | M32: ='Ingredient Cost'!$C$36 -> 0 | N32: =L32*M32 -> 0
A33: Labour (90 an hour) | B33: 90 | C33: ='Steak Pie v2'!$C$53 -> 20 | D33: =C33/B33 -> 0.22222222 | F33: Labour (48 per hour) | G33: 48 | H33: ='Steak Pie v2'!$C$53 -> 20 | I33: =H33/G33 -> 0.41666667 | K33: Labour (32 per hour) | L33: 32 | M33: ='Steak Pie v2'!$C$53 -> 20 | N33: =M33/L33 -> 0.625
A36: COST | D36: =D28+D29+D30+D31+D32+D33 -> 0.99061556 | F36: COST | I36: =I28+I29+I30+I31+I32+I33 -> 2.1326485 | K36: COST | N36: =N28+N29+N30+N31+N32+N33 -> 3.8082095
A38: Product | B38: Cooked Chicken & Ham Small Case | F38: Product | G38: Cooked Chicken & Ham Pie Medium Case
B39: No | C39: Cost | D39: Total | G39: Weight | H39: Cost | I39: Total
A40: Pie | B40: 9 | C40: =D36 -> 0.99061556 | D40: =B40*C40 -> 8.91554 | F40: Pie | G40: 6 | H40: =I36 -> 2.1326485 | I40: =G40*H40 -> 12.795891
A41: Cooking Paper in No | B41: 1 | C41: ='Ingredient Cost'!D86 -> 0.12 | D41: =B41*C41 -> 0.12 | F41: Cooking Paper | G41: 1 | H41: =C41 -> 0.12 | I41: =G41*H41 -> 0.12
A42: Packaging | B42: 9 | C42: ='Ingredient Cost'!D89 -> 0.06 | D42: =B42*C42 -> 0.54 | F42: Packaging | G42: 6 | H42: 0.1 | I42: =G42*H42 -> 0.6
A43: Case | B43: 1 | C43: ='Ingredient Cost'!D108 -> 0.2 | D43: =B43*C43 -> 0.2 | F43: Case | G43: 1 | H43: =C43 -> 0.2 | I43: =G43*H43 -> 0.2
A44: Wrap/Label | C44: 0.12 | D44: =C44 -> 0.12 | F44: Labour | G44: 20 | H44: =C33 -> 20 | I44: =H44/G44 -> 1
A45: Labour (75 per hour) | B45: 20 | C45: =C33 -> 20 | D45: =C45/B45 -> 1 | F45: Label | G45: 6 | H45: ='Steak Pie v2'!H64 -> 0.01 | I45: =G45*H45 -> 0.06
F46: Box end label | G46: 6 | H46: 0.01 | I46: =G46*H46 -> 0.06
A48: COST PER 9 CASE | D48: =D40+D41+D42+D43+D44+D45 -> 10.89554
A49: PER EACH | D49: =D48/9 -> 1.2106156 | F49: COST | I49: =I40+I41+I42+I43+I44+I45+I46 -> 14.835891
F50: PER EACH | I50: =I49/6 -> 2.4726485

Sheet C&C Pie v2
A1: Grasmere Farm
A2: Product Costings
A3: Chicken & Chorizo Pie
A4: INGREDIENTS | B4: . All allergens in BOLD.
A16: Sub-recipes
A18: Filling | F18: Cold Water Pastry
B19: Weight | C19: Cost | D19: Total | G19: Weight | H19: Cost | I19: Total
A20: Cooked Chicken | B20: 1.25 | C20: ='Ingredient Cost'!D62 -> 7.55 | D20: =B20*C20 -> 9.4375 | F20: Water | G20: 2.5
A21: Cooked Chorizo | B21: 0.3 | C21: ='Ingredient Cost'!D63 -> 6 | D21: =B21*C21 -> 1.8 | F21: Fat/Butter | G21: 4 | H21: ='Ingredient Cost'!$D$6 -> 2.06 | I21: =G21*H21 -> 8.24
A22: Milk & Stock | B22: 2.25 | C22: ='Ingredient Cost'!D12 -> 0.74 | D22: =B22*C22 -> 1.665 | F22: Flour | G22: 8 | H22: ='Ingredient Cost'!$D$7 -> 0.62 | I22: =G22*H22 -> 4.96
A23: Sauce Mix CW 110715 | B23: 0.375 | C23: ='Ingredient Cost'!D20 -> 8.95 | D23: =B23*C23 -> 3.35625 | F23: Salt | G23: 0.15 | H23: ='Ingredient Cost'!$D$8 -> 0.54 | I23: =G23*H23 -> 0.081
A24: Total | B24: =SUM(B20:B23) -> 4.175 | D24: =SUM(D20:D23) -> 16.25875 | F24: Total | G24: =G20+G21+G22+G23 -> 14.65 | I24: =SUM(I20:I23) -> 13.281
A26: COST | D26: =D24/B24 -> 3.8943114 | F26: COST/kg | I26: =I24/G24 -> 0.9065529
A28: Ingredient
A30: Small | F30: Medium | K30: Large
B31: Weight | C31: Cost | D31: Total | G31: Weight | H31: Cost | I31: Total | L31: Weight | M31: Cost | N31: Total
A32: C&H Filling Mix | B32: 0.129 | C32: =$D$26 -> 3.8943114 | D32: =B32*C32 -> 0.50236617 | F32: C&H Filling Mix | G32: 0.3 | H32: =$D$26 -> 3.8943114 | I32: =G32*H32 -> 1.1682934 | K32: C&H Filling Mix | L32: 0.6 | M32: =$D$26 -> 3.8943114 | N32: =L32*M32 -> 2.3365868
A33: Pastry | C33: ='Pastry Costing'!F34 -> 0 | D33: ='Pastry Costing'!F30 -> 0.21079469 | F33: Pastry | H33: ='Pastry Costing'!K34 -> 0 | I33: ='Pastry Costing'!F31 -> 0.3414143 | K33: Pastry | M33: ='Pastry Costing'!P34 -> 0 | N33: ='Pastry Costing'!F32 -> 0.5240744
A34: Foil | C34: ='Ingredient Cost'!$D$95 -> 0.09 | D34: =C34 -> 0.09 | F34: Foil | H34: ='Ingredient Cost'!$D$95 -> 0.09 | I34: =H34 -> 0.09 | K34: Foil | M34: ='Ingredient Cost'!$D$95 -> 0.09 | N34: =M34 -> 0.09
A35: Egg Glaze | B35: 1 | C35: ='Ingredient Cost'!$D$11 -> 0.02 | D35: =B35*C35 -> 0.02 | F35: Egg Glaze | G35: 1 | H35: ='Ingredient Cost'!$D$11 -> 0.02 | I35: =G35*H35 -> 0.02 | K35: Egg Glaze | L35: 1 | M35: ='Ingredient Cost'!$D$11 -> 0.02 | N35: =L35*M35 -> 0.02
A36: COST | D36: =SUM(D32:D33) -> 0.71316086 | F36: COST | I36: =SUM(I32:I33) -> 1.5097077 | K36: COST | N36: =SUM(N32:N33) -> 2.8606612
A38: Individual Packaged Products (excl. Labour)
A40: Small - Cooked | F40: Medium | K40: Large
B41: Weight | C41: Cost | D41: Total | G41: Weight | H41: Cost | I41: Total | L41: Weight | M41: Cost | N41: Total
A42: Ingredient Cost | B42: 1 | C42: =$D$36 -> 0.71316086 | D42: =B42*C42 -> 0.71316086 | F42: Ingredient Cost | G42: 1 | H42: =$I$36 -> 1.5097077 | I42: =G42*H42 -> 1.5097077 | K42: Ingredient Cost | L42: 1 | M42: =$N$36 -> 2.8606612 | N42: =L42*M42 -> 2.8606612
A43: Foil | B43: 1 | C43: ='Ingredient Cost'!$D$95 -> 0.09 | D43: =B43*C43 -> 0.09 | F43: Foil | G43: 1 | H43: ='Ingredient Cost'!$D$83 -> 0.07 | I43: =G43*H43 -> 0.07 | K43: Foil | L43: 1 | M43: ='Ingredient Cost'!$D$83 -> 0.07 | N43: =L43*M43 -> 0.07
A44: Packaging | B44: 1 | C44: ='Ingredient Cost'!$D$89 -> 0.06 | D44: =B44*C44 -> 0.06 | F44: Packaging | G44: 1 | H44: 0.22 | I44: =H44*G44 -> 0.22 | K44: Packaging | L44: 1 | M44: 0.3 | N44: 0.3
F45: Label | G45: 1 | H45: 0.15 | I45: 0.15 | K45: Label | L45: 1 | M45: 0.15 | N45: 0.15
A46: COST | D46: =SUM(D42:D44) -> 0.86316086 | F46: COST | I46: =SUM(I42:I45) -> 1.9497077 | K46: COST | N46: =SUM(N42:N45) -> 3.3806612
A49: Individual Packaged Products (incl. Labour) | D49: = | E49: COGS
A51: Small | F51: Medium | K51: Large
B52: Weight | C52: Cost | D52: Total | G52: Weight | H52: Cost | I52: Total | L52: Weight | M52: Cost | N52: Total
A53: Packaged Product Cost | B53: 1 | C53: =$D$46 -> 0.86316086 | D53: =B53*C53 -> 0.86316086 | F53: Packaged Product Cost | G53: 1 | H53: =$I$46 -> 1.9497077 | I53: =G53*H53 -> 1.9497077 | K53: Packaged Product Cost | L53: 1 | M53: =$N$46 -> 3.3806612 | N53: =L53*M53 -> 3.3806612
A54: Labour | B54: 60 | C54: ='Ingredient Cost'!$B$113 -> 20 | D54: =C54/B54 -> 0.33333333 | F54: Labour | G54: 48 | H54: ='Ingredient Cost'!$B$113 -> 20 | I54: =H54/G54 -> 0.41666667 | K54: Labour | L54: 32 | M54: ='Ingredient Cost'!$B$113 -> 20 | N54: =M54/L54 -> 0.625
A55: COST | D55: =SUM(D53:D54) -> 1.1964942 | F55: COST | I55: =SUM(I53:I54) -> 2.3663744 | K55: COST | N55: =SUM(N53:N54) -> 4.0056612
B57: Labour Percentage | D57: =D$54/D$53 -> 0.38617754 | G57: Labour Percentage | I57: =I$54/I$53 -> 0.21370725 | L57: Labour Percentage | N57: =N$54/N$53 -> 0.18487508
A58: CASES
A60: Small (9 per case) | F60: Medium (4 per case)
B61: Weight | C61: Cost | D61: Total | G61: Weight | H61: Cost | I61: Total
A62: Product Cost | B62: 9 | C62: =D55 -> 1.1964942 | D62: =B62*C62 -> 10.768448 | F62: Product Cost | G62: 4 | H62: =I55 -> 2.3663744 | I62: =G62*H62 -> 9.4654975
A63: Case Packaging | B63: 1 | C63: ='Ingredient Cost'!D108 -> 0.2 | D63: =B63*C63 -> 0.2 | F63: Case Packaging | G63: 1 | H63: =C63 -> 0.2 | I63: =G63*H63 -> 0.2
A64: Labour | B64: 40 | C64: =C54 -> 20 | D64: =C64/B64 -> 0.5 | F64: Labour | G64: 40 | H64: =C54 -> 20 | I64: =H64/G64 -> 0.5
A65: Box end label | B65: 1 | C65: 0.01 | D65: =B65*C65 -> 0.01 | F65: Box end label | G65: 1 | H65: 0.01 | I65: =G65*H65 -> 0.01
A66: COST | D66: =SUM(D62:D65) -> 11.478448 | F66: COST | I66: =SUM(I62:I65) -> 10.175498
A67: PER EACH | D67: =D66/9 -> 1.2753831 | F67: PER EACH | I67: =I66/4 -> 2.5438744
A69: Small (6 per case)
B70: Weight | C70: Cost | D70: Total
A71: Product Cost | B71: 6 | C71: =D55 -> 1.1964942 | D71: =B71*C71 -> 7.1789651
A72: Case Packaging | B72: 1 | C72: =C63 -> 0.2 | D72: =B72*C72 -> 0.2
A73: Labour | B73: 40 | C73: 20 | D73: =C73/B73 -> 0.5
A74: Box end label | B74: 1 | C74: 0.01 | D74: =B74*C74 -> 0.01
A75: COST | D75: =SUM(D71:D74) -> 7.8889651
A76: PER EACH | D76: =D75/6 -> 1.3148275
A78: Small (12 per case)
B79: Weight | C79: Cost | D79: Total
A80: Product Cost | B80: 12 | C80: =D55 -> 1.1964942 | D80: =B80*C80 -> 14.35793
A81: Case Packaging | B81: 1 | C81: =C63 -> 0.2 | D81: =B81*C81 -> 0.2
A82: Labour | B82: 40 | C82: 20 | D82: =C82/B82 -> 0.5
A83: Box end label | B83: 1 | C83: 0.01 | D83: =B83*C83 -> 0.01
A84: COST | D84: =SUM(D80:D83) -> 15.06793
A85: PER EACH | D85: =D84/12 -> 1.2556609

Sheet C&C Pie
A1: Grasmere Farm Manual
A2: Product Page
A3: Chicken & Chorizo Pie
A4: INGREDIENTS | B4: . All allergens in BOLD.
A16: Product | B16: Chicken & Chorizo Pie Filling
B17: Weight | C17: Cost | D17: Total
A18: Cooked Chicken | B18: 1.25 | C18: ='Ingredient Cost'!D62 -> 7.55 | D18: =B18*C18 -> 9.4375
A19: Chorizo | B19: 0.3 | C19: 6 | D19: =B19*C19 -> 1.8
A20: Milk & Stock | B20: 2.25 | C20: ='Ingredient Cost'!D11 -> 0.02 | D20: =B20*C20 -> 0.045
A21: Sauce Mix CW 110715 | B21: 0.375 | C21: ='Ingredient Cost'!D20 -> 8.95 | D21: =B21*C21 -> 3.35625
B23: =SUM(B18:B21) -> 4.175 | D23: =SUM(D18:D21) -> 14.63875
A25: COST | D25: =D23/B23 -> 3.5062874
A27: Product | B27: Chicken & Chorizo Pie Individual | F27: Product | G27: Chicken & Chorizo Pie Medium | K27: Product | L27: Chicken & Chorizo Pie Large
B28: Weight | C28: Cost | D28: Total | G28: Weight | H28: Cost | I28: Total | L28: Weight | M28: Cost | N28: Total
A29: Filling | B29: 0.129 | C29: =D25 -> 3.5062874 | D29: =B29*C29 -> 0.45231108 | F29: Filling | G29: 0.257 | H29: =C29 -> 3.5062874 | I29: =G29*H29 -> 0.90111587 | K29: Filling | L29: 0.74 | M29: =C29 -> 3.5062874 | N29: =L29*M29 -> 2.5946527
A30: Pasty (base & lid) | C30: ='Pastry Costing'!F30 -> 0.21079469 | D30: =C30 -> 0.21079469 | F30: Pasty (base & lid) | H30: ='Pastry Costing'!F31 -> 0.3414143 | I30: =H30 -> 0.3414143 | K30: Pasty (base & lid) | M30: ='Pastry Costing'!F32 -> 0.5240744 | N30: =M30 -> 0.5240744
A31: Egg Glaze | C31: ='Ingredient Cost'!C35 -> 0 | D31: =B31*C31 -> 0 | F31: Egg Glaze | H31: =C31 -> 0 | I31: =H31 -> 0 | K31: Egg Glaze | M31: ='Ingredient Cost'!M35 -> 0 | N31: =L31*M31 -> 0
A32: Foil | B32: 1 | C32: ='Ingredient Cost'!D95 -> 0.09 | D32: =B32*C32 -> 0.09 | F32: Foil | G32: 1 | H32: ='Ingredient Cost'!D96 -> 0.12 | I32: =G32*H32 -> 0.12 | K32: Foil | L32: 1 | M32: ='Ingredient Cost'!D97 -> 0.2 | N32: =L32*M32 -> 0.2
A33: Labour | B33: 90 | C33: 15 | D33: =C33/B33 -> 0.16666667 | F33: Labour | G33: 48 | H33: =C33 -> 15 | I33: =H33/G33 -> 0.3125 | K33: Labour | L33: 32 | M33: 15 | N33: =M33/L33 -> 0.46875
A36: COST | D36: =D29+D30+D31+D32+D33 -> 0.91977243 | F36: COST | I36: =I29+I30+I31+I32+I33 -> 1.6750302 | K36: COST | N36: =N29+N30+N31+N32+N33 -> 3.7874771
A38: Product | B38: Chicken & Chorizo Pie Individual Case Raw
B39: Weight | C39: Cost | D39: Total
A40: Filling | B40: 0.129 | C40: =D25 -> 3.5062874 | D40: =B40*C40 -> 0.45231108
A41: Pasty (base & lid) | C41: ='Pastry Costing'!F30 -> 0.21079469 | D41: =C41 -> 0.21079469
A42: Egg Glaze | C42: ='Ingredient Cost'!C59 -> 0 | D42: =B42*C42 -> 0
A43: Foil | B43: 1 | C43: ='Ingredient Cost'!D95 -> 0.09 | D43: =B43*C43 -> 0.09
A44: Labour | B44: 90 | C44: ='Steak Pie v2'!C53 -> 20 | D44: =C44/B44 -> 0.22222222
A45: Case | B45: 1 | C45: ='Ingredient Cost'!D108 -> 0.2 | D45: =B45*C45 -> 0.2
A48: COST | D48: =SUM(D40:D45) -> 1.175328
A50: Product | B50: Cooked Chicken & Chorizo Small Case Further Retail | F50: Product | G50: Cooked Chicken & Chorizo Medium Case Further Retail
B51: Weight | C51: Cost | D51: Total | G51: Weight | H51: Cost | I51: Total
A52: Pie | B52: 9 | C52: =D36 -> 0.91977243 | D52: =B52*C52 -> 8.2779519 | F52: Pie | G52: 6 | H52: =I36 -> 1.6750302 | I52: =G52*H52 -> 10.050181
A53: Cooking Paper | B53: 1 | C53: ='Ingredient Cost'!D86 -> 0.12 | D53: =B53*C53 -> 0.12 | F53: Cooking Paper | G53: 1 | H53: =C53 -> 0.12 | I53: =G53*H53 -> 0.12
A54: Packaging | B54: 9 | C54: ='Ingredient Cost'!D90 -> 0.22 | D54: =B54*C54 -> 1.98 | F54: Packaging | G54: 6 | H54: 0.1 | I54: =G54*H54 -> 0.6
A55: Case | B55: 1 | C55: ='Ingredient Cost'!D108 -> 0.2 | D55: =B55*C55 -> 0.2 | F55: Case | G55: 1 | H55: =C55 -> 0.2 | I55: =G55*H55 -> 0.2
A56: Labour | B56: 75 | C56: =C44 -> 20 | D56: =C56/B56 -> 0.26666667 | F56: Labour | G56: 75 | H56: =C44 -> 20 | I56: =H56/G56 -> 0.26666667
F57: Label | G57: 6 | H57: ='Steak Pie v2'!H64 -> 0.01 | I57: =G57*H57 -> 0.06
F58: Box end label | G58: 6 | H58: 0.01 | I58: =G58*H58 -> 0.06
A61: COST | D61: =D52+D53+D54+D55+D56 -> 10.844619 | F61: COST | I61: =I52+I53+I54+I55+I56+I57+I58 -> 11.356848
A62: PER EACH | D62: =D61/9 -> 1.2049576 | F62: PER EACH | I62: =I61/6 -> 1.8928079

Sheet Pulled Pork Pie v2 (2)
A1: Grasmere Farm
A2: Product Costings
A3: Chicken & Chorizo Pie
A4: INGREDIENTS | B4: . All allergens in BOLD.
A16: Sub-recipes
A18: Filling | F18: Cold Water Pastry
B19: Weight | C19: Cost | D19: Total | G19: Weight | H19: Cost | I19: Total
A20: Cooked Chicken | B20: 1.25 | C20: ='Ingredient Cost'!D62 -> 7.55 | D20: =B20*C20 -> 9.4375 | F20: Water | G20: 2.5
A21: Cooked Chorizo | B21: 0.3 | C21: ='Ingredient Cost'!D63 -> 6 | D21: =B21*C21 -> 1.8 | F21: Fat/Butter | G21: 4 | H21: ='Ingredient Cost'!$D$6 -> 2.06 | I21: =G21*H21 -> 8.24
A22: Milk & Stock | B22: 2.25 | C22: ='Ingredient Cost'!D12 -> 0.74 | D22: =B22*C22 -> 1.665 | F22: Flour | G22: 8 | H22: ='Ingredient Cost'!$D$7 -> 0.62 | I22: =G22*H22 -> 4.96
A23: Sauce Mix CW 110715 | B23: 0.375 | C23: ='Ingredient Cost'!D20 -> 8.95 | D23: =B23*C23 -> 3.35625 | F23: Salt | G23: 0.15 | H23: ='Ingredient Cost'!$D$8 -> 0.54 | I23: =G23*H23 -> 0.081
A24: Total | B24: =SUM(B20:B23) -> 4.175 | D24: =SUM(D20:D23) -> 16.25875 | F24: Total | G24: =G20+G21+G22+G23 -> 14.65 | I24: =SUM(I20:I23) -> 13.281
A26: COST | D26: =D24/B24 -> 3.8943114 | F26: COST/kg | I26: =I24/G24 -> 0.9065529
A28: Ingredient
A30: Small | F30: Medium | K30: Large
B31: Weight | C31: Cost | D31: Total | G31: Weight | H31: Cost | I31: Total | L31: Weight | M31: Cost | N31: Total
A32: C&H Filling Mix | B32: 0.129 | C32: =$D$26 -> 3.8943114 | D32: =B32*C32 -> 0.50236617 | F32: C&H Filling Mix | G32: 0.3 | H32: =$D$26 -> 3.8943114 | I32: =G32*H32 -> 1.1682934 | K32: C&H Filling Mix | L32: 0.6 | M32: =$D$26 -> 3.8943114 | N32: =L32*M32 -> 2.3365868
A33: Pastry | C33: ='Pastry Costing'!F34 -> 0 | D33: ='Pastry Costing'!F30 -> 0.21079469 | F33: Pastry | H33: ='Pastry Costing'!K34 -> 0 | I33: ='Pastry Costing'!F31 -> 0.3414143 | K33: Pastry | M33: ='Pastry Costing'!P34 -> 0 | N33: ='Pastry Costing'!F32 -> 0.5240744
A34: Foil | C34: ='Ingredient Cost'!$D$95 -> 0.09 | D34: =C34 -> 0.09 | F34: Foil | H34: ='Ingredient Cost'!$D$95 -> 0.09 | I34: =H34 -> 0.09 | K34: Foil | M34: ='Ingredient Cost'!$D$95 -> 0.09 | N34: =M34 -> 0.09
A35: Egg Glaze | B35: 1 | C35: ='Ingredient Cost'!$D$11 -> 0.02 | D35: =B35*C35 -> 0.02 | F35: Egg Glaze | G35: 1 | H35: ='Ingredient Cost'!$D$11 -> 0.02 | I35: =G35*H35 -> 0.02 | K35: Egg Glaze | L35: 1 | M35: ='Ingredient Cost'!$D$11 -> 0.02 | N35: =L35*M35 -> 0.02
A36: COST | D36: =SUM(D32:D33) -> 0.71316086 | F36: COST | I36: =SUM(I32:I33) -> 1.5097077 | K36: COST | N36: =SUM(N32:N33) -> 2.8606612
A38: Individual Packaged Products (excl. Labour)
A40: Small - Cooked | F40: Medium | K40: Large
B41: Weight | C41: Cost | D41: Total | G41: Weight | H41: Cost | I41: Total | L41: Weight | M41: Cost | N41: Total
A42: Ingredient Cost | B42: 1 | C42: =$D$36 -> 0.71316086 | D42: =B42*C42 -> 0.71316086 | F42: Ingredient Cost | G42: 1 | H42: =$I$36 -> 1.5097077 | I42: =G42*H42 -> 1.5097077 | K42: Ingredient Cost | L42: 1 | M42: =$N$36 -> 2.8606612 | N42: =L42*M42 -> 2.8606612
A43: Foil | B43: 1 | C43: ='Ingredient Cost'!$D$95 -> 0.09 | D43: =B43*C43 -> 0.09 | F43: Foil | G43: 1 | H43: ='Ingredient Cost'!$D$83 -> 0.07 | I43: =G43*H43 -> 0.07 | K43: Foil | L43: 1 | M43: ='Ingredient Cost'!$D$83 -> 0.07 | N43: =L43*M43 -> 0.07
A44: Packaging | B44: 1 | C44: ='Ingredient Cost'!$D$89 -> 0.06 | D44: =B44*C44 -> 0.06 | F44: Packaging | G44: 1 | H44: 0.22 | I44: =H44*G44 -> 0.22 | K44: Packaging | L44: 1 | M44: 0.3 | N44: 0.3
F45: Label | G45: 1 | H45: 0.15 | I45: 0.15 | K45: Label | L45: 1 | M45: 0.15 | N45: 0.15
A46: COST | D46: =SUM(D42:D44) -> 0.86316086 | F46: COST | I46: =SUM(I42:I45) -> 1.9497077 | K46: COST | N46: =SUM(N42:N45) -> 3.3806612
A49: Individual Packaged Products (incl. Labour) | D49: = | E49: COGS
A51: Small | F51: Medium | K51: Large
B52: Weight | C52: Cost | D52: Total | G52: Weight | H52: Cost | I52: Total | L52: Weight | M52: Cost | N52: Total
A53: Packaged Product Cost | B53: 1 | C53: =$D$46 -> 0.86316086 | D53: =B53*C53 -> 0.86316086 | F53: Packaged Product Cost | G53: 1 | H53: =$I$46 -> 1.9497077 | I53: =G53*H53 -> 1.9497077 | K53: Packaged Product Cost | L53: 1 | M53: =$N$46 -> 3.3806612 | N53: =L53*M53 -> 3.3806612
A54: Labour | B54: 60 | C54: ='Ingredient Cost'!$B$113 -> 20 | D54: =C54/B54 -> 0.33333333 | F54: Labour | G54: 48 | H54: ='Ingredient Cost'!$B$113 -> 20 | I54: =H54/G54 -> 0.41666667 | K54: Labour | L54: 32 | M54: ='Ingredient Cost'!$B$113 -> 20 | N54: =M54/L54 -> 0.625
A55: COST | D55: =SUM(D53:D54) -> 1.1964942 | F55: COST | I55: =SUM(I53:I54) -> 2.3663744 | K55: COST | N55: =SUM(N53:N54) -> 4.0056612
B57: Labour Percentage | D57: =D$54/D$53 -> 0.38617754 | G57: Labour Percentage | I57: =I$54/I$53 -> 0.21370725 | L57: Labour Percentage | N57: =N$54/N$53 -> 0.18487508
A58: CASES
A60: Small (9 per case) | F60: Medium (4 per case)
B61: Weight | C61: Cost | D61: Total | G61: Weight | H61: Cost | I61: Total
A62: Product Cost | B62: 9 | C62: =D55 -> 1.1964942 | D62: =B62*C62 -> 10.768448 | F62: Product Cost | G62: 4 | H62: =I55 -> 2.3663744 | I62: =G62*H62 -> 9.4654975
A63: Case Packaging | B63: 1 | C63: ='Ingredient Cost'!D108 -> 0.2 | D63: =B63*C63 -> 0.2 | F63: Case Packaging | G63: 1 | H63: =C63 -> 0.2 | I63: =G63*H63 -> 0.2
A64: Labour | B64: 40 | C64: =C54 -> 20 | D64: =C64/B64 -> 0.5 | F64: Labour | G64: 40 | H64: =C54 -> 20 | I64: =H64/G64 -> 0.5
A65: Box end label | B65: 1 | C65: 0.01 | D65: =B65*C65 -> 0.01 | F65: Box end label | G65: 1 | H65: 0.01 | I65: =G65*H65 -> 0.01
A66: COST | D66: =SUM(D62:D65) -> 11.478448 | F66: COST | I66: =SUM(I62:I65) -> 10.175498
A67: PER EACH | D67: =D66/9 -> 1.2753831 | F67: PER EACH | I67: =I66/4 -> 2.5438744
A69: Small (6 per case)
B70: Weight | C70: Cost | D70: Total
A71: Product Cost | B71: 6 | C71: =D55 -> 1.1964942 | D71: =B71*C71 -> 7.1789651
A72: Case Packaging | B72: 1 | C72: =C63 -> 0.2 | D72: =B72*C72 -> 0.2
A73: Labour | B73: 40 | C73: 20 | D73: =C73/B73 -> 0.5
A74: Box end label | B74: 1 | C74: 0.01 | D74: =B74*C74 -> 0.01
A75: COST | D75: =SUM(D71:D74) -> 7.8889651
A76: PER EACH | D76: =D75/6 -> 1.3148275
A78: Small (12 per case)
B79: Weight | C79: Cost | D79: Total
A80: Product Cost | B80: 12 | C80: =D55 -> 1.1964942 | D80: =B80*C80 -> 14.35793
A81: Case Packaging | B81: 1 | C81: =C63 -> 0.2 | D81: =B81*C81 -> 0.2
A82: Labour | B82: 40 | C82: 20 | D82: =C82/B82 -> 0.5
A83: Box end label | B83: 1 | C83: 0.01 | D83: =B83*C83 -> 0.01
A84: COST | D84: =SUM(D80:D83) -> 15.06793
A85: PER EACH | D85: =D84/12 -> 1.2556609

Sheet C&S Pie
A1: Grasmere Farm Manual
A2: Product Page
A3: Chicken & Stilton with Bacon Pie
A4: INGREDIENTS | B4: . All allergens in BOLD.
A16: Product | B16: Chicken & Stilton with Bacon Pie Filling
B17: Weight | C17: Cost | D17: Total
A18: Chicken | B18: 1.25 | C18: ='Ingredient Cost'!D62 -> 7.55 | D18: =B18*C18 -> 9.4375
A19: Bacon Bits | B19: 0.75 | C19: ='Ingredient Cost'!D68 -> 3.32 | D19: =B19*C19 -> 2.49
A20: Stilton | B20: 0.25 | C20: ='Ingredient Cost'!D18 -> 4.75 | D20: =B20*C20 -> 1.1875
A21: Stock & Water | B21: 1.25 | C21: 0 | D21: =B21*C21 -> 0
A22: Milk | B22: 1 | C22: ='Ingredient Cost'!D12 -> 0.74 | D22: =B22*C22 -> 0.74
A23: Sauce Mix CW 110715 | B23: 0.375 | C23: ='Ingredient Cost'!D20 -> 8.95 | D23: =B23*C23 -> 3.35625
B25: =SUM(B18:B23) -> 4.875 | D25: =SUM(D18:D23) -> 17.21125
A27: COST | D27: =D25/B25 -> 3.5305128
A29: Product | B29: Raw Chicken & Stilton with Bacon Pie Small | F29: Product | G29: Raw Chicken & Stilton with Bacon Pie Medium | K29: Product | L29: Raw Chicken & Stilton with Bacon Pie Large
B30: Weight | C30: Cost | D30: Total | G30: Weight | H30: Cost | I30: Total | L30: Weight | M30: Cost | N30: Total
A31: Filling | B31: 0.129 | C31: =D27 -> 3.5305128 | D31: =B31*C31 -> 0.45543615 | F31: Filling | G31: 0.257 | H31: =C31 -> 3.5305128 | I31: =G31*H31 -> 0.90734179 | K31: Filling | L31: 0.74 | M31: =C31 -> 3.5305128 | N31: =L31*M31 -> 2.6125795
A32: Pasty | C32: ='Pastry Costing'!F30 -> 0.21079469 | D32: =C32 -> 0.21079469 | F32: Pasty | H32: ='Pastry Costing'!F31 -> 0.3414143 | I32: =H32 -> 0.3414143 | K32: Pasty | M32: ='Pastry Costing'!F32 -> 0.5240744 | N32: =M32 -> 0.5240744
A33: Foil | B33: 1 | C33: ='Ingredient Cost'!D95 -> 0.09 | D33: =B33*C33 -> 0.09 | F33: Foil | G33: 1 | H33: ='Ingredient Cost'!D96 -> 0.12 | I33: =G33*H33 -> 0.12 | K33: Foil | L33: 1 | M33: ='Ingredient Cost'!D97 -> 0.2 | N33: =L33*M33 -> 0.2
A34: Labour | B34: 90 | C34: ='Steak Pie v2'!C53 -> 20 | D34: =C34/B34 -> 0.22222222 | F34: Labour | G34: 48 | H34: =C34 -> 20 | I34: =H34/G34 -> 0.41666667 | K34: Labour | L34: 32 | M34: =C34 -> 20 | N34: =M34/L34 -> 0.625
A37: COST | D37: =D31+D32+D33+D34 -> 0.97845307 | F37: COST | I37: =I31+I32+I33+I34 -> 1.7854228 | K37: COST | N37: =N31+N32+N33+N34 -> 3.9616539
A40: Product | B40: Raw Chicken & Stilton with Bacon Pie Small | F40: Product | G40: Raw Chicken & Stilton with Bacon Pie Medium
B41: Weight | C41: Cost | D41: Total | G41: Weight | H41: Cost | I41: Total
A42: Pie | B42: 9 | C42: =D37 -> 0.97845307 | D42: =B42*C42 -> 8.8060776 | F42: Pie | G42: 6 | H42: =I37 -> 1.7854228 | I42: =G42*H42 -> 10.712537
A43: Cooking Paper | B43: 1 | C43: ='Ingredient Cost'!D86 -> 0.12 | D43: =B43*C43 -> 0.12 | F43: Cooking Paper | G43: 1 | H43: =C43 -> 0.12 | I43: =G43*H43 -> 0.12
A44: Packaging | B44: 9 | C44: ='Ingredient Cost'!D90 -> 0.22 | D44: =B44*C44 -> 1.98 | F44: Packaging | G44: 6 | H44: 0.1 | I44: =G44*H44 -> 0.6
A45: Case | B45: 1 | C45: ='Ingredient Cost'!D108 -> 0.2 | D45: =B45*C45 -> 0.2 | F45: Case | G45: 1 | H45: =C45 -> 0.2 | I45: =G45*H45 -> 0.2
A46: Labour | B46: 75 | C46: =C34 -> 20 | D46: =C46/B46 -> 0.26666667 | F46: Labour | G46: 75 | H46: =C34 -> 20 | I46: =H46/G46 -> 0.26666667
F47: Label | G47: 6 | H47: ='Steak Pie v2'!H64 -> 0.01 | I47: =G47*H47 -> 0.06
F48: Box end label | G48: 6 | H48: 0.01 | I48: =G48*H48 -> 0.06
A51: COST | D51: =D42+D43+D44+D45+D46 -> 11.372744 | F51: COST | I51: =I42+I43+I44+I45+I46+I47+I48 -> 12.019203
A52: PER EACH | D52: =D51/9 -> 1.2636383 | F52: PER EACH | I52: =I51/6 -> 2.0032005

Sheet Pulled Pork Pie
A1: Grasmere Farm Manual
A2: Product Page
A3: Pulled Pork, Cider & Mustard Pie
A4: INGREDIENTS | B4: . All allergens in BOLD.
A16: Product | B16: Pulled Pork, Cider & Mustard Filling
B17: Weight | C17: Cost | D17: Total
A18: Pulled Pork | B18: 2.5 | C18: ='Ingredient Cost'!D64 -> 7 | D18: =B18*C18 -> 17.5
A19: Cider | B19: 0.75 | C19: ='Ingredient Cost'!D28 -> 1.15 | D19: =B19*C19 -> 0.8625
A20: Water | B20: 1.45 | C20: 0 | D20: =B20*C20 -> 0
A21: Gravey Mix | B21: 0.45 | C21: ='Ingredient Cost'!D21 -> 8.9 | D21: =B21*C21 -> 4.005
A22: Grain Mustard | B22: 0.15 | C22: ='Ingredient Cost'!D24 -> 7.65 | D22: =B22*C22 -> 1.1475
B23: =SUM(B18:B22) -> 5.3 | D23: =SUM(D18:D22) -> 23.515
A25: COST | D25: =D23/B23 -> 4.4367925
A27: Product | B27: Raw Pulled Pork, Cider & Mustard Small | F27: Product | G27: Raw Pulled Pork, Cider & Mustard Medium | K27: Product | L27: Raw Pulled Pork, Cider & Mustard Large
B28: Weight | C28: Cost | D28: Total | G28: Weight | H28: Cost | I28: Total | L28: Weight | M28: Cost | N28: Total
A29: Filling | B29: 0.129 | C29: =D25 -> 4.4367925 | D29: =B29*C29 -> 0.57234623 | F29: Filling | G29: 0.257 | H29: =C29 -> 4.4367925 | I29: =G29*H29 -> 1.1402557 | K29: Filling | L29: 0.74 | M29: =C29 -> 4.4367925 | N29: =L29*M29 -> 3.2832264
A30: Pasty | C30: ='Pastry Costing'!F30 -> 0.21079469 | D30: =C30 -> 0.21079469 | F30: Pasty | H30: ='Pastry Costing'!F31 -> 0.3414143 | I30: =H30 -> 0.3414143 | K30: Pasty | M30: ='Pastry Costing'!F32 -> 0.5240744 | N30: =M30 -> 0.5240744
A31: Foil | B31: 1 | C31: ='Ingredient Cost'!D95 -> 0.09 | D31: =B31*C31 -> 0.09 | F31: Foil | G31: 1 | H31: ='Ingredient Cost'!D96 -> 0.12 | I31: =G31*H31 -> 0.12 | K31: Foil | L31: 1 | M31: ='Ingredient Cost'!D97 -> 0.2 | N31: =L31*M31 -> 0.2
A32: Labour | B32: 90 | C32: ='Steak Pie v2'!C53 -> 20 | D32: =C32/B32 -> 0.22222222 | F32: Labour | G32: 48 | H32: =C32 -> 20 | I32: =H32/G32 -> 0.41666667 | K32: Labour | L32: 32 | M32: =C32 -> 20 | N32: =M32/L32 -> 0.625
A35: COST | D35: =D29+D30+D31+D32 -> 1.0953631 | F35: COST | I35: =I29+I30+I31+I32 -> 2.0183366 | K35: COST | N35: =N29+N30+N31+N32 -> 4.6323008
A38: Product | B38: Raw Pulled Pork, Cider & Mustard Small Case | F38: Product | G38: Raw Pulled Pork, Cider & Mustard Medium Case
B39: Weight | C39: Cost | D39: Total | G39: Weight | H39: Cost | I39: Total
A40: Pie | B40: 9 | C40: =D35 -> 1.0953631 | D40: =B40*C40 -> 9.8582682 | F40: Pie | G40: 6 | H40: =I35 -> 2.0183366 | I40: =G40*H40 -> 12.11002
A41: Cooking Paper | B41: 1 | C41: ='Ingredient Cost'!D86 -> 0.12 | D41: =B41*C41 -> 0.12 | F41: Cooking Paper | G41: 1 | H41: =C41 -> 0.12 | I41: =G41*H41 -> 0.12
A42: Packaging | B42: 9 | C42: ='Ingredient Cost'!D90 -> 0.22 | D42: =B42*C42 -> 1.98 | F42: Packaging | G42: 6 | H42: 0.1 | I42: =G42*H42 -> 0.6
A43: Case | B43: 1 | C43: ='Ingredient Cost'!D108 -> 0.2 | D43: =B43*C43 -> 0.2 | F43: Case | G43: 1 | H43: =C43 -> 0.2 | I43: =G43*H43 -> 0.2
A44: Labour | B44: 75 | C44: =C32 -> 20 | D44: =C44/B44 -> 0.26666667 | F44: Labour | G44: 75 | H44: =C32 -> 20 | I44: =H44/G44 -> 0.26666667
F45: Label | G45: 6 | H45: ='Steak Pie v2'!H64 -> 0.01 | I45: =G45*H45 -> 0.06
F46: Box end label | G46: 6 | H46: 0.01 | I46: =G46*H46 -> 0.06
A49: COST | D49: =D40+D41+D42+D43+D44 -> 12.424935 | F49: COST | I49: =I40+I41+I42+I43+I44+I45+I46 -> 13.416686
A50: PER EACH | D50: =D49/9 -> 1.3805483 | F50: PER EACH | I50: =I49/6 -> 2.2361144

Sheet Ham Hock Pie
A1: Grasmere Farm Manual
A2: Product Page
A3: Ham Hock, Cider & Tarragon
A4: INGREDIENTS | B4: . All allergens in BOLD.
A16: Product | B16: Ham Hock, Cider & Tarragon Filling
B17: Weight | C17: Cost | D17: Total
A18: Ham Hock | B18: 2 | C18: ='Ingredient Cost'!D58 -> 6 | D18: =B18*C18 -> 12
A19: Milk | B19: 1 | C19: ='Ingredient Cost'!D12 -> 0.74 | D19: =B19*C19 -> 0.74
A20: Gravy Mix CW 111020 | B20: 0.375 | C20: ='Ingredient Cost'!D21 -> 8.9 | D20: =B20*C20 -> 3.3375
A21: Dried Tarragon | B21: 0.005 | C21: ='Ingredient Cost'!D22 -> 13 | D21: =B21*C21 -> 0.065
A22: Water | B22: 0.25 | C22: 0 | D22: =B22*C22 -> 0
A23: Cider | B23: 1 | C23: ='Ingredient Cost'!D28 -> 1.15 | D23: =B23*C23 -> 1.15
B25: =SUM(B18:B23) -> 4.63 | D25: =SUM(D18:D23) -> 17.2925
A27: COST | D27: =D25/B25 -> 3.7348812
A29: Product | B29: Raw Ham Hock, Cider & Tarragon Pie Small | F29: Product | G29: Raw Ham Hock, Cider & Tarragon Pie Medium | K29: Product | L29: Raw Ham Hock, Cider & Tarragon Pie Large
B30: Weight | C30: Cost | D30: Total | G30: Weight | H30: Cost | I30: Total | L30: Weight | M30: Cost | N30: Total
A31: Filling | B31: 0.129 | C31: =D27 -> 3.7348812 | D31: =B31*C31 -> 0.48179968 | F31: Filling | G31: 0.257 | H31: =C31 -> 3.7348812 | I31: =G31*H31 -> 0.95986447 | K31: Filling | L31: 0.74 | M31: =C31 -> 3.7348812 | N31: =L31*M31 -> 2.7638121
A32: Pasty | C32: ='Pastry Costing'!F30 -> 0.21079469 | D32: =C32 -> 0.21079469 | F32: Pasty | H32: ='Pastry Costing'!F31 -> 0.3414143 | I32: =H32 -> 0.3414143 | K32: Pasty | M32: ='Pastry Costing'!F32 -> 0.5240744 | N32: =M32 -> 0.5240744
A33: Foil | B33: 1 | C33: ='Ingredient Cost'!D95 -> 0.09 | D33: =B33*C33 -> 0.09 | F33: Foil | G33: 1 | H33: ='Ingredient Cost'!D96 -> 0.12 | I33: =G33*H33 -> 0.12 | K33: Foil | L33: 1 | M33: ='Ingredient Cost'!D97 -> 0.2 | N33: =L33*M33 -> 0.2
A34: Labour | B34: 90 | C34: 15 | D34: =C34/B34 -> 0.16666667 | F34: Labour | G34: 48 | H34: =C34 -> 15 | I34: =H34/G34 -> 0.3125 | K34: Labour | L34: 32 | M34: 15 | N34: =M34/L34 -> 0.46875
A37: COST | D37: =D31+D32+D33+D34 -> 0.94926103 | F37: COST | I37: =I31+I32+I33+I34 -> 1.7337788 | K37: COST | N37: =N31+N32+N33+N34 -> 3.9566365
A40: Product | B40: Cooked Ham Hock, Cider & Tarragon Pie Small Case | F40: Product | G40: Cooked Ham Hock, Cider & Tarragon Pie Medium Case
B41: Weight | C41: Cost | D41: Total | G41: Weight | H41: Cost | I41: Total
A42: Pie | B42: 9 | C42: =D37 -> 0.94926103 | D42: =B42*C42 -> 8.5433493 | F42: Pie | G42: 6 | H42: =I37 -> 1.7337788 | I42: =G42*H42 -> 10.402673
A43: Cooking Paper | B43: 1 | C43: ='Ingredient Cost'!D86 -> 0.12 | D43: =B43*C43 -> 0.12 | F43: Cooking Paper | G43: 1 | H43: =C43 -> 0.12 | I43: =G43*H43 -> 0.12
A44: Packaging | B44: 9 | C44: ='Ingredient Cost'!D90 -> 0.22 | D44: =B44*C44 -> 1.98 | F44: Packaging | G44: 6 | H44: 0.1 | I44: =G44*H44 -> 0.6
A45: Case | B45: 1 | C45: ='Ingredient Cost'!D108 -> 0.2 | D45: =B45*C45 -> 0.2 | F45: Case | G45: 1 | H45: =C45 -> 0.2 | I45: =G45*H45 -> 0.2
A46: Labour | B46: 75 | C46: 15 | D46: =C46/B46 -> 0.2 | F46: Labour | G46: 75 | H46: 15 | I46: =H46/G46*6 -> 1.2
F47: Label | G47: 6 | H47: 0.1 | I47: =G47*H47 -> 0.6
F48: Box end label | G48: 6 | H48: 0.01 | I48: =G48*H48 -> 0.06
A51: COST | D51: =D42+D43+D44+D45+D46 -> 11.043349 | F51: COST | I51: =I42+I43+I44+I45+I46+I47+I48 -> 13.182673
A52: PER EACH | D52: =D51/9 -> 1.2270388 | F52: PER EACH | I52: =I51/6 -> 2.1971121

Sheet Purses
A1: Grasmere Farm Manual
A2: Product Page
A3: Pork Cider & Mustard Purse | F3: Lamb & Mint Purse | K3: Steak & Ale Purse | P3: Chicken & Ham Purse
A5: Product | B5: Pork Cider & Mustard Filling | F5: Product | G5: Lamb & Mint Purse Filling | K5: Product | L5: Steak & Ale Purse Filling | P5: Product | Q5: Steak & Ale Purse Filling
B6: Weight | C6: Cost | D6: Total | G6: Weight | H6: Cost | I6: Total | L6: Weight | M6: Cost | N6: Total | Q6: Weight | R6: Cost | S6: Total
A7: Pulled Pork | B7: 2.5 | C7: ='Ingredient Cost'!D64 -> 7 | D7: =B7*C7 -> 17.5 | F7: Cooked Lamb | G7: 2.5 | H7: ='Ingredient Cost'!D60 -> 11.71 | I7: =G7*H7 -> 29.275 | K7: Cooked Beef | L7: 2.5 | M7: ='Ingredient Cost'!D59 -> 8.5 | N7: =L7*M7 -> 21.25 | P7: Cooked Chicken | Q7: 1.2 | R7: ='Ingredient Cost'!D62 -> 7.55 | S7: =Q7*R7 -> 9.06
A8: Grain Mustard | B8: 0.15 | C8: ='Ingredient Cost'!D68 -> 3.32 | D8: =B8*C8 -> 0.498 | F8: Water/Stock | G8: 1.4 | H8: ='Ingredient Cost'!I68 -> 0 | I8: =G8*H8 -> 0 | K8: Ale | L8: 0.8 | M8: ='Ingredient Cost'!D29 -> 1.38 | N8: =L8*M8 -> 1.104 | P8: Cooked Gammon | Q8: 0.75 | R8: ='Ingredient Cost'!D65 -> 25 | S8: =Q8*R8 -> 18.75
A9: Cider | B9: 0.75 | C9: ='Ingredient Cost'!D18 -> 4.75 | D9: =B9*C9 -> 3.5625 | F9: Mint Sauce | G9: 0.2 | H9: ='Ingredient Cost'!D44 -> 1.79 | I9: =G9*H9 -> 0.358 | K9: Water Stock | L9: 1.4 | M9: ='Ingredient Cost'!N18 -> 0 | N9: =L9*M9 -> 0 | P9: Stock & Milk | Q9: 2.25 | R9: ='Ingredient Cost'!D12 -> 0.74 | S9: =Q9*R9 -> 1.665
A10: Stock & Water | B10: 1.45 | C10: 0 | D10: =B10*C10 -> 0 | F10: Gravy Mix CW111020 | G10: 0.4 | H10: ='Ingredient Cost'!D21 -> 8.9 | I10: =G10*H10 -> 3.56 | K10: Gravy Mix CW111020 | L10: 0.4 | M10: ='Ingredient Cost'!D21 -> 8.9 | N10: =L10*M10 -> 3.56 | P10: Gravy Mix CW110715 | Q10: 0.325 | R10: ='Ingredient Cost'!D20 -> 8.95 | S10: =Q10*R10 -> 2.90875
A11: Gravy Mix | B11: 0.45 | C11: ='Ingredient Cost'!D21 -> 8.9 | D11: =B11*C11 -> 4.005
B14: =SUM(B7:B12) -> 5.3 | D14: =SUM(D7:D12) -> 25.5655 | G14: =SUM(G7:G12) -> 4.5 | I14: =SUM(I7:I12) -> 33.193 | L14: =SUM(L7:L12) -> 5.1 | N14: =SUM(N7:N12) -> 25.914 | Q14: =SUM(Q7:Q12) -> 4.525 | S14: =SUM(S7:S12) -> 32.38375
A16: COST | D16: =D14/B14 -> 4.8236792 | F16: COST | I16: =I14/G14 -> 7.3762222 | K16: COST | N16: =N14/L14 -> 5.0811765 | P16: COST | S16: =S14/Q14 -> 7.1566298
A18: Product | B18: Pork, Cider & Mustard Purse | F18: Product | G18: Lamb & Mint Purse | K18: Product | L18: Steak & Ale Purse | P18: Product | Q18: Steak & Ale Purse
B19: Weight | C19: Cost | D19: Total | G19: Weight | H19: Cost | I19: Total | L19: Weight | M19: Cost | N19: Total | Q19: Weight | R19: Cost | S19: Total
A20: Pastry Base | B20: 0.135 | C20: ='Ingredient Cost'!D9 -> 1.94 | D20: =B20*C20 -> 0.2619 | F20: Pastry Base | G20: 0.135 | H20: =C20 -> 1.94 | I20: =G20*H20 -> 0.2619 | K20: Pastry Base | L20: 0.135 | M20: =H20 -> 1.94 | N20: =L20*M20 -> 0.2619 | P20: Pastry Base | Q20: 0.135 | R20: =M20 -> 1.94 | S20: =Q20*R20 -> 0.2619
A21: Filling | B21: 0.125 | C21: =D16 -> 4.8236792 | D21: =B21*C21 -> 0.60295991 | F21: Filling | G21: 0.125 | H21: =I16 -> 7.3762222 | I21: =G21*H21 -> 0.92202778 | K21: Filling | L21: 0.125 | M21: =N16 -> 5.0811765 | N21: =L21*M21 -> 0.63514706 | P21: Filling | Q21: 0.125 | R21: =S16 -> 7.1566298 | S21: =Q21*R21 -> 0.89457873
A22: Puff Lid/Symbol | B22: 0.006 | C22: =C20 -> 1.94 | D22: =B22*C22 -> 0.01164 | F22: Puff Lid/Symbol | G22: 0.006 | H22: =H20 -> 1.94 | I22: =G22*H22 -> 0.01164 | K22: Puff Lid/Symbol | L22: 0.006 | M22: =M20 -> 1.94 | N22: =L22*M22 -> 0.01164 | P22: Puff Lid/Symbol | Q22: 0.006 | R22: =R20 -> 1.94 | S22: =Q22*R22 -> 0.01164
A23: Labour | B23: 72 | C23: ='Steak Pie v2'!C53 -> 20 | D23: =C23/B23 -> 0.27777778 | F23: Labour | G23: 72 | H23: ='Steak Pie v2'!H53 -> 20 | I23: =H23/G23 -> 0.27777778 | K23: Labour | L23: 72 | M23: ='Steak Pie v2'!M53 -> 20 | N23: =M23/L23 -> 0.27777778 | P23: Labour | Q23: 72 | R23: ='Steak Pie v2'!R53 -> 0 | S23: =R23/Q23 -> 0
A26: COST | D26: =D20+D21+D22+D23 -> 1.1542777 | F26: COST | I26: =I20+I21+I22+I23 -> 1.4733456 | K26: COST | N26: =N20+N21+N22+N23 -> 1.1864648 | P26: COST | S26: =S20+S21+S22+S23 -> 1.1681187
A29: 1.75 | B29: =(A29-D26)/A29 -> 0.34041275 | F29: 2.35 | G29: =(F29-I26)/F29 -> 0.37304444 | K29: 1.85 | L29: =(K29-N26)/K29 -> 0.35866766 | P29: 1.85 | Q29: =(P29-S26)/P29 -> 0.36858447
P30: =(180*S26) -> 210.26137 | Q30: =(180*P29) -> 333 | S30: =(Q30-P30)/Q30 -> 0.36858447
Q31: 219.21
